Workbook

Sheet MONTHLY

Sheet Monitor CS Attempt
A1: Tracking | B1: Customer Name | C1: Contact | D1: Address | E1: Items | F1: COD Amount | G1: Attempt Reason | H1: Date | I1: 📜 Courier Timeline (Last 4) | J1: 🛒 Shopify Notes | K1: 📋 CS Status | L1: 📝 CS Resolution Note | M1: ⚡ Action | N1: 📲 Escalate
A2: 24120050021639 | B2: Manzoor Hussain | C2: 3143944980 | D2: Gali Tawasuli , Alamdar Road, Momin abad, Quetta Quetta | E2: Tipping Crew - L / Black (x1), Tipping Crew - L / White (x1) | F2: 2749 | G2: Attempted | H2: 46067.835 | I2: • Merchant Request For Re-Attempt • Delivery Under Review • Attempt Made: RFD(REFUSED TO RECEIVE) • Enroute for Delivery | J2: Order has been shipped via PostEx with Tracking 24120050021639. confirm not ans | N2: =HYPERLINK("https://api.whatsapp.com/send?text=" & ENCODEURL("🚨 *PostEx Attempt Follow-up*" & CHAR(10) & "📦 Tracking: " & A2 & CHAR(10) & "❌ Issue: " & G2 & CHAR(10) & "💬 CS Update: " & L2), "📲 Send to Courier") -> 📲 Send to Courier
A3: 23120050021855 | B3: Aimal Khan | C3: 3394849051 | D3: PAF Base Shahrah E Faisal Karachi Karachi | E3: Multi ref PUM-A - 2XL / White (x1), Multi ref PUM-A - 2XL / Black (x1) | F3: 3099 | G3: Attempted | H3: 46070.656 | I3: • Attempt Made: CNA(CUSTOMER NOT AVAILABLE) • Enroute for Delivery • Attempt Made: CNA(CUSTOMER NOT AVAILABLE) • Enroute for Delivery | J3: Order has been shipped via PostEx with Tracking 23120050021855. ok | N3: =HYPERLINK("https://api.whatsapp.com/send?text=" & ENCODEURL("🚨 *PostEx Attempt Follow-up*" & CHAR(10) & "📦 Tracking: " & A3 & CHAR(10) & "❌ Issue: " & G3 & CHAR(10) & "💬 CS Update: " & L3), "📲 Send to Courier") -> 📲 Send to Courier
A4: 27120050021727 | B4: Asim Risz | C4: 3245751049 | D4: Moscow Plaza Subway Building 3rd Floor Office No 6 Blue Area Islamabad Islamabad | E4: Multi ref PUM-A - M / White (x1), Multi ref PUM-A - M / Black (x1) | F4: 3099 | G4: Attempted | H4: 46066.564 | I4: • Merchant Request For Re-Attempt • Delivery Under Review • Attempt Made: CNA(CUSTOMER NOT AVAILABLE) • Enroute for Delivery | J4: Order has been shipped via PostEx with Tracking 27120050021727. rider na rabta nahi kiya | N4: =HYPERLINK("https://api.whatsapp.com/send?text=" & ENCODEURL("🚨 *PostEx Attempt Follow-up*" & CHAR(10) & "📦 Tracking: " & A4 & CHAR(10) & "❌ Issue: " & G4 & CHAR(10) & "💬 CS Update: " & L4), "📲 Send to Courier") -> 📲 Send to Courier
A5: 26120050021847 | B5: Shahrooz Wali | C5: 3425169661 | D5: Aga Khan University Karachi, University Center Building Karachi | E5: Multi ref PUM-A - M / White (x1), Multi ref PUM-A - M / Black (x1) | F5: 3099 | G5: Attempted | H5: 46070.656 | I5: • Attempt Made: CNA(CUSTOMER NOT AVAILABLE) • Enroute for Delivery • Attempt Made: CNA(CUSTOMER NOT AVAILABLE) • Enroute for Delivery | J5: Order has been shipped via PostEx with Tracking 26120050021847. confrm | N5: =HYPERLINK("https://api.whatsapp.com/send?text=" & ENCODEURL("🚨 *PostEx Attempt Follow-up*" & CHAR(10) & "📦 Tracking: " & A5 & CHAR(10) & "❌ Issue: " & G5 & CHAR(10) & "💬 CS Update: " & L5), "📲 Send to Courier") -> 📲 Send to Courier
A6: 22120050021869 | B6: Abu Bakar | C6: 3236551086 | D6: Nadeem Traders Shorkot cantt | E6: Tipping Crew - M / Black (x1), Tipping Crew - M / White (x1) | F6: 2749 | G6: Attempted | H6: 46070.656 | I6: • Merchant Request For Re-Attempt • Delivery Under Review • Attempt Made: OPN(CONSIGNEE WANTS TO OPEN PARCEL) • Enroute for Delivery | J6: Order has been shipped via PostEx with Tracking 22120050021869. confirm consignee want open parcel | N6: =HYPERLINK("https://api.whatsapp.com/send?text=" & ENCODEURL("🚨 *PostEx Attempt Follow-up*" & CHAR(10) & "📦 Tracking: " & A6 & CHAR(10) & "❌ Issue: " & G6 & CHAR(10) & "💬 CS Update: " & L6), "📲 Send to Courier") -> 📲 Send to Courier
A7: 22120050021862 | B7: Atif Rafiq Rafiq Rafiq | C7: 3224142431 | D7: Paradox London office#708 7th floor Haly tower DHA phase 2 Lahore Lahore | E7: ADI Multi Ref Stripes - XL / White (x1), ADI Multi Ref Stripes - XL / Black (x1) | F7: 3348 | G7: Attempted | H7: 46067.666 | I7: • Attempt Made: CNA(CUSTOMER NOT AVAILABLE) • Enroute for Delivery • Attempt Made: HCR(HOLD ON CONSIGNEE REQUEST) • Enroute for Delivery | J7: Order has been shipped via PostEx with Tracking 22120050021862. confirm | N7: =HYPERLINK("https://api.whatsapp.com/send?text=" & ENCODEURL("🚨 *PostEx Attempt Follow-up*" & CHAR(10) & "📦 Tracking: " & A7 & CHAR(10) & "❌ Issue: " & G7 & CHAR(10) & "💬 CS Update: " & L7), "📲 Send to Courier") -> 📲 Send to Courier
A8: 22120050021879 | B8: Farhan Saeed | C8: 3212447691 | D8: Rio center building saddar karachi flat no 216 2nd floor near attrium mall Karachi | E8: A | X Embroidery LOGO - XL / Black (x1), A | X Embroidery LOGO - XL / White (x1), A | X Embroidery LOGO - XL / Pista (x1) | F8: 4599 | G8: Attempted | H8: 46070.656 | I8: • Attempt Made: CNA(CUSTOMER NOT AVAILABLE) • Enroute for Delivery • Waiting for Delivery • Arrived at Transit Hub KHI | J8: Order has been shipped via PostEx with Tracking 22120050021879. open to allow | N8: =HYPERLINK("https://api.whatsapp.com/send?text=" & ENCODEURL("🚨 *PostEx Attempt Follow-up*" & CHAR(10) & "📦 Tracking: " & A8 & CHAR(10) & "❌ Issue: " & G8 & CHAR(10) & "💬 CS Update: " & L8), "📲 Send to Courier") -> 📲 Send to Courier
A9: 25120050021888 | B9: Muhammad RAMZAN | C9: 3004031405 | D9: Fauji Fresh n Freeze pvt limited 16km Pakptan road,Sahiwal SAHIWAL | E9: Multi ref PUM-A - L / White (x1), Multi ref PUM-A - L / Black (x1) | F9: 3348 | G9: Attempted | H9: 46070.656 | I9: • Attempt Made: CNA(CUSTOMER NOT AVAILABLE) • Enroute for Delivery • Waiting for Delivery • Arrived at Transit Hub SWL | J9: Order has been shipped via PostEx with Tracking 25120050021888. confirm | N9: =HYPERLINK("https://api.whatsapp.com/send?text=" & ENCODEURL("🚨 *PostEx Attempt Follow-up*" & CHAR(10) & "📦 Tracking: " & A9 & CHAR(10) & "❌ Issue: " & G9 & CHAR(10) & "💬 CS Update: " & L9), "📲 Send to Courier") -> 📲 Send to Courier

Sheet Payment Updates
A1: 🔑 MASTER KEY: | B1: Match by Tracking Number
A2: Order ID | B2: Tracking Number | C2: Type (D/R) | D2: COD Amount | E2: Charges | F2: Ref | G2: Date | H2: Courier Name | I2: Balance | J2: Status | K2: Recommendation | L2: Net Payout | M2: Comments | N2: Charges Trick | O2: 4% TAX ADD ON | P2: FINAL CHARGES | Q2: value paste(recheck)
A3: TR31268 | B3: 24120050023622 | C3: D | D3: 3149 | E3: 254.95 | F3: CPR-RAGFP443199 | G3: 46129 | H3: PostEx | I3: 3149 | J3: ✅ Done | K3: ✅ Full Payment | L3: 2894.05 | N3: {=XLOOKUP($B3, XLOOKUP("Tracking Number", Orders!$1:$1, Orders!$A:$AAA), XLOOKUP("Courier Fee", Orders!$1:$1, Orders!$A:$AAA), "Not Found")} -> 254.95 | O3: =E3*4% -> 10.198 | P3: =SUM(N3:O3) -> 265.148
A4: TR31249 | B4: 25120050023598 | C4: D | D4: 4998 | E4: 578.83 | F4: CPR-RAGFP443199 | G4: 46129 | H4: PostEx | I4: 4998 | J4: ✅ Done | K4: ✅ Full Payment | L4: 4419.17 | N4: {=XLOOKUP($B4, XLOOKUP("Tracking Number", Orders!$1:$1, Orders!$A:$AAA), XLOOKUP("Courier Fee", Orders!$1:$1, Orders!$A:$AAA), "Not Found")} -> 578.83 | O4: =E4*4% -> 23.1532 | P4: =SUM(N4:O4) -> 601.9832
A5: TR31229 | B5: 24120050023592 | C5: D | D5: 6299 | E5: 518.01 | F5: CPR-RAGFP443199 | G5: 46129 | H5: PostEx | I5: 6299 | J5: ✅ Done | K5: ✅ Full Payment | L5: 5780.99 | N5: {=XLOOKUP($B5, XLOOKUP("Tracking Number", Orders!$1:$1, Orders!$A:$AAA), XLOOKUP("Courier Fee", Orders!$1:$1, Orders!$A:$AAA), "Not Found")} -> 518.01 | O5: =E5*4% -> 20.7204 | P5: =SUM(N5:O5) -> 538.7304
A6: TR31227 | B6: 24120050023593 | C6: D | D6: 4997 | E6: 465.93 | F6: CPR-RAGFP443199 | G6: 46129 | H6: PostEx | I6: 4997 | J6: ✅ Done | K6: ✅ Full Payment | L6: 4531.07 | N6: {=XLOOKUP($B6, XLOOKUP("Tracking Number", Orders!$1:$1, Orders!$A:$AAA), XLOOKUP("Courier Fee", Orders!$1:$1, Orders!$A:$AAA), "Not Found")} -> 465.93 | O6: =E6*4% -> 18.6372 | P6: =SUM(N6:O6) -> 484.5672
A7: TR31223 | B7: 26120050023565 | C7: D | D7: 2249 | E7: 218.95 | F7: CPR-RAGFP443199 | G7: 46129 | H7: PostEx | I7: 2249 | J7: ✅ Done | K7: ✅ Full Payment | L7: 2030.05 | N7: {=XLOOKUP($B7, XLOOKUP("Tracking Number", Orders!$1:$1, Orders!$A:$AAA), XLOOKUP("Courier Fee", Orders!$1:$1, Orders!$A:$AAA), "Not Found")} -> 218.95 | O7: =E7*4% -> 8.758 | P7: =SUM(N7:O7) -> 227.708
A8: TR31220 | B8: 27120050023569 | C8: D | D8: 3397 | E8: 264.87 | F8: CPR-RAGFP443199 | G8: 46129 | H8: PostEx | I8: 3397 | J8: ✅ Done | K8: ✅ Full Payment | L8: 3132.13 | N8: {=XLOOKUP($B8, XLOOKUP("Tracking Number", Orders!$1:$1, Orders!$A:$AAA), XLOOKUP("Courier Fee", Orders!$1:$1, Orders!$A:$AAA), "Not Found")} -> 264.87 | O8: =E8*4% -> 10.5948 | P8: =SUM(N8:O8) -> 275.4648
A9: TR31219 | B9: 26120050023566 | C9: D | D9: 1949 | E9: 319.82 | F9: CPR-RAGFP443199 | G9: 46129 | H9: PostEx | I9: 1949 | J9: ✅ Done | K9: ✅ Full Payment | L9: 1629.18 | N9: {=XLOOKUP($B9, XLOOKUP("Tracking Number", Orders!$1:$1, Orders!$A:$AAA), XLOOKUP("Courier Fee", Orders!$1:$1, Orders!$A:$AAA), "Not Found")} -> 319.82 | O9: =E9*4% -> 12.7928 | P9: =SUM(N9:O9) -> 332.6128
A10: TR31217 | B10: 24120050023567 | C10: D | D10: 1949 | E10: 206.95 | F10: CPR-RAGFP443199 | G10: 46129 | H10: PostEx | I10: 1949 | J10: ✅ Done | K10: ✅ Full Payment | L10: 1742.05 | N10: {=XLOOKUP($B10, XLOOKUP("Tracking Number", Orders!$1:$1, Orders!$A:$AAA), XLOOKUP("Courier Fee", Orders!$1:$1, Orders!$A:$AAA), "Not Found")} -> 206.95 | O10: =E10*4% -> 8.278 | P10: =SUM(N10:O10) -> 215.228
A11: TR31213 | B11: 25120050023570 | C11: D | D11: 2098 | E11: 325.78 | F11: CPR-RAGFP443199 | G11: 46129 | H11: PostEx | I11: 2098 | J11: ✅ Done | K11: ✅ Full Payment | L11: 1772.22 | N11: {=XLOOKUP($B11, XLOOKUP("Tracking Number", Orders!$1:$1, Orders!$A:$AAA), XLOOKUP("Courier Fee", Orders!$1:$1, Orders!$A:$AAA), "Not Found")} -> 325.78 | O11: =E11*4% -> 13.0312 | P11: =SUM(N11:O11) -> 338.8112
A12: TR31204 | B12: 23120050023579 | C12: D | D12: 2049 | E12: 210.95 | F12: CPR-RAGFP443199 | G12: 46129 | H12: PostEx | I12: 2049 | J12: ✅ Done | K12: ✅ Full Payment | L12: 1838.05 | N12: {=XLOOKUP($B12, XLOOKUP("Tracking Number", Orders!$1:$1, Orders!$A:$AAA), XLOOKUP("Courier Fee", Orders!$1:$1, Orders!$A:$AAA), "Not Found")} -> 210.95 | O12: =E12*4% -> 8.438 | P12: =SUM(N12:O12) -> 219.388
A13: TR31201 | B13: 24120050023580 | C13: D | D13: 2999 | E13: 377.94 | F13: CPR-RAGFP443199 | G13: 46129 | H13: PostEx | I13: 2999 | J13: ✅ Done | K13: ✅ Full Payment | L13: 2621.06 | N13: {=XLOOKUP($B13, XLOOKUP("Tracking Number", Orders!$1:$1, Orders!$A:$AAA), XLOOKUP("Courier Fee", Orders!$1:$1, Orders!$A:$AAA), "Not Found")} -> 377.94 | O13: =E13*4% -> 15.1176 | P13: =SUM(N13:O13) -> 393.0576
A14: TR31198 | B14: 21120050023523 | C14: D | D14: 2099 | E14: 341.94 | F14: CPR-RAGFP443199 | G14: 46129 | H14: PostEx | I14: 2099 | J14: ✅ Done | K14: ✅ Full Payment | L14: 1757.06 | N14: {=XLOOKUP($B14, XLOOKUP("Tracking Number", Orders!$1:$1, Orders!$A:$AAA), XLOOKUP("Courier Fee", Orders!$1:$1, Orders!$A:$AAA), "Not Found")} -> 341.94 | O14: =E14*4% -> 13.6776 | P14: =SUM(N14:O14) -> 355.6176
... A103: TR29985 | B103: 23120050023015 | C103: R | D103: 0 | E103: 235.71 | F103: CPR-RAGFP443199 | G103: 46129 | H103: PostEx | I103: 249 | J103: ✅ Done | K103: Return Fee Recorded | L103: -235.71 | N103: {=XLOOKUP($B103, XLOOKUP("Tracking Number", Orders!$1:$1, Orders!$A:$AAA), XLOOKUP("Courier Fee", Orders!$1:$1, Orders!$A:$AAA), "Not Found")} -> 235.71 | O103: =E103*4% -> 9.4284 | P103: =SUM(N103:O103) -> 245.1384
A104: TR31248 | B104: 28120050023589 | C104: D | D104: 0 | E104: 257.98 | F104: CPR-RAGFP443199 | G104: 46129 | H104: PostEx | I104: 2520 | J104: ❌ API Error | K104: Request failed for https://041839-3.myshopify.com returned code 422. Truncated server response: {"errors":{"amount":["must be greater than zero for capture transactions"]}} (use muteHttpExceptions option to examine full response) | N104: {=XLOOKUP($B104, XLOOKUP("Tracking Number", Orders!$1:$1, Orders!$A:$AAA), XLOOKUP("Courier Fee", Orders!$1:$1, Orders!$A:$AAA), "Not Found")} | O104: =E104*4% -> 10.3192 | P104: =SUM(N104:O104) -> 10.3192
A105: TR31246 | B105: 25120050023590 | C105: D | D105: 0 | E105: 241.86 | F105: CPR-RAGFP443199 | G105: 46129 | H105: PostEx | I105: 1665 | J105: ❌ API Error | K105: Request failed for https://041839-3.myshopify.com returned code 422. Truncated server response: {"errors":{"amount":["must be greater than zero for capture transactions"]}} (use muteHttpExceptions option to examine full response) | N105: {=XLOOKUP($B105, XLOOKUP("Tracking Number", Orders!$1:$1, Orders!$A:$AAA), XLOOKUP("Courier Fee", Orders!$1:$1, Orders!$A:$AAA), "Not Found")} | O105: =E105*4% -> 9.6744 | P105: =SUM(N105:O105) -> 9.6744
A106: TR31226 | B106: 23120050023577 | C106: D | D106: 0 | E106: 257.98 | F106: CPR-RAGFP443199 | G106: 46129 | H106: PostEx | I106: 3399 | J106: ❌ API Error | K106: Request failed for https://041839-3.myshopify.com returned code 422. Truncated server response: {"errors":{"amount":["must be greater than zero for capture transactions"]}} (use muteHttpExceptions option to examine full response) | N106: {=XLOOKUP($B106, XLOOKUP("Tracking Number", Orders!$1:$1, Orders!$A:$AAA), XLOOKUP("Courier Fee", Orders!$1:$1, Orders!$A:$AAA), "Not Found")} | O106: =E106*4% -> 10.3192 | P106: =SUM(N106:O106) -> 10.3192
A107: TR31202 | B107: 25120050023541 | C107: D | D107: 0 | E107: 241.86 | F107: CPR-RAGFP443199 | G107: 46129 | H107: PostEx | I107: 1499 | J107: ❌ API Error | K107: Request failed for https://041839-3.myshopify.com returned code 422. Truncated server response: {"errors":{"amount":["must be greater than zero for capture transactions"]}} (use muteHttpExceptions option to examine full response) | N107: {=XLOOKUP($B107, XLOOKUP("Tracking Number", Orders!$1:$1, Orders!$A:$AAA), XLOOKUP("Courier Fee", Orders!$1:$1, Orders!$A:$AAA), "Not Found")} | O107: =E107*4% -> 9.6744 | P107: =SUM(N107:O107) -> 9.6744
A108: TR31005 | B108: 24120050023415 | C108: D | D108: 0 | E108: 257.98 | F108: CPR-RAGFP443199 | G108: 46129 | H108: PostEx | I108: 3397 | J108: ❌ API Error | K108: Request failed for https://041839-3.myshopify.com returned code 422. Truncated server response: {"errors":{"amount":["must be greater than zero for capture transactions"]}} (use muteHttpExceptions option to examine full response) | N108: {=XLOOKUP($B108, XLOOKUP("Tracking Number", Orders!$1:$1, Orders!$A:$AAA), XLOOKUP("Courier Fee", Orders!$1:$1, Orders!$A:$AAA), "Not Found")} | O108: =E108*4% -> 10.3192 | P108: =SUM(N108:O108) -> 10.3192
A109: TR31203 | B109: 27120050023547 | C109: D | D109: 0 | E109: 128.99 | F109: CPR-RAGFP443199 | G109: 46129 | H109: PostEx | J109: 🛑 Skipped | K109: Already Paid | N109: {=XLOOKUP($B109, XLOOKUP("Tracking Number", Orders!$1:$1, Orders!$A:$AAA), XLOOKUP("Courier Fee", Orders!$1:$1, Orders!$A:$AAA), "Not Found")} | O109: =E109*4% -> 5.1596 | P109: =SUM(N109:O109) -> 5.1596
N110: {=XLOOKUP($B110, XLOOKUP("Tracking Number", Orders!$1:$1, Orders!$A:$AAA), XLOOKUP("Courier Fee", Orders!$1:$1, Orders!$A:$AAA), "Not Found")} -> Not Found | O110: =E110*4% -> 0 | P110: =SUM(N110:O110) -> 0
N111: {=XLOOKUP($B111, XLOOKUP("Tracking Number", Orders!$1:$1, Orders!$A:$AAA), XLOOKUP("Courier Fee", Orders!$1:$1, Orders!$A:$AAA), "Not Found")} -> Not Found | O111: =E111*4% -> 0 | P111: =SUM(N111:O111) -> 0
N112: {=XLOOKUP($B112, XLOOKUP("Tracking Number", Orders!$1:$1, Orders!$A:$AAA), XLOOKUP("Courier Fee", Orders!$1:$1, Orders!$A:$AAA), "Not Found")} -> Not Found | O112: =E112*4% -> 0 | P112: =SUM(N112:O112) -> 0
N113: {=XLOOKUP($B113, XLOOKUP("Tracking Number", Orders!$1:$1, Orders!$A:$AAA), XLOOKUP("Courier Fee", Orders!$1:$1, Orders!$A:$AAA), "Not Found")} -> Not Found | O113: =E113*4% -> 0 | P113: =SUM(N113:O113) -> 0
N114: {=XLOOKUP($B114, XLOOKUP("Tracking Number", Orders!$1:$1, Orders!$A:$AAA), XLOOKUP("Courier Fee", Orders!$1:$1, Orders!$A:$AAA), "Not Found")} -> Not Found | O114: =E114*4% -> 0 | P114: =SUM(N114:O114) -> 0
N115: {=XLOOKUP($B115, XLOOKUP("Tracking Number", Orders!$1:$1, Orders!$A:$AAA), XLOOKUP("Courier Fee", Orders!$1:$1, Orders!$A:$AAA), "Not Found")} -> Not Found | O115: =E115*4% -> 0 | P115: =SUM(N115:O115) -> 0
N116: {=XLOOKUP($B116, XLOOKUP("Tracking Number", Orders!$1:$1, Orders!$A:$AAA), XLOOKUP("Courier Fee", Orders!$1:$1, Orders!$A:$AAA), "Not Found")} -> Not Found | O116: =E116*4% -> 0 | P116: =SUM(N116:O116) -> 0
N117: {=XLOOKUP($B117, XLOOKUP("Tracking Number", Orders!$1:$1, Orders!$A:$AAA), XLOOKUP("Courier Fee", Orders!$1:$1, Orders!$A:$AAA), "Not Found")} -> Not Found | O117: =E117*4% -> 0 | P117: =SUM(N117:O117) -> 0
N118: {=XLOOKUP($B118, XLOOKUP("Tracking Number", Orders!$1:$1, Orders!$A:$AAA), XLOOKUP("Courier Fee", Orders!$1:$1, Orders!$A:$AAA), "Not Found")} -> Not Found | O118: =E118*4% -> 0 | P118: =SUM(N118:O118) -> 0
N119: {=XLOOKUP($B119, XLOOKUP("Tracking Number", Orders!$1:$1, Orders!$A:$AAA), XLOOKUP("Courier Fee", Orders!$1:$1, Orders!$A:$AAA), "Not Found")} -> Not Found | O119: =E119*4% -> 0 | P119: =SUM(N119:O119) -> 0
N120: {=XLOOKUP($B120, XLOOKUP("Tracking Number", Orders!$1:$1, Orders!$A:$AAA), XLOOKUP("Courier Fee", Orders!$1:$1, Orders!$A:$AAA), "Not Found")} -> Not Found | O120: =E120*4% -> 0 | P120: =SUM(N120:O120) -> 0
N121: {=XLOOKUP($B121, XLOOKUP("Tracking Number", Orders!$1:$1, Orders!$A:$AAA), XLOOKUP("Courier Fee", Orders!$1:$1, Orders!$A:$AAA), "Not Found")} -> Not Found | O121: =E121*4% -> 0 | P121: =SUM(N121:O121) -> 0
... N705: {=XLOOKUP($B705, XLOOKUP("Tracking Number", Orders!$1:$1, Orders!$A:$AAA), XLOOKUP("Courier Fee", Orders!$1:$1, Orders!$A:$AAA), "Not Found")} -> Not Found | O705: =E705*4% -> 0 | P705: =SUM(N705:O705) -> 0

Sheet Monitor Stuck Parcels
A1: Tracking | B1: Customer | C1: Status | D1: ⏳ Days Stuck | E1: Note | F1: Price | G1: Product | H1: Last Date | I1: ACTION
A2: 23120050020579 | B2: Nadeem Abbasi | C2: returned | D2: 109 Days | E2: complain marked PostEx | Product MIssing | details Shared | | ↩️ Return Charged: 2026-01-02 | Fee: 200.1 | F2: 2748 | G2: Imported Scoba Executive Nik Tro - M / Silver Grey (x1) | H2: 46022.757
A3: 20120050022641 | B3: Muzammil Sabir | C3: attempted | D3: 5 Days | E3: confirm | F3: 3348 | G3: Multi ref PUM-A - M / White (x1), Multi ref PUM-A - M / Black (x1) | H3: 46126.081
A4: 29120050023561 | B4: Junaid Babu | C4: un-assigned by me | D4: 3 Days | E4: not ans / not confirmed | F4: 5247 | G4: Embossed NIK-E - XL / Black (x1), Embossed NIK-E - XL / White (x1), Basic Branded Adi Trouser - L / Black (x1) | H4: 46128.081
A5: 29120050023007 | B5: Dr Junaid Junaid | C5: un-assigned by me | D5: 9 Days | E5: confirm | F5: 3348 | G5: Multi ref PUM-A - M / White (x1), Multi ref PUM-A - M / Black (x1) | H5: 46122.081
A6: 27120050023005 | B6: Sohrab Qalandari | C6: un-assigned by me | D6: 9 Days | E6: confirm | F6: 3348 | G6: Multi ref PUM-A - M / White (x1), Multi ref PUM-A - M / Black (x1) | H6: 46122.081
A7: LE7532033190 | B7: Ali Ahmad | C7: shipper advice | D7: 2 Days | E7: lcs Nankana sahib | F7: 3348 | G7: ADI Multi Ref Stripes - XL / White (x1), ADI Multi Ref Stripes - L / Black (x1) | H7: 46129.083
A8: 22120050023112 | B8: Faro Khan | C8: un-assigned by me | D8: 9 Days | E8: confirm | F8: 2199 | G8: Multi ref PUM-A - M / White (x1) | H8: 46122.081
A9: 24120050023097 | B9: Waseem Aslam | C9: un-assigned by me | D9: 9 Days | E9: confirm | F9: 3348 | G9: Multi ref PUM-A - L / White (x1), Multi ref PUM-A - L / Black (x1) | H9: 46122.081
A10: 25120050023000 | B10: adeel raja | C10: un-assigned by me | D10: 9 Days | E10: open to allow | F10: 3348 | G10: Multi ref PUM-A - M / White (x1), Multi ref PUM-A - M / Black (x1) | H10: 46122.081
A11: 25120050023040 | B11: Afnan Saeed | C11: un-assigned by me | D11: 9 Days | E11: confirm | F11: 3348 | G11: Multi ref PUM-A - M / White (x1), Multi ref PUM-A - M / Black (x1) | H11: 46122.081
A12: 22120050023206 | B12: Hammad Arif | C12: en-route to lahore warehouse | D12: 3 Days | E12: not ans confirm | F12: 3348 | G12: ADI Multi Ref Stripes - M / White (x1), ADI Multi Ref Stripes - M / Black (x1) | H12: 46128.081
A13: 20120050023204 | B13: Aqeel Ali | C13: un-assigned by me | D13: 9 Days | E13: confirm | F13: 3348 | G13: Multi ref PUM-A - M / White (x1), Multi ref PUM-A - M / Black (x1) | H13: 46122.081
A14: LE7530384423 | B14: Waris iqbal Iqbal | C14: in transit | D14: 5 Days | E14: khaplu lcs | F14: 3348 | G14: Multi ref PUM-A - 3XL / White (x1), Multi ref PUM-A - 3XL / Black (x1) | H14: 46126.083
A15: 27120050023032 | B15: Awais Aslam | C15: returned | D15: 10 Days | E15: (rehman issue) allow to oepn rider open kerna nahi da raha | ↩️ Return Charged: 2026-04-10 | Ref: CPR-XWOR8962608 | Fee: 552.45 | F15: 11447 | G15: Basic Branded Adi Trouser - XL / Black (x1), Adi- Hoodie - XL / Black (x1), ADI Multi Ref Stripes - XL / White (x1), ADI Multi Ref Stripes - XL / Black (x1), ADI - TriStrip-Tracksuit Winter - XL / Gray (x1) | H15: 46121.081
A16: 22120050023188 | B16: Zekash Ahmad Allow to Open | C16: un-assigned by me | D16: 9 Days | E16: confirm | F16: 3348 | G16: Multi ref PUM-A - L / White (x1), Multi ref PUM-A - L / Black (x1) | H16: 46122.081
A17: 22120050023186 | B17: Muhammad Tayyab Abbasi | C17: un-assigned by me | D17: 9 Days | E17: confirm | F17: 3348 | G17: Multi ref PUM-A - L / White (x1), Multi ref PUM-A - L / Black (x1) | H17: 46122.081
A18: 24120050023236 | B18: Omer Mehmood Ch Mehmood Son’s | C18: un-assigned by me | D18: 9 Days | E18: confirm | F18: 2199 | G18: Multi ref PUM-A - L / White (x1) | H18: 46122.081
A19: 29120050023181 | B19: Sohaib Nasir | C19: un-assigned by me | D19: 9 Days | F19: 3399 | G19: Multi ref PUM-A - L / White (x1), ADI - EMBOSSED LOGO - L / Olive( Commando Green) (x1) | H19: 46122.081
A20: 29120050023178 | B20: Muhammad Usman Muhammad | C20: un-assigned by me | D20: 9 Days | E20: confirm | F20: 2199 | G20: Multi ref PUM-A - M / White (x1) | H20: 46122.081
A21: 29120050023235 | B21: Tauqeer Akbar | C21: un-assigned by me | D21: 9 Days | E21: confirm | F21: 6249 | G21: Multi ref PUM-A - L / White (x1), ADI - EMBOSSED LOGO - L / Black (x1), Tipping Crew - L / White (x1), Tipping Crew - L / Black (x1) | H21: 46122.081
A22: 23120050023128 | B22: Saima Butt | C22: un-assigned by me | D22: 9 Days | F22: 3348 | G22: Multi ref PUM-A - L / White (x1), Multi ref PUM-A - L / Black (x1) | H22: 46122.081
A23: LE7530384557 | B23: Nabeel Ch Ch | C23: shipper advice | D23: 3 Days | E23: confirm ( call when arrived at Station ) office sa recive ker la ga parcel | F23: 1848 | G23: ADI-Trouser Tri strip - L / Black (x1) | H23: 46128.083
A24: 21120050023303 | B24: Zubair Ahmad | C24: un-assigned by me | D24: 9 Days | E24: confirm | F24: 1449 | G24: ADI - EMBOSSED LOGO - M / Black (x1) | H24: 46122.081
A25: 25120050023211 | B25: Zunair Munir | C25: un-assigned by me | D25: 9 Days | E25: confirm postex | F25: 3348 | G25: Multi ref PUM-A - L / White (x1), Multi ref PUM-A - L / Black (x1) | H25: 46122.081
A26: 24120050023261 | B26: asad Habib | C26: un-assigned by me | D26: 9 Days | E26: confirm on call | F26: 3348 | G26: Multi ref PUM-A - M / White (x1), Multi ref PUM-A - M / Black (x1) | H26: 46122.081
A27: 24120050023260 | B27: Abubakar Ch | C27: un-assigned by me | D27: 9 Days | F27: 3348 | G27: Multi ref PUM-A - M / White (x1), Multi ref PUM-A - M / Black (x1) | H27: 46122.081
A28: 21120050023560 | B28: Ismail Khan | C28: un-assigned by me | D28: 3 Days | E28: confirm | F28: 4098 | G28: Adi Winter Trouser - M / Black (x1), Embossed NIK-E - M / Black (x1) | H28: 46128.081
A29: 21120050023256 | B29: javed iqbal | C29: un-assigned by me | D29: 9 Days | E29: confirm | F29: 3348 | G29: Multi ref PUM-A - L / White (x1), Multi ref PUM-A - L / Black (x1) | H29: 46122.081
A30: 23120050023255 | B30: Ali Raza | C30: un-assigned by me | D30: 9 Days | E30: confirm | F30: 2199 | G30: Multi ref PUM-A - M / White (x1) | H30: 46122.081
A31: 28120050023299 | B31: Irum Bukhari | C31: un-assigned by me | D31: 9 Days | E31: confirm | F31: 3348 | G31: Multi ref PUM-A - M / White (x1), Multi ref PUM-A - M / Black (x1) | H31: 46122.081
A32: 29120050023250 | B32: Syed Aashir Abbas | C32: un-assigned by me | D32: 9 Days | E32: confirm | F32: 2199 | G32: Multi ref PUM-A - M / White (x1) | H32: 46122.081
A33: 28120050023279 | B33: Athwani Akash | C33: un-assigned by me | D33: 9 Days | E33: confirm | F33: 3348 | G33: Multi ref PUM-A - M / White (x1), Multi ref PUM-A - M / Black (x1) | H33: 46122.081
A34: 21120050023247 | B34: Inam Khan | C34: un-assigned by me | D34: 9 Days | E34: confirm | F34: 3348 | G34: Multi ref PUM-A - M / White (x1), Multi ref PUM-A - M / Black (x1) | H34: 46122.081
A35: 29120050023242 | B35: danish danish | C35: un-assigned by me | D35: 9 Days | E35: in wp whatsup | F35: 3698 | G35: ADI-Trouser Tri strip - L / Black (x1), Multi ref PUM-A - L / White (x1) | H35: 46122.081
A36: 173012419967 | B36: Amir Ilyas | C36: delivery unsuccessful | D36: 5 Days | E36: TCS | F36: 3348 | G36: ADI Multi Ref Stripes - 4XL / White (x1), ADI Multi Ref Stripes - 4XL / Black (x1) | H36: 46126.083
A37: 27120050023293 | B37: Muhammad Asim | C37: un-assigned by me | D37: 9 Days | F37: 3348 | G37: Multi ref PUM-A - L / White (x1), Multi ref PUM-A - L / Black (x1) | H37: 46122.081
A38: 22120050023286 | B38: Osaid Khaled | C38: un-assigned by me | D38: 9 Days | E38: confirm | F38: 3398 | G38: Multi ref PUM-A - M / White (x1), Multi ref PUM-A - M / Black (x1) | H38: 46122.081
A39: 20120050023340 | B39: Yasir Wasim | C39: un-assigned by me | D39: 9 Days | E39: confirm | F39: 3398 | G39: Multi ref PUM-A - L / White (x1), Multi ref PUM-A - L / Black (x1) | H39: 46122.081
A40: 23120050023339 | B40: Shah Zeb | C40: un-assigned by me | D40: 9 Days | E40: confirm | F40: 4199 | G40: Multi ref PUM-A - M / Black (x1), Multi ref PUM-A - M / White (x1) | H40: 46122.081
A41: 23120050023336 | B41: Arif Balti | C41: un-assigned by me | D41: 9 Days | E41: confirm | F41: 3398 | G41: Multi ref PUM-A - M / White (x1), Multi ref PUM-A - M / Black (x1) | H41: 46122.081
A42: 21120050023335 | B42: Hassam Abbasi | C42: un-assigned by me | D42: 9 Days | E42: confirm | F42: 3398 | G42: Multi ref PUM-A - M / White (x1), Multi ref PUM-A - M / Black (x1) | H42: 46122.081
A43: 21120050023332 | B43: Raqeeb Cheema | C43: un-assigned by me | D43: 9 Days | E43: confirm | F43: 3398 | G43: Multi ref PUM-A - L / White (x1), Multi ref PUM-A - L / Black (x1) | H43: 46122.081
A44: 21120050023331 | B44: Khawar afridi Afridi | C44: un-assigned by me | D44: 9 Days | E44: confirm allow to open | F44: 3398 | G44: Multi ref PUM-A - M / White (x1), Multi ref PUM-A - M / Black (x1) | H44: 46122.081
A45: 26120050023328 | B45: Mudasir Mushtaq | C45: un-assigned by me | D45: 9 Days | E45: open to allow | F45: 3398 | G45: Multi ref PUM-A - M / White (x1), Multi ref PUM-A - M / Black (x1) | H45: 46122.081
A46: 21120050023323 | B46: Maham Zafar | C46: un-assigned by me | D46: 9 Days | E46: confirm | F46: 3398 | G46: Multi ref PUM-A - M / White (x1), Multi ref PUM-A - M / Black (x1) | H46: 46122.081
A47: 21120050023320 | B47: Muhammad Asif | C47: un-assigned by me | D47: 9 Days | E47: confirm | F47: 2249 | G47: Multi ref PUM-A - L / White (x1) | H47: 46122.081
A48: 21120050023313 | B48: Usman Sani | C48: un-assigned by me | D48: 9 Days | E48: allow to oepn | F48: 5049 | G48: Multi ref PUM-A - L / White (x1), Multi ref PUM-A - L / Black (x1), Embossed NIK-E - L / Black (x1) | H48: 46122.081
A49: 20120050023309 | B49: Suman Zehra | C49: un-assigned by me | D49: 9 Days | E49: confirm | F49: 3398 | G49: Multi ref PUM-A - M / White (x1), Multi ref PUM-A - M / Black (x1) | H49: 46122.081
A50: LE7531953845 | B50: Tanvir Baloch | C50: shipper advice | D50: 3 Days | E50: confirm ( call when arrived at station ) office sa receive ker la gaa parcel | F50: 3398 | G50: ADI Multi Ref Stripes - L / White (x1), ADI Multi Ref Stripes - L / Black (x1) | H50: 46128.083
A51: 26120050023381 | B51: Moazzam Butt | C51: un-assigned by me | D51: 10 Days | E51: 6000/- cash received | F51: 6198 | G51: Multi ref PUM-A - 2XL / White (x1), Multi ref PUM-A - 2XL / Black (x1), ADI Ref Stripes - 2XL / White (x1), ADI Ref Stripes - 2XL / Black (x1) | H51: 46121.081
A52: 23120050023496 | B52: Mustafa Ali | C52: un-assigned by me | D52: 3 Days | E52: confirm | F52: 1499 | G52: ADI - EMBOSSED LOGO - M / White (x1) | H52: 46128.081
A53: 29120050023360 | B53: Afrasiab Akbar | C53: un-assigned by me | D53: 9 Days | E53: confirm | F53: 2249 | G53: Multi ref PUM-A - L / White (x1) | H53: 46122.081
A54: 23120050023355 | B54: Ali Jamil | C54: un-assigned by me | D54: 9 Days | E54: confirm | F54: 3297 | G54: ADI - EMBOSSED LOGO - XL / White (x1), ADI - EMBOSSED LOGO - XL / Black (x1) | H54: 46122.081
A55: 24120050023352 | B55: Muhammad Usman Niaz | C55: un-assigned by me | D55: 9 Days | E55: confirm | F55: 1798 | G55: ADI - EMBOSSED LOGO - M / White (x1) | H55: 46122.081
A56: 29120050023359 | B56: Naveed Ali | C56: un-assigned by me | D56: 9 Days | E56: confirm | F56: 1798 | G56: ADI - EMBOSSED LOGO - L / White (x1) | H56: 46122.081
A57: 21120050023394 | B57: Asad Zaheer | C57: un-assigned by me | D57: 9 Days | E57: confirm | F57: 6298 | G57: A | X Embroidery LOGO - M / Bottle Green (x1), A | X Embroidery LOGO - M / American Blue (x1), ADI - EMBOSSED LOGO - XL / Black (x1), ADI - EMBOSSED LOGO - XL / White (x1) | H57: 46122.081
A58: LE7532032650 | B58: Hasnain Memon | C58: delivery unsuccessful | D58: 3 Days | E58: confirm | F58: 3149 | G58: Tipping Crew - M / Black (x1), Tipping Crew - M / White (x1) | H58: 46128.083
A59: 20120050023389 | B59: Syed Awais Sherazi | C59: un-assigned by me | D59: 9 Days | E59: confirm | F59: 5496 | G59: ADI - EMBOSSED LOGO - M / Zinc Blue (x1), ADI - EMBOSSED LOGO - M / Grey (x1), ADI - EMBOSSED LOGO - M / Black (x1), ADI - EMBOSSED LOGO - M / White (x1) | H59: 46122.081
A60: 24120050023613 | B60: Nasir Rafiq Channar | C60: en-route to lahore warehouse | D60: 2 Days | E60: confrm | F60: 2997 | G60: ADI-Trouser Tri strip - L / Black (x2) | H60: 46129.081
A61: 23120050023564 | B61: Sohail Rajpoot | C61: attempted | D61: 2 Days | E61: again confirm 3014438504 is number per call ker la rider reatempt | F61: 3399 | G61: ADI Multi Ref Stripes - M / White (x1), ADI Multi Ref Stripes - M / Black (x1) | H61: 46129.081
A62: 27120050023494 | B62: Faisal Nizami | C62: attempted | D62: 4 Days | E62: confirm | F62: 3999 | G62: Tipping Crew - L / Black (x1), Tipping Crew - L / White (x1) | H62: 46127.081
A63: 26120050023516 | B63: javed iqbal | C63: attempted | D63: 2 Days | E63: confrm | F63: 3149 | G63: TEXTURE LIGHT SKY - 15 (x1) | H63: 46129.081
A64: 23120050023500 | B64: Asif jawaid Gondal | C64: un-assigned by me | D64: 3 Days | E64: confirm | F64: 2797 | G64: ADI - EMBOSSED LOGO - XL / Zinc Blue (x1), ADI - EMBOSSED LOGO - XL / Bottle green (x1) | H64: 46128.081
A65: 27120050023546 | B65: Hamid Raza | C65: attempted | D65: 2 Days | E65: confirm koi call nahi ai | F65: 2098 | G65: Multi ref PUM-A - XL / White (x1) | H65: 46129.081
A66: 29120050023575 | B66: Sikandar Khushal | C66: attempted | D66: 2 Days | E66: confirm | F66: 2797 | G66: ADI - EMBOSSED LOGO - L / Mustard (x1), ADI - EMBOSSED LOGO - L / Sky (x1) | H66: 46129.081
A67: 28120050023578 | B67: Haseeb Shah | C67: attempted | D67: 2 Days | E67: confirm fake attempt | F67: 3899 | G67: Basic RL Crew- Plus Size - 3XL / Black (x1), Basic RL Crew- Plus Size - 3XL / Mehroon (x1) | H67: 46129.081
A68: LOCALDISPATCHED@SHOP01 | B68: Abdul moiz Abdul moiz | C68: booked | D68: 4 Days | E68: whatsup paid parcel haa | F68: 2700 | G68: ADI - EMBOSSED LOGO - M / Sky (x1), ADI - EMBOSSED LOGO - M / Mustard (x1) | H68: 46127.081

Sheet SEARCH_TOOL
A1: 📅 Preset | B1: 📆 Start | C1: 🏁 End | D1: 🏷️ Status Filter | E1: 🔑 Keyword | F1: 🗂️ Sort By | G1: ⭐ Load View | H1: 🔍 Found: 8 Orders 💰 Sum: Rs 30,085 | J1: ✅ Delivered: 0 | 🔄 Returned: 8 | ⏳ Pending: 0 | L1: =IFERROR(__xludf.DUMMYFUNCTION("SPARKLINE({0,8,0}, {""charttype"",""bar""; ""color1"",""#d9ead3""; ""color2"",""#f4cccc""; ""color3"",""#fce5cd""})"),"")
A2: All Time | B2: 46109 | C2: 46109 | D2: Returned, Returned to Shipper | F2: Default
A3: 🔄 RUN SEARCH ➡️ | B3: FALSE | C3: 💾 SAVE VIEW ➡️ | D3: FALSE | E3: 🗑️ DELETE VIEW ➡️ | F3: FALSE | G3: 🧹 RESET BOARD ➡️ | H3: FALSE
A4: Order ID | B4: Date | C4: Customer Name | D4: Phone | E4: City | F4: Price | G4: Paid Amount | H4: Pending Balance | I4: Delivery Status | J4: Courier | K4: Tracking Number | L4: notes | M4: COST
A5: =HYPERLINK("https://admin.shopify.com/store/041839-3/orders/6804722188547", "🛍️ 6804722188547") -> 🛍️ 6804722188547 | B5: 46008 | C5: Nadeem Abbasi | D5: =HYPERLINK("https://wa.me/923239699795?text=Hi%2C%20this%20is%20TracePK!%20%F0%9F%8C%9F%20Confirming%20your%20order%20%236804722188547%20for%20Rs%202748.%20Please%20reply%20'YES'%20to%20dispatch.", "💬 3239699795") -> 💬 3239699795 | E5: Murree | F5: 2748 | G5: 0 | H5: 2748 | I5: Returned | J5: Postex | K5: =HYPERLINK("https://merchant.postex.pk/track/23120050020579", "🚚 23120050020579") -> 🚚 23120050020579 | L5: complain marked PostEx | Product MIssing | details Shared | | ↩️ Return Charged: 2026-01-02 | Fee: 200.1 | M5: 1400
A6: =HYPERLINK("https://admin.shopify.com/store/041839-3/orders/6959736619267", "🛍️ 6959736619267") -> 🛍️ 6959736619267 | B6: 46101 | C6: Raza Abbas | D6: =HYPERLINK("https://wa.me/923093895214?text=Hi%2C%20this%20is%20TracePK!%20%F0%9F%8C%9F%20Confirming%20your%20order%20%236959736619267%20for%20Rs%201499.%20Please%20reply%20'YES'%20to%20dispatch.", "💬 3093895214") -> 💬 3093895214 | E6: Matairi | F6: 1499 | H6: 1499 | I6: Returned | J6: PostEx | K6: =HYPERLINK("https://merchant.postex.pk/track/29120050023334", "🚚 29120050023334") -> 🚚 29120050023334 | L6: confirm | M6: 750
A7: =HYPERLINK("https://admin.shopify.com/store/041839-3/orders/6972048507139", "🛍️ 6972048507139") -> 🛍️ 6972048507139 | B7: 46108 | C7: Awais Aslam | D7: =HYPERLINK("https://wa.me/923352360116?text=Hi%2C%20this%20is%20TracePK!%20%F0%9F%8C%9F%20Confirming%20your%20order%20%236972048507139%20for%20Rs%2011447.%20Please%20reply%20'YES'%20to%20dispatch.", "💬 3352360116") -> 💬 3352360116 | E7: Rawalpindi | F7: 11447 | H7: 11447 | I7: Returned | J7: PostEx | K7: =HYPERLINK("https://merchant.postex.pk/track/27120050023032", "🚚 27120050023032") -> 🚚 27120050023032 | L7: (rehman issue) allow to oepn rider open kerna nahi da raha | ↩️ Return Charged: 2026-04-10 | Ref: CPR-XWOR8962608 | Fee: 552.45 | M7: 3900
A8: =HYPERLINK("https://admin.shopify.com/store/041839-3/orders/6984277983491", "🛍️ 6984277983491") -> 🛍️ 6984277983491 | B8: 46116 | C8: Zeshan niazi Zeshan niazi | D8: =HYPERLINK("https://wa.me/923254721823?text=Hi%2C%20this%20is%20TracePK!%20%F0%9F%8C%9F%20Confirming%20your%20order%20%236984277983491%20for%20Rs%203149.%20Please%20reply%20'YES'%20to%20dispatch.", "💬 +923254721823") -> 💬 +923254721823 | E8: Lahore | F8: 3149 | H8: 3149 | I8: Returned | J8: PostEx | K8: =HYPERLINK("https://merchant.postex.pk/track/23120050023425", "🚚 23120050023425") -> 🚚 23120050023425 | L8: whatsup | M8: 720
A9: =HYPERLINK("https://admin.shopify.com/store/041839-3/orders/6990662959363", "🛍️ 6990662959363") -> 🛍️ 6990662959363 | B9: 46121 | C9: Jalees Khan | D9: =HYPERLINK("https://wa.me/923047788894?text=Hi%2C%20this%20is%20TracePK!%20%F0%9F%8C%9F%20Confirming%20your%20order%20%236990662959363%20for%20Rs%202797.%20Please%20reply%20'YES'%20to%20dispatch.", "💬 3047788894") -> 💬 3047788894 | E9: Mailsi | F9: 2797 | H9: 2797 | I9: Returned | J9: PostEx | K9: =HYPERLINK("https://merchant.postex.pk/track/20120050023404", "🚚 20120050023404") -> 🚚 20120050023404 | L9: consignee want open parcel | M9: 1100
A10: =HYPERLINK("https://admin.shopify.com/store/041839-3/orders/6991776973059", "🛍️ 6991776973059") -> 🛍️ 6991776973059 | B10: 46121 | C10: Qasim Jutt | D10: =HYPERLINK("https://wa.me/923007213980?text=Hi%2C%20this%20is%20TracePK!%20%F0%9F%8C%9F%20Confirming%20your%20order%20%236991776973059%20for%20Rs%203397.%20Please%20reply%20'YES'%20to%20dispatch.", "💬 3007213980") -> 💬 3007213980 | E10: Faisalabad | F10: 3397 | H10: 3397 | I10: Returned | J10: PostEx | K10: =HYPERLINK("https://merchant.postex.pk/track/20120050023478", "🚚 20120050023478") -> 🚚 20120050023478 | L10: not ans confirm | M10: 720
A11: =HYPERLINK("https://admin.shopify.com/store/041839-3/orders/6993094312195", "🛍️ 6993094312195") -> 🛍️ 6993094312195 | B11: 46122 | C11: Hassan Raza | D11: =HYPERLINK("https://wa.me/923044495171?text=Hi%2C%20this%20is%20TracePK!%20%F0%9F%8C%9F%20Confirming%20your%20order%20%236993094312195%20for%20Rs%201949.%20Please%20reply%20'YES'%20to%20dispatch.", "💬 3044495171") -> 💬 3044495171 | E11: Bhera | F11: 1949 | H11: 1949 | I11: Returned | J11: PostEx | K11: =HYPERLINK("https://merchant.postex.pk/track/21120050023499", "🚚 21120050023499") -> 🚚 21120050023499 | L11: confir koi nahi aya | M11: 550
A12: =HYPERLINK("https://admin.shopify.com/store/041839-3/orders/6994171855107", "🛍️ 6994171855107") -> 🛍️ 6994171855107 | B12: 46123 | C12: Arslan Nawaz | D12: =HYPERLINK("https://wa.me/923016870627?text=Hi%2C%20this%20is%20TracePK!%20%F0%9F%8C%9F%20Confirming%20your%20order%20%236994171855107%20for%20Rs%203099.%20Please%20reply%20'YES'%20to%20dispatch.", "💬 3016870627") -> 💬 3016870627 | E12: Lahore | F12: 3099 | H12: 3099 | I12: Returned | J12: PostEx | K12: =HYPERLINK("https://merchant.postex.pk/track/28120050023597", "🚚 28120050023597") -> 🚚 28120050023597 | L12: confirm on wp open to allow | M12: 1100

Sheet PNL
C1: IN | D1: IN | F1: OUT | G1: OUT | H1: OUT | I1: OUT | J1: IN | K1: OUT | M1: OUT | N1: OUT | O1: OUT | P1: IN | Q1: OUT | R1: OUT | S1: IN | T1: OUT | W1: IN
A2: Averages | G2: =AVERAGE(G5:G35) -> 3161.322 | J2: =AVERAGE(J5:J35) -> 28605.704 | N2: =AVERAGE(N5:N35) -> 10808.001 | O2: =AVERAGE(O5:O35) -> 70.827636 | S2: =AVERAGE(S5:S35) -> 40.741935 | T2: =AVERAGE(T5:T35) -> 5.0967742 | W2: =AVERAGE(W5:W35) -> 35.645161
A3: Totals | B3: =AVERAGE(B5:B35) -> 3138.3367 | C3: =sum(C5:C35) -> 2450024.6 | D3: =SUM(D5:D35) -> 903820 | E3: =AVERAGE(E5:E35) -> 0.36757546 | F3: =SUM(F5:F35) -> 2352023.6 | G3: =SUM(G5:G35) -> 98000.983 | H3: =sum(F5:F35) -> 2352023.6 | I3: =AVERAGE(I5:I35) -> 38.803116 | J3: =sum(J5:J35) -> 886776.81 | K3: =sum(K5:K35) -> 0 | L3: =SUM(L5:L35) -> 319000.98 | M3: =sum(M5:M35) -> 324379.74 | N3: =sum(N5:N35) -> 335048.03 | O3: =AVERAGE(O5:O35) -> 70.827636 | P3: =AVERAGE(P5:P35) -> 4.7325904 | Q3: =AVERAGE(Q5:Q35) -> 747.43677 | R3: =AVERAGE(R5:R35) -> 851.58616 | S3: =sum(S5:S35) -> 1263 | T3: =sum(T5:T35) -> 158 | U3: =AVERAGE(U5:U35) -> 0.12373487 | V3: =sum(V5:V35) -> 0 | W3: =sum(W5:W35) -> 1105 | X3: =AVERAGE(X5:X35) -> 0.87626513 | Y3: =sum(Y5:Y35) -> 786 | Z3: =sum(Z5:Z35) -> 318 | AA3: =SUM(AA5:AA35) -> 1 | AB3: =sum(AB5:AB35) -> 1 | AD3: =SUM(AD5:AD35) -> 2447525.6 | AE3: =sum(AE5:AE35) -> 2499
A4: Dates | B4: AOV | C4: Delivered sale | D4: CGS | E4: CGS % | F4: -4% tax | G4: TAX Paid | H4: Gross Profit | I4: Mar % | J4: Marketing 10% tax | K4: Tiktok marketing | L4: est courier (200 x total parcel dispatch | M4: Actual exp + tax | N4: PNL (Day vise) | O4: Del% | P4: ROAS(meta) | Q4: CPA AVG (mar/landed orders) | R4: Net CPA AVG(after cancelations) | S4: Landed orders | T4: Cancelations | U4: cal % | V4: Pending | W4: Total Dipatched | X4: Dis % | Y4: Delivered | Z4: Restocked | AA4: Intransit | AB4: Fake Return | AC4: without tracking id | AD4: payment paid | AE4: Diff correction | AF4: Refrance Number that have diff | AG4: Unsorted Tracking IDs | AH4: Delivered (payment pending)
A5: 45992 | B5: =C5/Y5 -> 2773.5714 | C5: =SUMIFS(Orders!$H:$H, Orders!$Z:$Z, $A5, Orders!$M:$M, "Delivered") -> 77660 | D5: =SUMIFS(Orders!$Q:$Q, Orders!$Z:$Z, $A5, Orders!$M:$M, "Delivered") -> 26870 | E5: =D5/C5 -> 0.34599536 | F5: =C5-(C5*4/100) -> 74553.6 | G5: =C5-F5 -> 3106.4 | H5: =C5-D5 -> 50790 | I5: =IFERROR(J5/C5, 0)*100 -> 48.799897 | J5: 37898 | L5: =(200*W5)+C5*4% -> 11506.4 | M5: =SUMIFS(Orders!$W:$W, Orders!$Z:$Z, $A5) -> 11400 | N5: =H5-J5-K5-M5 -> 1492 | O5: =Y5/W5*100 -> 66.666667 | P5: 3.8442817 | Q5: =J5/S5 -> 823.86957 | R5: =J5/W5 -> 902.33333 | S5: =COUNTIFS(Orders!$Z:$Z, $A5) -> 46 | T5: =COUNTIFS(Orders!$Z:$Z, $A5, Orders!$M:$M, "Cancelled") -> 4 | U5: =T5/S5 -> 0.086956522 | V5: =COUNTIFS(Orders!$Z:$Z, $A5, Orders!$M:$M, "pending") -> 0 | W5: =S5-T5 -> 42 | X5: =W5/S5 -> 0.91304348 | Y5: =COUNTIFS(Orders!$Z:$Z, $A5, Orders!$M:$M, "Delivered") -> 28 | Z5: =COUNTIFS(Orders!$Z:$Z, $A5, Orders!$M:$M, "Return Received") -> 14 | AA5: =W5-Y5-Z5-V5 -> 0 | AB5: {=SUM(COUNTIFS(Orders!$Z:$Z, $A5, Orders!$M:$M, {"Returned","Returned to Shipper"}))} -> 0 | AC5: =COUNTIFS(Orders!$Z:$Z, $A5, Orders!$I:$I, "", Orders!$M:$M, "<>Cancelled") -> 0 | AD5: =SUMIFS(Orders!$U:$U, Orders!$Z:$Z, $A5, Orders!$M:$M, "Delivered") -> 75161 | AE5: =C5-AD5 -> 2499 | AF5: =IFERROR(__xludf.DUMMYFUNCTION("IFERROR(TEXTJOIN("", "", TRUE, FILTER(Orders!$B$2:$B$2517, (TEXT(Orders!$D$2:$D$2517,""d-mmm"")=TEXT($A5,""d-mmm"")) * (ABS(Orders!$H$2:$H$2517 - Orders!$U$2:$U$2517) >= 1) * (Orders!$M$2:$M$2517=""Delivered""))), ""All Balanced"")"),"TR26747") -> TR26747 | AG5: =IFERROR(__xludf.DUMMYFUNCTION("IFERROR(TEXTJOIN("", "", TRUE, FILTER(Orders!$I$2:$I$2517, (Orders!$M$2:$M$2517=""Delivered"") * (Orders!$N$2:$N$2517<>""Paid"") * (Orders!$Z$2:$Z$2517=$A5))), """")"),"23120050019955") -> 23120050019955 | AH5: =COUNTIFS(Orders!$M:$M, "Delivered", Orders!$N:$N, "<>Paid", Orders!$Z:$Z, $A5) -> 0
A6: 45993 | B6: =C6/Y6 -> 3035.9219 | C6: =SUMIFS(Orders!$H:$H, Orders!$Z:$Z, $A6, Orders!$M:$M, "Delivered") -> 194299 | D6: =SUMIFS(Orders!$Q:$Q, Orders!$Z:$Z, $A6, Orders!$M:$M, "Delivered") -> 73085 | E6: =D6/C6 -> 0.37614707 | F6: =C6-(C6*4/100) -> 186527.04 | G6: =C6-F6 -> 7771.96 | H6: =C6-D6 -> 121214 | I6: =IFERROR(J6/C6, 0)*100 -> 17.932274 | J6: 34842.23 | L6: =(200*W6)+C6*4% -> 23171.96 | M6: =SUMIFS(Orders!$W:$W, Orders!$Z:$Z, $A6) -> 23755.2 | N6: =H6-J6-K6-M6 -> 62616.57 | O6: =Y6/W6*100 -> 83.116883 | P6: 4.5074073 | Q6: =J6/S6 -> 419.7859 | R6: =J6/W6 -> 452.49649 | S6: =COUNTIFS(Orders!$Z:$Z, $A6) -> 83 | T6: =COUNTIFS(Orders!$Z:$Z, $A6, Orders!$M:$M, "Cancelled") -> 6 | U6: =T6/S6 -> 0.072289157 | V6: =COUNTIFS(Orders!$Z:$Z, $A6, Orders!$M:$M, "pending") -> 0 | W6: =S6-T6 -> 77 | X6: =W6/S6 -> 0.92771084 | Y6: =COUNTIFS(Orders!$Z:$Z, $A6, Orders!$M:$M, "Delivered") -> 64 | Z6: =COUNTIFS(Orders!$Z:$Z, $A6, Orders!$M:$M, "Return Received") -> 13 | AA6: =W6-Y6-Z6-V6 -> 0 | AB6: {=SUM(COUNTIFS(Orders!$Z:$Z, $A6, Orders!$M:$M, {"Returned","Returned to Shipper"}))} -> 0 | AC6: =COUNTIFS(Orders!$Z:$Z, $A6, Orders!$I:$I, "", Orders!$M:$M, "<>Cancelled") -> 0 | AD6: =SUMIFS(Orders!$U:$U, Orders!$Z:$Z, $A6, Orders!$M:$M, "Delivered") -> 194299 | AE6: =C6-AD6 -> 0 | AF6: =IFERROR(__xludf.DUMMYFUNCTION("IFERROR(TEXTJOIN("", "", TRUE, FILTER(Orders!$B$2:$B$2517, (TEXT(Orders!$D$2:$D$2517,""d-mmm"")=TEXT($A6,""d-mmm"")) * (ABS(Orders!$H$2:$H$2517 - Orders!$U$2:$U$2517) >= 1) * (Orders!$M$2:$M$2517=""Delivered""))), ""All Balanced"")"),"All Balanced") -> All Balanced | AG6: =IFERROR(__xludf.DUMMYFUNCTION("IFERROR(TEXTJOIN("", "", TRUE, FILTER(Orders!$I$2:$I$3000, (Orders!$M$2:$M$3000=""Delivered"") * (Orders!$N$2:$N$3000<>""Paid"") * (Orders!$Z$2:$Z$3000=$A6))), """")"),"") | AH6: =COUNTIFS(Orders!$M:$M, "Delivered", Orders!$N:$N, "<>Paid", Orders!$Z:$Z, $A6) -> 0
A7: 45994 | B7: =C7/Y7 -> 2751.9048 | C7: =SUMIFS(Orders!$H:$H, Orders!$Z:$Z, $A7, Orders!$M:$M, "Delivered") -> 57790 | D7: =SUMIFS(Orders!$Q:$Q, Orders!$Z:$Z, $A7, Orders!$M:$M, "Delivered") -> 22175 | E7: =D7/C7 -> 0.38371691 | F7: =C7-(C7*4/100) -> 55478.4 | G7: =C7-F7 -> 2311.6 | H7: =C7-D7 -> 35615 | I7: =IFERROR(J7/C7, 0)*100 -> 31.433587 | J7: 18165.47 | L7: =(200*W7)+C7*4% -> 8911.6 | M7: =SUMIFS(Orders!$W:$W, Orders!$Z:$Z, $A7) -> 9020.16 | N7: =H7-J7-K7-M7 -> 8429.37 | O7: =Y7/W7*100 -> 63.636364 | P7: 6.8936409 | Q7: =J7/S7 -> 443.06024 | R7: =J7/W7 -> 550.46879 | S7: =COUNTIFS(Orders!$Z:$Z, $A7) -> 41 | T7: =COUNTIFS(Orders!$Z:$Z, $A7, Orders!$M:$M, "Cancelled") -> 8 | U7: =T7/S7 -> 0.19512195 | V7: =COUNTIFS(Orders!$Z:$Z, $A7, Orders!$M:$M, "pending") -> 0 | W7: =S7-T7 -> 33 | X7: =W7/S7 -> 0.80487805 | Y7: =COUNTIFS(Orders!$Z:$Z, $A7, Orders!$M:$M, "Delivered") -> 21 | Z7: =COUNTIFS(Orders!$Z:$Z, $A7, Orders!$M:$M, "Return Received") -> 12 | AA7: =W7-Y7-Z7-V7 -> 0 | AB7: {=SUM(COUNTIFS(Orders!$Z:$Z, $A7, Orders!$M:$M, {"Returned","Returned to Shipper"}))} -> 0 | AC7: =COUNTIFS(Orders!$Z:$Z, $A7, Orders!$I:$I, "", Orders!$M:$M, "<>Cancelled") -> 0 | AD7: =SUMIFS(Orders!$U:$U, Orders!$Z:$Z, $A7, Orders!$M:$M, "Delivered") -> 57790 | AE7: =C7-AD7 -> 0 | AF7: =IFERROR(__xludf.DUMMYFUNCTION("IFERROR(TEXTJOIN("", "", TRUE, FILTER(Orders!$B$2:$B$2517, (TEXT(Orders!$D$2:$D$2517,""d-mmm"")=TEXT($A7,""d-mmm"")) * (ABS(Orders!$H$2:$H$2517 - Orders!$U$2:$U$2517) >= 1) * (Orders!$M$2:$M$2517=""Delivered""))), ""All Balanced"")"),"All Balanced") -> All Balanced | AG7: =IFERROR(__xludf.DUMMYFUNCTION("IFERROR(TEXTJOIN("", "", TRUE, FILTER(Orders!$I$2:$I$3000, (Orders!$M$2:$M$3000=""Delivered"") * (Orders!$N$2:$N$3000<>""Paid"") * (Orders!$Z$2:$Z$3000=$A7))), """")"),"") | AH7: =COUNTIFS(Orders!$M:$M, "Delivered", Orders!$N:$N, "<>Paid", Orders!$Z:$Z, $A7) -> 0
A8: 45995 | B8: =C8/Y8 -> 3473.92 | C8: =SUMIFS(Orders!$H:$H, Orders!$Z:$Z, $A8, Orders!$M:$M, "Delivered") -> 86848 | D8: =SUMIFS(Orders!$Q:$Q, Orders!$Z:$Z, $A8, Orders!$M:$M, "Delivered") -> 32460 | E8: =D8/C8 -> 0.37375645 | F8: =C8-(C8*4/100) -> 83374.08 | G8: =C8-F8 -> 3473.92 | H8: =C8-D8 -> 54388 | I8: =IFERROR(J8/C8, 0)*100 -> 22.991744 | J8: 19967.87 | L8: =(200*W8)+C8*4% -> 11073.92 | M8: =SUMIFS(Orders!$W:$W, Orders!$Z:$Z, $A8) -> 10852 | N8: =H8-J8-K8-M8 -> 23568.13 | O8: =Y8/W8*100 -> 65.789474 | P8: 7.5459121 | Q8: =J8/S8 -> 424.8483 | R8: =J8/W8 -> 525.47026 | S8: =COUNTIFS(Orders!$Z:$Z, $A8) -> 47 | T8: =COUNTIFS(Orders!$Z:$Z, $A8, Orders!$M:$M, "Cancelled") -> 9 | U8: =T8/S8 -> 0.19148936 | V8: =COUNTIFS(Orders!$Z:$Z, $A8, Orders!$M:$M, "pending") -> 0 | W8: =S8-T8 -> 38 | X8: =W8/S8 -> 0.80851064 | Y8: =COUNTIFS(Orders!$Z:$Z, $A8, Orders!$M:$M, "Delivered") -> 25 | Z8: =COUNTIFS(Orders!$Z:$Z, $A8, Orders!$M:$M, "Return Received") -> 13 | AA8: =W8-Y8-Z8-V8 -> 0 | AB8: {=SUM(COUNTIFS(Orders!$Z:$Z, $A8, Orders!$M:$M, {"Returned","Returned to Shipper"}))} -> 0 | AC8: =COUNTIFS(Orders!$Z:$Z, $A8, Orders!$I:$I, "", Orders!$M:$M, "<>Cancelled") -> 0 | AD8: =SUMIFS(Orders!$U:$U, Orders!$Z:$Z, $A8, Orders!$M:$M, "Delivered") -> 86848 | AE8: =C8-AD8 -> 0 | AF8: =IFERROR(__xludf.DUMMYFUNCTION("IFERROR(TEXTJOIN("", "", TRUE, FILTER(Orders!$B$2:$B$2517, (TEXT(Orders!$D$2:$D$2517,""d-mmm"")=TEXT($A8,""d-mmm"")) * (ABS(Orders!$H$2:$H$2517 - Orders!$U$2:$U$2517) >= 1) * (Orders!$M$2:$M$2517=""Delivered""))), ""All Balanced"")"),"All Balanced") -> All Balanced | AG8: =IFERROR(__xludf.DUMMYFUNCTION("IFERROR(TEXTJOIN("", "", TRUE, FILTER(Orders!$I$2:$I$3000, (Orders!$M$2:$M$3000=""Delivered"") * (Orders!$N$2:$N$3000<>""Paid"") * (Orders!$Z$2:$Z$3000=$A8))), """")"),"") | AH8: =COUNTIFS(Orders!$M:$M, "Delivered", Orders!$N:$N, "<>Paid", Orders!$Z:$Z, $A8) -> 0
A9: 45996 | B9: =C9/Y9 -> 2979.2963 | C9: =SUMIFS(Orders!$H:$H, Orders!$Z:$Z, $A9, Orders!$M:$M, "Delivered") -> 80441 | D9: =SUMIFS(Orders!$Q:$Q, Orders!$Z:$Z, $A9, Orders!$M:$M, "Delivered") -> 28195 | E9: =D9/C9 -> 0.35050534 | F9: =C9-(C9*4/100) -> 77223.36 | G9: =C9-F9 -> 3217.64 | H9: =C9-D9 -> 52246 | I9: =IFERROR(J9/C9, 0)*100 -> 35.84943 | J9: 28837.64 | L9: =(200*W9)+C9*4% -> 10217.64 | M9: =SUMIFS(Orders!$W:$W, Orders!$Z:$Z, $A9) -> 10474.88 | N9: =H9-J9-K9-M9 -> 12933.48 | O9: =Y9/W9*100 -> 77.142857 | P9: 4.5993216 | Q9: =J9/S9 -> 758.88526 | R9: =J9/W9 -> 823.93257 | S9: =COUNTIFS(Orders!$Z:$Z, $A9) -> 38 | T9: =COUNTIFS(Orders!$Z:$Z, $A9, Orders!$M:$M, "Cancelled") -> 3 | U9: =T9/S9 -> 0.078947368 | V9: =COUNTIFS(Orders!$Z:$Z, $A9, Orders!$M:$M, "pending") -> 0 | W9: =S9-T9 -> 35 | X9: =W9/S9 -> 0.92105263 | Y9: =COUNTIFS(Orders!$Z:$Z, $A9, Orders!$M:$M, "Delivered") -> 27 | Z9: =COUNTIFS(Orders!$Z:$Z, $A9, Orders!$M:$M, "Return Received") -> 8 | AA9: =W9-Y9-Z9-V9 -> 0 | AB9: {=SUM(COUNTIFS(Orders!$Z:$Z, $A9, Orders!$M:$M, {"Returned","Returned to Shipper"}))} -> 0 | AC9: =COUNTIFS(Orders!$Z:$Z, $A9, Orders!$I:$I, "", Orders!$M:$M, "<>Cancelled") -> 0 | AD9: =SUMIFS(Orders!$U:$U, Orders!$Z:$Z, $A9, Orders!$M:$M, "Delivered") -> 80441 | AE9: =C9-AD9 -> 0 | AF9: =IFERROR(__xludf.DUMMYFUNCTION("IFERROR(TEXTJOIN("", "", TRUE, FILTER(Orders!$B$2:$B$2517, (TEXT(Orders!$D$2:$D$2517,""d-mmm"")=TEXT($A9,""d-mmm"")) * (ABS(Orders!$H$2:$H$2517 - Orders!$U$2:$U$2517) >= 1) * (Orders!$M$2:$M$2517=""Delivered""))), ""All Balanced"")"),"All Balanced") -> All Balanced | AG9: =IFERROR(__xludf.DUMMYFUNCTION("IFERROR(TEXTJOIN("", "", TRUE, FILTER(Orders!$I$2:$I$3000, (Orders!$M$2:$M$3000=""Delivered"") * (Orders!$N$2:$N$3000<>""Paid"") * (Orders!$Z$2:$Z$3000=$A9))), """")"),"") | AH9: =COUNTIFS(Orders!$M:$M, "Delivered", Orders!$N:$N, "<>Paid", Orders!$Z:$Z, $A9) -> 0
A10: 45997 | B10: =C10/Y10 -> 3091.05 | C10: =SUMIFS(Orders!$H:$H, Orders!$Z:$Z, $A10, Orders!$M:$M, "Delivered") -> 61821 | D10: =SUMIFS(Orders!$Q:$Q, Orders!$Z:$Z, $A10, Orders!$M:$M, "Delivered") -> 21310 | E10: =D10/C10 -> 0.34470487 | F10: =C10-(C10*4/100) -> 59348.16 | G10: =C10-F10 -> 2472.84 | H10: =C10-D10 -> 40511 | I10: =IFERROR(J10/C10, 0)*100 -> 43.842513 | J10: 27103.88 | L10: =(200*W10)+C10*4% -> 8472.84 | M10: =SUMIFS(Orders!$W:$W, Orders!$Z:$Z, $A10) -> 9083.4 | N10: =H10-J10-K10-M10 -> 4323.72 | O10: =Y10/W10*100 -> 66.666667 | P10: 4.1925512 | Q10: =J10/S10 -> 797.17294 | R10: =J10/W10 -> 903.46267 | S10: =COUNTIFS(Orders!$Z:$Z, $A10) -> 34 | T10: =COUNTIFS(Orders!$Z:$Z, $A10, Orders!$M:$M, "Cancelled") -> 4 | U10: =T10/S10 -> 0.11764706 | V10: =COUNTIFS(Orders!$Z:$Z, $A10, Orders!$M:$M, "pending") -> 0 | W10: =S10-T10 -> 30 | X10: =W10/S10 -> 0.88235294 | Y10: =COUNTIFS(Orders!$Z:$Z, $A10, Orders!$M:$M, "Delivered") -> 20 | Z10: =COUNTIFS(Orders!$Z:$Z, $A10, Orders!$M:$M, "Return Received") -> 10 | AA10: =W10-Y10-Z10-V10 -> 0 | AB10: {=SUM(COUNTIFS(Orders!$Z:$Z, $A10, Orders!$M:$M, {"Returned","Returned to Shipper"}))} -> 0 | AC10: =COUNTIFS(Orders!$Z:$Z, $A10, Orders!$I:$I, "", Orders!$M:$M, "<>Cancelled") -> 0 | AD10: =SUMIFS(Orders!$U:$U, Orders!$Z:$Z, $A10, Orders!$M:$M, "Delivered") -> 61821 | AE10: =C10-AD10 -> 0 | AF10: =IFERROR(__xludf.DUMMYFUNCTION("IFERROR(TEXTJOIN("", "", TRUE, FILTER(Orders!$B$2:$B$2517, (TEXT(Orders!$D$2:$D$2517,""d-mmm"")=TEXT($A10,""d-mmm"")) * (ABS(Orders!$H$2:$H$2517 - Orders!$U$2:$U$2517) >= 1) * (Orders!$M$2:$M$2517=""Delivered""))), ""All Balanced"")"),"All Balanced") -> All Balanced | AG10: =IFERROR(__xludf.DUMMYFUNCTION("IFERROR(TEXTJOIN("", "", TRUE, FILTER(Orders!$I$2:$I$3000, (Orders!$M$2:$M$3000=""Delivered"") * (Orders!$N$2:$N$3000<>""Paid"") * (Orders!$Z$2:$Z$3000=$A10))), """")"),"") | AH10: =COUNTIFS(Orders!$M:$M, "Delivered", Orders!$N:$N, "<>Paid", Orders!$Z:$Z, $A10) -> 0
A11: 45998 | B11: =C11/Y11 -> 2998.75 | C11: =SUMIFS(Orders!$H:$H, Orders!$Z:$Z, $A11, Orders!$M:$M, "Delivered") -> 83965 | D11: =SUMIFS(Orders!$Q:$Q, Orders!$Z:$Z, $A11, Orders!$M:$M, "Delivered") -> 28110 | E11: =D11/C11 -> 0.33478235 | F11: =C11-(C11*4/100) -> 80606.4 | G11: =C11-F11 -> 3358.6 | H11: =C11-D11 -> 55855 | I11: =IFERROR(J11/C11, 0)*100 -> 32.984815 | J11: 27695.7 | L11: =(200*W11)+C11*4% -> 10558.6 | M11: =SUMIFS(Orders!$W:$W, Orders!$Z:$Z, $A11) -> 11519.56 | N11: =H11-J11-K11-M11 -> 16639.74 | O11: =Y11/W11*100 -> 77.777778 | P11: 5.0577669 | Q11: =J11/S11 -> 659.42143 | R11: =J11/W11 -> 769.325 | S11: =COUNTIFS(Orders!$Z:$Z, $A11) -> 42 | T11: =COUNTIFS(Orders!$Z:$Z, $A11, Orders!$M:$M, "Cancelled") -> 6 | U11: =T11/S11 -> 0.14285714 | V11: =COUNTIFS(Orders!$Z:$Z, $A11, Orders!$M:$M, "pending") -> 0 | W11: =S11-T11 -> 36 | X11: =W11/S11 -> 0.85714286 | Y11: =COUNTIFS(Orders!$Z:$Z, $A11, Orders!$M:$M, "Delivered") -> 28 | Z11: =COUNTIFS(Orders!$Z:$Z, $A11, Orders!$M:$M, "Return Received") -> 8 | AA11: =W11-Y11-Z11-V11 -> 0 | AB11: {=SUM(COUNTIFS(Orders!$Z:$Z, $A11, Orders!$M:$M, {"Returned","Returned to Shipper"}))} -> 0 | AC11: =COUNTIFS(Orders!$Z:$Z, $A11, Orders!$I:$I, "", Orders!$M:$M, "<>Cancelled") -> 0 | AD11: =SUMIFS(Orders!$U:$U, Orders!$Z:$Z, $A11, Orders!$M:$M, "Delivered") -> 83965 | AE11: =C11-AD11 -> 0 | AF11: =IFERROR(__xludf.DUMMYFUNCTION("IFERROR(TEXTJOIN("", "", TRUE, FILTER(Orders!$B$2:$B$2517, (TEXT(Orders!$D$2:$D$2517,""d-mmm"")=TEXT($A11,""d-mmm"")) * (ABS(Orders!$H$2:$H$2517 - Orders!$U$2:$U$2517) >= 1) * (Orders!$M$2:$M$2517=""Delivered""))), ""All Balanced"")"),"All Balanced") -> All Balanced | AG11: =IFERROR(__xludf.DUMMYFUNCTION("IFERROR(TEXTJOIN("", "", TRUE, FILTER(Orders!$I$2:$I$3000, (Orders!$M$2:$M$3000=""Delivered"") * (Orders!$N$2:$N$3000<>""Paid"") * (Orders!$Z$2:$Z$3000=$A11))), """")"),"") | AH11: =COUNTIFS(Orders!$M:$M, "Delivered", Orders!$N:$N, "<>Paid", Orders!$Z:$Z, $A11) -> 0
A12: 45999 | B12: =C12/Y12 -> 3008.9 | C12: =SUMIFS(Orders!$H:$H, Orders!$Z:$Z, $A12, Orders!$M:$M, "Delivered") -> 87258.1 | D12: =SUMIFS(Orders!$Q:$Q, Orders!$Z:$Z, $A12, Orders!$M:$M, "Delivered") -> 32245 | E12: =D12/C12 -> 0.36953589 | F12: =C12-(C12*4/100) -> 83767.776 | G12: =C12-F12 -> 3490.324 | H12: =C12-D12 -> 55013.1 | I12: =IFERROR(J12/C12, 0)*100 -> 34.53441 | J12: 30134.07 | L12: =(200*W12)+C12*4% -> 11490.324 | M12: =SUMIFS(Orders!$W:$W, Orders!$Z:$Z, $A12) -> 11715.48 | N12: =H12-J12-K12-M12 -> 13163.55 | O12: =Y12/W12*100 -> 72.5 | P12: 5.4914452 | Q12: =J12/S12 -> 684.86523 | R12: =J12/W12 -> 753.35175 | S12: =COUNTIFS(Orders!$Z:$Z, $A12) -> 44 | T12: =COUNTIFS(Orders!$Z:$Z, $A12, Orders!$M:$M, "Cancelled") -> 4 | U12: =T12/S12 -> 0.090909091 | V12: =COUNTIFS(Orders!$Z:$Z, $A12, Orders!$M:$M, "pending") -> 0 | W12: =S12-T12 -> 40 | X12: =W12/S12 -> 0.90909091 | Y12: =COUNTIFS(Orders!$Z:$Z, $A12, Orders!$M:$M, "Delivered") -> 29 | Z12: =COUNTIFS(Orders!$Z:$Z, $A12, Orders!$M:$M, "Return Received") -> 11 | AA12: =W12-Y12-Z12-V12 -> 0 | AB12: {=SUM(COUNTIFS(Orders!$Z:$Z, $A12, Orders!$M:$M, {"Returned","Returned to Shipper"}))} -> 0 | AC12: =COUNTIFS(Orders!$Z:$Z, $A12, Orders!$I:$I, "", Orders!$M:$M, "<>Cancelled") -> 0 | AD12: =SUMIFS(Orders!$U:$U, Orders!$Z:$Z, $A12, Orders!$M:$M, "Delivered") -> 87258.1 | AE12: =C12-AD12 -> 0 | AF12: =IFERROR(__xludf.DUMMYFUNCTION("IFERROR(TEXTJOIN("", "", TRUE, FILTER(Orders!$B$2:$B$2517, (TEXT(Orders!$D$2:$D$2517,""d-mmm"")=TEXT($A12,""d-mmm"")) * (ABS(Orders!$H$2:$H$2517 - Orders!$U$2:$U$2517) >= 1) * (Orders!$M$2:$M$2517=""Delivered""))), ""All Balanced"")"),"All Balanced") -> All Balanced | AG12: =IFERROR(__xludf.DUMMYFUNCTION("IFERROR(TEXTJOIN("", "", TRUE, FILTER(Orders!$I$2:$I$3000, (Orders!$M$2:$M$3000=""Delivered"") * (Orders!$N$2:$N$3000<>""Paid"") * (Orders!$Z$2:$Z$3000=$A12))), """")"),"") | AH12: =COUNTIFS(Orders!$M:$M, "Delivered", Orders!$N:$N, "<>Paid", Orders!$Z:$Z, $A12) -> 0
A13: 46000 | B13: =C13/Y13 -> 2971.0556 | C13: =SUMIFS(Orders!$H:$H, Orders!$Z:$Z, $A13, Orders!$M:$M, "Delivered") -> 53479 | D13: =SUMIFS(Orders!$Q:$Q, Orders!$Z:$Z, $A13, Orders!$M:$M, "Delivered") -> 18605 | E13: =D13/C13 -> 0.34789357 | F13: =C13-(C13*4/100) -> 51339.84 | G13: =C13-F13 -> 2139.16 | H13: =C13-D13 -> 34874 | I13: =IFERROR(J13/C13, 0)*100 -> 50.432675 | J13: 26970.89 | L13: =(200*W13)+C13*4% -> 6539.16 | M13: =SUMIFS(Orders!$W:$W, Orders!$Z:$Z, $A13) -> 6871 | N13: =H13-J13-K13-M13 -> 1032.11 | O13: =Y13/W13*100 -> 81.818182 | P13: 2.670216 | Q13: =J13/S13 -> 1078.8356 | R13: =J13/W13 -> 1225.9495 | S13: =COUNTIFS(Orders!$Z:$Z, $A13) -> 25 | T13: =COUNTIFS(Orders!$Z:$Z, $A13, Orders!$M:$M, "Cancelled") -> 3 | U13: =T13/S13 -> 0.12 | V13: =COUNTIFS(Orders!$Z:$Z, $A13, Orders!$M:$M, "pending") -> 0 | W13: =S13-T13 -> 22 | X13: =W13/S13 -> 0.88 | Y13: =COUNTIFS(Orders!$Z:$Z, $A13, Orders!$M:$M, "Delivered") -> 18 | Z13: =COUNTIFS(Orders!$Z:$Z, $A13, Orders!$M:$M, "Return Received") -> 4 | AA13: =W13-Y13-Z13-V13 -> 0 | AB13: {=SUM(COUNTIFS(Orders!$Z:$Z, $A13, Orders!$M:$M, {"Returned","Returned to Shipper"}))} -> 0 | AC13: =COUNTIFS(Orders!$Z:$Z, $A13, Orders!$I:$I, "", Orders!$M:$M, "<>Cancelled") -> 0 | AD13: =SUMIFS(Orders!$U:$U, Orders!$Z:$Z, $A13, Orders!$M:$M, "Delivered") -> 53479 | AE13: =C13-AD13 -> 0 | AF13: =IFERROR(__xludf.DUMMYFUNCTION("IFERROR(TEXTJOIN("", "", TRUE, FILTER(Orders!$B$2:$B$2517, (TEXT(Orders!$D$2:$D$2517,""d-mmm"")=TEXT($A13,""d-mmm"")) * (ABS(Orders!$H$2:$H$2517 - Orders!$U$2:$U$2517) >= 1) * (Orders!$M$2:$M$2517=""Delivered""))), ""All Balanced"")"),"All Balanced") -> All Balanced | AG13: =IFERROR(__xludf.DUMMYFUNCTION("IFERROR(TEXTJOIN("", "", TRUE, FILTER(Orders!$I$2:$I$3000, (Orders!$M$2:$M$3000=""Delivered"") * (Orders!$N$2:$N$3000<>""Paid"") * (Orders!$Z$2:$Z$3000=$A13))), """")"),"") | AH13: =COUNTIFS(Orders!$M:$M, "Delivered", Orders!$N:$N, "<>Paid", Orders!$Z:$Z, $A13) -> 0
A14: 46001 | B14: =C14/Y14 -> 2917.0667 | C14: =SUMIFS(Orders!$H:$H, Orders!$Z:$Z, $A14, Orders!$M:$M, "Delivered") -> 87512 | D14: =SUMIFS(Orders!$Q:$Q, Orders!$Z:$Z, $A14, Orders!$M:$M, "Delivered") -> 32055 | E14: =D14/C14 -> 0.36629262 | F14: =C14-(C14*4/100) -> 84011.52 | G14: =C14-F14 -> 3500.48 | H14: =C14-D14 -> 55457 | I14: =IFERROR(J14/C14, 0)*100 -> 33.341439 | J14: 29177.76 | L14: =(200*W14)+C14*4% -> 12300.48 | M14: =SUMIFS(Orders!$W:$W, Orders!$Z:$Z, $A14) -> 13145 | N14: =H14-J14-K14-M14 -> 13134.24 | O14: =Y14/W14*100 -> 68.181818 | P14: 6.11248 | Q14: =J14/S14 -> 561.11077 | R14: =J14/W14 -> 663.13091 | S14: =COUNTIFS(Orders!$Z:$Z, $A14) -> 52 | T14: =COUNTIFS(Orders!$Z:$Z, $A14, Orders!$M:$M, "Cancelled") -> 8 | U14: =T14/S14 -> 0.15384615 | V14: =COUNTIFS(Orders!$Z:$Z, $A14, Orders!$M:$M, "pending") -> 0 | W14: =S14-T14 -> 44 | X14: =W14/S14 -> 0.84615385 | Y14: =COUNTIFS(Orders!$Z:$Z, $A14, Orders!$M:$M, "Delivered") -> 30 | Z14: =COUNTIFS(Orders!$Z:$Z, $A14, Orders!$M:$M, "Return Received") -> 14 | AA14: =W14-Y14-Z14-V14 -> 0 | AB14: {=SUM(COUNTIFS(Orders!$Z:$Z, $A14, Orders!$M:$M, {"Returned","Returned to Shipper"}))} -> 0 | AC14: =COUNTIFS(Orders!$Z:$Z, $A14, Orders!$I:$I, "", Orders!$M:$M, "<>Cancelled") -> 0 | AD14: =SUMIFS(Orders!$U:$U, Orders!$Z:$Z, $A14, Orders!$M:$M, "Delivered") -> 87512 | AE14: =C14-AD14 -> 0 | AF14: =IFERROR(__xludf.DUMMYFUNCTION("IFERROR(TEXTJOIN("", "", TRUE, FILTER(Orders!$B$2:$B$2517, (TEXT(Orders!$D$2:$D$2517,""d-mmm"")=TEXT($A14,""d-mmm"")) * (ABS(Orders!$H$2:$H$2517 - Orders!$U$2:$U$2517) >= 1) * (Orders!$M$2:$M$2517=""Delivered""))), ""All Balanced"")"),"All Balanced") -> All Balanced | AG14: =IFERROR(__xludf.DUMMYFUNCTION("IFERROR(TEXTJOIN("", "", TRUE, FILTER(Orders!$I$2:$I$3000, (Orders!$M$2:$M$3000=""Delivered"") * (Orders!$N$2:$N$3000<>""Paid"") * (Orders!$Z$2:$Z$3000=$A14))), """")"),"") | AH14: =COUNTIFS(Orders!$M:$M, "Delivered", Orders!$N:$N, "<>Paid", Orders!$Z:$Z, $A14) -> 0
A15: 46002 | B15: =C15/Y15 -> 3448.9583 | C15: =SUMIFS(Orders!$H:$H, Orders!$Z:$Z, $A15, Orders!$M:$M, "Delivered") -> 82775 | D15: =SUMIFS(Orders!$Q:$Q, Orders!$Z:$Z, $A15, Orders!$M:$M, "Delivered") -> 31615 | E15: =D15/C15 -> 0.38193899 | F15: =C15-(C15*4/100) -> 79464 | G15: =C15-F15 -> 3311 | H15: =C15-D15 -> 51160 | I15: =IFERROR(J15/C15, 0)*100 -> 32.705056 | J15: 27071.61 | L15: =(200*W15)+C15*4% -> 10711 | M15: =SUMIFS(Orders!$W:$W, Orders!$Z:$Z, $A15) -> 10944.16 | N15: =H15-J15-K15-M15 -> 13144.23 | O15: =Y15/W15*100 -> 64.864865 | P15: 5.6255955 | Q15: =J15/S15 -> 676.79025 | R15: =J15/W15 -> 731.66514 | S15: =COUNTIFS(Orders!$Z:$Z, $A15) -> 40 | T15: =COUNTIFS(Orders!$Z:$Z, $A15, Orders!$M:$M, "Cancelled") -> 3 | U15: =T15/S15 -> 0.075 | V15: =COUNTIFS(Orders!$Z:$Z, $A15, Orders!$M:$M, "pending") -> 0 | W15: =S15-T15 -> 37 | X15: =W15/S15 -> 0.925 | Y15: =COUNTIFS(Orders!$Z:$Z, $A15, Orders!$M:$M, "Delivered") -> 24 | Z15: =COUNTIFS(Orders!$Z:$Z, $A15, Orders!$M:$M, "Return Received") -> 13 | AA15: =W15-Y15-Z15-V15 -> 0 | AB15: {=SUM(COUNTIFS(Orders!$Z:$Z, $A15, Orders!$M:$M, {"Returned","Returned to Shipper"}))} -> 0 | AC15: =COUNTIFS(Orders!$Z:$Z, $A15, Orders!$I:$I, "", Orders!$M:$M, "<>Cancelled") -> 0 | AD15: =SUMIFS(Orders!$U:$U, Orders!$Z:$Z, $A15, Orders!$M:$M, "Delivered") -> 82775 | AE15: =C15-AD15 -> 0 | AF15: =IFERROR(__xludf.DUMMYFUNCTION("IFERROR(TEXTJOIN("", "", TRUE, FILTER(Orders!$B$2:$B$2517, (TEXT(Orders!$D$2:$D$2517,""d-mmm"")=TEXT($A15,""d-mmm"")) * (ABS(Orders!$H$2:$H$2517 - Orders!$U$2:$U$2517) >= 1) * (Orders!$M$2:$M$2517=""Delivered""))), ""All Balanced"")"),"All Balanced") -> All Balanced | AG15: =IFERROR(__xludf.DUMMYFUNCTION("IFERROR(TEXTJOIN("", "", TRUE, FILTER(Orders!$I$2:$I$3000, (Orders!$M$2:$M$3000=""Delivered"") * (Orders!$N$2:$N$3000<>""Paid"") * (Orders!$Z$2:$Z$3000=$A15))), """")"),"") | AH15: =COUNTIFS(Orders!$M:$M, "Delivered", Orders!$N:$N, "<>Paid", Orders!$Z:$Z, $A15) -> 0
A16: 46003 | B16: =C16/Y16 -> 3021.2581 | C16: =SUMIFS(Orders!$H:$H, Orders!$Z:$Z, $A16, Orders!$M:$M, "Delivered") -> 93659 | D16: =SUMIFS(Orders!$Q:$Q, Orders!$Z:$Z, $A16, Orders!$M:$M, "Delivered") -> 32815 | E16: =D16/C16 -> 0.35036676 | F16: =C16-(C16*4/100) -> 89912.64 | G16: =C16-F16 -> 3746.36 | H16: =C16-D16 -> 60844 | I16: =IFERROR(J16/C16, 0)*100 -> 29.619994 | J16: 27741.79 | L16: =(200*W16)+C16*4% -> 12346.36 | M16: =SUMIFS(Orders!$W:$W, Orders!$Z:$Z, $A16) -> 12480.2 | N16: =H16-J16-K16-M16 -> 20622.01 | O16: =Y16/W16*100 -> 72.093023 | P16: 5.8835891 | Q16: =J16/S16 -> 554.8358 | R16: =J16/W16 -> 645.15791 | S16: =COUNTIFS(Orders!$Z:$Z, $A16) -> 50 | T16: =COUNTIFS(Orders!$Z:$Z, $A16, Orders!$M:$M, "Cancelled") -> 7 | U16: =T16/S16 -> 0.14 | V16: =COUNTIFS(Orders!$Z:$Z, $A16, Orders!$M:$M, "pending") -> 0 | W16: =S16-T16 -> 43 | X16: =W16/S16 -> 0.86 | Y16: =COUNTIFS(Orders!$Z:$Z, $A16, Orders!$M:$M, "Delivered") -> 31 | Z16: =COUNTIFS(Orders!$Z:$Z, $A16, Orders!$M:$M, "Return Received") -> 12 | AA16: =W16-Y16-Z16-V16 -> 0 | AB16: {=SUM(COUNTIFS(Orders!$Z:$Z, $A16, Orders!$M:$M, {"Returned","Returned to Shipper"}))} -> 0 | AC16: =COUNTIFS(Orders!$Z:$Z, $A16, Orders!$I:$I, "", Orders!$M:$M, "<>Cancelled") -> 0 | AD16: =SUMIFS(Orders!$U:$U, Orders!$Z:$Z, $A16, Orders!$M:$M, "Delivered") -> 93659 | AE16: =C16-AD16 -> 0 | AF16: =IFERROR(__xludf.DUMMYFUNCTION("IFERROR(TEXTJOIN("", "", TRUE, FILTER(Orders!$B$2:$B$2517, (TEXT(Orders!$D$2:$D$2517,""d-mmm"")=TEXT($A16,""d-mmm"")) * (ABS(Orders!$H$2:$H$2517 - Orders!$U$2:$U$2517) >= 1) * (Orders!$M$2:$M$2517=""Delivered""))), ""All Balanced"")"),"All Balanced") -> All Balanced | AG16: =IFERROR(__xludf.DUMMYFUNCTION("IFERROR(TEXTJOIN("", "", TRUE, FILTER(Orders!$I$2:$I$3000, (Orders!$M$2:$M$3000=""Delivered"") * (Orders!$N$2:$N$3000<>""Paid"") * (Orders!$Z$2:$Z$3000=$A16))), """")"),"") | AH16: =COUNTIFS(Orders!$M:$M, "Delivered", Orders!$N:$N, "<>Paid", Orders!$Z:$Z, $A16) -> 0
A17: 46004 | B17: =C17/Y17 -> 2908.76 | C17: =SUMIFS(Orders!$H:$H, Orders!$Z:$Z, $A17, Orders!$M:$M, "Delivered") -> 72719 | D17: =SUMIFS(Orders!$Q:$Q, Orders!$Z:$Z, $A17, Orders!$M:$M, "Delivered") -> 24860 | E17: =D17/C17 -> 0.34186389 | F17: =C17-(C17*4/100) -> 69810.24 | G17: =C17-F17 -> 2908.76 | H17: =C17-D17 -> 47859 | I17: =IFERROR(J17/C17, 0)*100 -> 39.272652 | J17: 28558.68 | L17: =(200*W17)+C17*4% -> 10708.76 | M17: =SUMIFS(Orders!$W:$W, Orders!$Z:$Z, $A17) -> 10993.4 | N17: =H17-J17-K17-M17 -> 8306.92 | O17: =Y17/W17*100 -> 64.102564 | P17: 5.2264348 | Q17: =J17/S17 -> 607.63149 | R17: =J17/W17 -> 732.27385 | S17: =COUNTIFS(Orders!$Z:$Z, $A17) -> 47 | T17: =COUNTIFS(Orders!$Z:$Z, $A17, Orders!$M:$M, "Cancelled") -> 8 | U17: =T17/S17 -> 0.17021277 | V17: =COUNTIFS(Orders!$Z:$Z, $A17, Orders!$M:$M, "pending") -> 0 | W17: =S17-T17 -> 39 | X17: =W17/S17 -> 0.82978723 | Y17: =COUNTIFS(Orders!$Z:$Z, $A17, Orders!$M:$M, "Delivered") -> 25 | Z17: =COUNTIFS(Orders!$Z:$Z, $A17, Orders!$M:$M, "Return Received") -> 14 | AA17: =W17-Y17-Z17-V17 -> 0 | AB17: {=SUM(COUNTIFS(Orders!$Z:$Z, $A17, Orders!$M:$M, {"Returned","Returned to Shipper"}))} -> 0 | AC17: =COUNTIFS(Orders!$Z:$Z, $A17, Orders!$I:$I, "", Orders!$M:$M, "<>Cancelled") -> 0 | AD17: =SUMIFS(Orders!$U:$U, Orders!$Z:$Z, $A17, Orders!$M:$M, "Delivered") -> 72719 | AE17: =C17-AD17 -> 0 | AF17: =IFERROR(__xludf.DUMMYFUNCTION("IFERROR(TEXTJOIN("", "", TRUE, FILTER(Orders!$B$2:$B$2517, (TEXT(Orders!$D$2:$D$2517,""d-mmm"")=TEXT($A17,""d-mmm"")) * (ABS(Orders!$H$2:$H$2517 - Orders!$U$2:$U$2517) >= 1) * (Orders!$M$2:$M$2517=""Delivered""))), ""All Balanced"")"),"All Balanced") -> All Balanced | AG17: =IFERROR(__xludf.DUMMYFUNCTION("IFERROR(TEXTJOIN("", "", TRUE, FILTER(Orders!$I$2:$I$3000, (Orders!$M$2:$M$3000=""Delivered"") * (Orders!$N$2:$N$3000<>""Paid"") * (Orders!$Z$2:$Z$3000=$A17))), """")"),"") | AH17: =COUNTIFS(Orders!$M:$M, "Delivered", Orders!$N:$N, "<>Paid", Orders!$Z:$Z, $A17) -> 0
A18: 46005 | B18: =C18/Y18 -> 2999.4865 | C18: =SUMIFS(Orders!$H:$H, Orders!$Z:$Z, $A18, Orders!$M:$M, "Delivered") -> 110981 | D18: =SUMIFS(Orders!$Q:$Q, Orders!$Z:$Z, $A18, Orders!$M:$M, "Delivered") -> 43000 | E18: =D18/C18 -> 0.38745371 | F18: =C18-(C18*4/100) -> 106541.76 | G18: =C18-F18 -> 4439.24 | H18: =C18-D18 -> 67981 | I18: =IFERROR(J18/C18, 0)*100 -> 30.404367 | J18: 33743.07 | L18: =(200*W18)+C18*4% -> 13839.24 | M18: =SUMIFS(Orders!$W:$W, Orders!$Z:$Z, $A18) -> 14889.12 | N18: =H18-J18-K18-M18 -> 19348.81 | O18: =Y18/W18*100 -> 78.723404 | P18: 5.2691201 | Q18: =J18/S18 -> 648.90519 | R18: =J18/W18 -> 717.93766 | S18: =COUNTIFS(Orders!$Z:$Z, $A18) -> 52 | T18: =COUNTIFS(Orders!$Z:$Z, $A18, Orders!$M:$M, "Cancelled") -> 5 | U18: =T18/S18 -> 0.096153846 | V18: =COUNTIFS(Orders!$Z:$Z, $A18, Orders!$M:$M, "pending") -> 0 | W18: =S18-T18 -> 47 | X18: =W18/S18 -> 0.90384615 | Y18: =COUNTIFS(Orders!$Z:$Z, $A18, Orders!$M:$M, "Delivered") -> 37 | Z18: =COUNTIFS(Orders!$Z:$Z, $A18, Orders!$M:$M, "Return Received") -> 10 | AA18: =W18-Y18-Z18-V18 -> 0 | AB18: {=SUM(COUNTIFS(Orders!$Z:$Z, $A18, Orders!$M:$M, {"Returned","Returned to Shipper"}))} -> 0 | AC18: =COUNTIFS(Orders!$Z:$Z, $A18, Orders!$I:$I, "", Orders!$M:$M, "<>Cancelled") -> 0 | AD18: =SUMIFS(Orders!$U:$U, Orders!$Z:$Z, $A18, Orders!$M:$M, "Delivered") -> 110981 | AE18: =C18-AD18 -> 0 | AF18: =IFERROR(__xludf.DUMMYFUNCTION("IFERROR(TEXTJOIN("", "", TRUE, FILTER(Orders!$B$2:$B$2517, (TEXT(Orders!$D$2:$D$2517,""d-mmm"")=TEXT($A18,""d-mmm"")) * (ABS(Orders!$H$2:$H$2517 - Orders!$U$2:$U$2517) >= 1) * (Orders!$M$2:$M$2517=""Delivered""))), ""All Balanced"")"),"All Balanced") -> All Balanced | AG18: =IFERROR(__xludf.DUMMYFUNCTION("IFERROR(TEXTJOIN("", "", TRUE, FILTER(Orders!$I$2:$I$3000, (Orders!$M$2:$M$3000=""Delivered"") * (Orders!$N$2:$N$3000<>""Paid"") * (Orders!$Z$2:$Z$3000=$A18))), """")"),"") | AH18: =COUNTIFS(Orders!$M:$M, "Delivered", Orders!$N:$N, "<>Paid", Orders!$Z:$Z, $A18) -> 0
A19: 46006 | B19: =C19/Y19 -> 2941.7143 | C19: =SUMIFS(Orders!$H:$H, Orders!$Z:$Z, $A19, Orders!$M:$M, "Delivered") -> 82368 | D19: =SUMIFS(Orders!$Q:$Q, Orders!$Z:$Z, $A19, Orders!$M:$M, "Delivered") -> 30960 | E19: =D19/C19 -> 0.37587413 | F19: =C19-(C19*4/100) -> 79073.28 | G19: =C19-F19 -> 3294.72 | H19: =C19-D19 -> 51408 | I19: =IFERROR(J19/C19, 0)*100 -> 39.579218 | J19: 32600.61 | L19: =(200*W19)+C19*4% -> 10494.72 | M19: =SUMIFS(Orders!$W:$W, Orders!$Z:$Z, $A19) -> 10051.76 | N19: =H19-J19-K19-M19 -> 8755.63 | O19: =Y19/W19*100 -> 77.777778 | P19: 3.5750341 | Q19: =J19/S19 -> 881.09757 | R19: =J19/W19 -> 905.5725 | S19: =COUNTIFS(Orders!$Z:$Z, $A19) -> 37 | T19: =COUNTIFS(Orders!$Z:$Z, $A19, Orders!$M:$M, "Cancelled") -> 1 | U19: =T19/S19 -> 0.027027027 | V19: =COUNTIFS(Orders!$Z:$Z, $A19, Orders!$M:$M, "pending") -> 0 | W19: =S19-T19 -> 36 | X19: =W19/S19 -> 0.97297297 | Y19: =COUNTIFS(Orders!$Z:$Z, $A19, Orders!$M:$M, "Delivered") -> 28 | Z19: =COUNTIFS(Orders!$Z:$Z, $A19, Orders!$M:$M, "Return Received") -> 8 | AA19: =W19-Y19-Z19-V19 -> 0 | AB19: {=SUM(COUNTIFS(Orders!$Z:$Z, $A19, Orders!$M:$M, {"Returned","Returned to Shipper"}))} -> 0 | AC19: =COUNTIFS(Orders!$Z:$Z, $A19, Orders!$I:$I, "", Orders!$M:$M, "<>Cancelled") -> 0 | AD19: =SUMIFS(Orders!$U:$U, Orders!$Z:$Z, $A19, Orders!$M:$M, "Delivered") -> 82368 | AE19: =C19-AD19 -> 0 | AF19: =IFERROR(__xludf.DUMMYFUNCTION("IFERROR(TEXTJOIN("", "", TRUE, FILTER(Orders!$B$2:$B$2517, (TEXT(Orders!$D$2:$D$2517,""d-mmm"")=TEXT($A19,""d-mmm"")) * (ABS(Orders!$H$2:$H$2517 - Orders!$U$2:$U$2517) >= 1) * (Orders!$M$2:$M$2517=""Delivered""))), ""All Balanced"")"),"All Balanced") -> All Balanced | AG19: =IFERROR(__xludf.DUMMYFUNCTION("IFERROR(TEXTJOIN("", "", TRUE, FILTER(Orders!$I$2:$I$3000, (Orders!$M$2:$M$3000=""Delivered"") * (Orders!$N$2:$N$3000<>""Paid"") * (Orders!$Z$2:$Z$3000=$A19))), """")"),"") | AH19: =COUNTIFS(Orders!$M:$M, "Delivered", Orders!$N:$N, "<>Paid", Orders!$Z:$Z, $A19) -> 0
A20: 46007 | B20: =C20/Y20 -> 3204.2143 | C20: =SUMIFS(Orders!$H:$H, Orders!$Z:$Z, $A20, Orders!$M:$M, "Delivered") -> 89718 | D20: =SUMIFS(Orders!$Q:$Q, Orders!$Z:$Z, $A20, Orders!$M:$M, "Delivered") -> 34490 | E20: =D20/C20 -> 0.38442676 | F20: =C20-(C20*4/100) -> 86129.28 | G20: =C20-F20 -> 3588.72 | H20: =C20-D20 -> 55228 | I20: =IFERROR(J20/C20, 0)*100 -> 41.247877 | J20: 37006.77 | L20: =(200*W20)+C20*4% -> 12788.72 | M20: =SUMIFS(Orders!$W:$W, Orders!$Z:$Z, $A20) -> 12753.68 | N20: =H20-J20-K20-M20 -> 5467.55 | O20: =Y20/W20*100 -> 60.869565 | P20: 5.4494431 | Q20: =J20/S20 -> 672.85036 | R20: =J20/W20 -> 804.495 | S20: =COUNTIFS(Orders!$Z:$Z, $A20) -> 55 | T20: =COUNTIFS(Orders!$Z:$Z, $A20, Orders!$M:$M, "Cancelled") -> 9 | U20: =T20/S20 -> 0.16363636 | V20: =COUNTIFS(Orders!$Z:$Z, $A20, Orders!$M:$M, "pending") -> 0 | W20: =S20-T20 -> 46 | X20: =W20/S20 -> 0.83636364 | Y20: =COUNTIFS(Orders!$Z:$Z, $A20, Orders!$M:$M, "Delivered") -> 28 | Z20: =COUNTIFS(Orders!$Z:$Z, $A20, Orders!$M:$M, "Return Received") -> 18 | AA20: =W20-Y20-Z20-V20 -> 0 | AB20: {=SUM(COUNTIFS(Orders!$Z:$Z, $A20, Orders!$M:$M, {"Returned","Returned to Shipper"}))} -> 0 | AC20: =COUNTIFS(Orders!$Z:$Z, $A20, Orders!$I:$I, "", Orders!$M:$M, "<>Cancelled") -> 0 | AD20: =SUMIFS(Orders!$U:$U, Orders!$Z:$Z, $A20, Orders!$M:$M, "Delivered") -> 89718 | AE20: =C20-AD20 -> 0 | AF20: =IFERROR(__xludf.DUMMYFUNCTION("IFERROR(TEXTJOIN("", "", TRUE, FILTER(Orders!$B$2:$B$2517, (TEXT(Orders!$D$2:$D$2517,""d-mmm"")=TEXT($A20,""d-mmm"")) * (ABS(Orders!$H$2:$H$2517 - Orders!$U$2:$U$2517) >= 1) * (Orders!$M$2:$M$2517=""Delivered""))), ""All Balanced"")"),"All Balanced") -> All Balanced | AG20: =IFERROR(__xludf.DUMMYFUNCTION("IFERROR(TEXTJOIN("", "", TRUE, FILTER(Orders!$I$2:$I$3000, (Orders!$M$2:$M$3000=""Delivered"") * (Orders!$N$2:$N$3000<>""Paid"") * (Orders!$Z$2:$Z$3000=$A20))), """")"),"") | AH20: =COUNTIFS(Orders!$M:$M, "Delivered", Orders!$N:$N, "<>Paid", Orders!$Z:$Z, $A20) -> 0
A21: 46008 | B21: =C21/Y21 -> 3336.4583 | C21: =SUMIFS(Orders!$H:$H, Orders!$Z:$Z, $A21, Orders!$M:$M, "Delivered") -> 80075 | D21: =SUMIFS(Orders!$Q:$Q, Orders!$Z:$Z, $A21, Orders!$M:$M, "Delivered") -> 32770 | E21: =D21/C21 -> 0.40924134 | F21: =C21-(C21*4/100) -> 76872 | G21: =C21-F21 -> 3203 | H21: =C21-D21 -> 47305 | I21: =IFERROR(J21/C21, 0)*100 -> 38.305963 | J21: 30673.5 | L21: =(200*W21)+C21*4% -> 11603 | M21: =SUMIFS(Orders!$W:$W, Orders!$Z:$Z, $A21) -> 11552.5 | N21: =H21-J21-K21-M21 -> 5079 | O21: =Y21/W21*100 -> 57.142857 | P21: 5.7939753 | Q21: =J21/S21 -> 578.74528 | R21: =J21/W21 -> 730.32143 | S21: =COUNTIFS(Orders!$Z:$Z, $A21) -> 53 | T21: =COUNTIFS(Orders!$Z:$Z, $A21, Orders!$M:$M, "Cancelled") -> 11 | U21: =T21/S21 -> 0.20754717 | V21: =COUNTIFS(Orders!$Z:$Z, $A21, Orders!$M:$M, "pending") -> 0 | W21: =S21-T21 -> 42 | X21: =W21/S21 -> 0.79245283 | Y21: =COUNTIFS(Orders!$Z:$Z, $A21, Orders!$M:$M, "Delivered") -> 24 | Z21: =COUNTIFS(Orders!$Z:$Z, $A21, Orders!$M:$M, "Return Received") -> 17 | AA21: =W21-Y21-Z21-V21 -> 1 | AB21: {=SUM(COUNTIFS(Orders!$Z:$Z, $A21, Orders!$M:$M, {"Returned","Returned to Shipper"}))} -> 1 | AC21: =COUNTIFS(Orders!$Z:$Z, $A21, Orders!$I:$I, "", Orders!$M:$M, "<>Cancelled") -> 0 | AD21: =SUMIFS(Orders!$U:$U, Orders!$Z:$Z, $A21, Orders!$M:$M, "Delivered") -> 80075 | AE21: =C21-AD21 -> 0 | AF21: =IFERROR(__xludf.DUMMYFUNCTION("IFERROR(TEXTJOIN("", "", TRUE, FILTER(Orders!$B$2:$B$2517, (TEXT(Orders!$D$2:$D$2517,""d-mmm"")=TEXT($A21,""d-mmm"")) * (ABS(Orders!$H$2:$H$2517 - Orders!$U$2:$U$2517) >= 1) * (Orders!$M$2:$M$2517=""Delivered""))), ""All Balanced"")"),"All Balanced") -> All Balanced | AG21: =IFERROR(__xludf.DUMMYFUNCTION("IFERROR(TEXTJOIN("", "", TRUE, FILTER(Orders!$I$2:$I$3000, (Orders!$M$2:$M$3000=""Delivered"") * (Orders!$N$2:$N$3000<>""Paid"") * (Orders!$Z$2:$Z$3000=$A21))), """")"),"") | AH21: =COUNTIFS(Orders!$M:$M, "Delivered", Orders!$N:$N, "<>Paid", Orders!$Z:$Z, $A21) -> 0
A22: 46009 | B22: =C22/Y22 -> 3229.5161 | C22: =SUMIFS(Orders!$H:$H, Orders!$Z:$Z, $A22, Orders!$M:$M, "Delivered") -> 100115 | D22: =SUMIFS(Orders!$Q:$Q, Orders!$Z:$Z, $A22, Orders!$M:$M, "Delivered") -> 37650 | E22: =D22/C22 -> 0.37606752 | F22: =C22-(C22*4/100) -> 96110.4 | G22: =C22-F22 -> 4004.6 | H22: =C22-D22 -> 62465 | I22: =IFERROR(J22/C22, 0)*100 -> 31.213325 | J22: 31249.22 | L22: =(200*W22)+C22*4% -> 12404.6 | M22: =SUMIFS(Orders!$W:$W, Orders!$Z:$Z, $A22) -> 12017.51 | N22: =H22-J22-K22-M22 -> 19198.27 | O22: =Y22/W22*100 -> 73.809524 | P22: 5.1819343 | Q22: =J22/S22 -> 651.02542 | R22: =J22/W22 -> 744.02905 | S22: =COUNTIFS(Orders!$Z:$Z, $A22) -> 48 | T22: =COUNTIFS(Orders!$Z:$Z, $A22, Orders!$M:$M, "Cancelled") -> 6 | U22: =T22/S22 -> 0.125 | V22: =COUNTIFS(Orders!$Z:$Z, $A22, Orders!$M:$M, "pending") -> 0 | W22: =S22-T22 -> 42 | X22: =W22/S22 -> 0.875 | Y22: =COUNTIFS(Orders!$Z:$Z, $A22, Orders!$M:$M, "Delivered") -> 31 | Z22: =COUNTIFS(Orders!$Z:$Z, $A22, Orders!$M:$M, "Return Received") -> 11 | AA22: =W22-Y22-Z22-V22 -> 0 | AB22: {=SUM(COUNTIFS(Orders!$Z:$Z, $A22, Orders!$M:$M, {"Returned","Returned to Shipper"}))} -> 0 | AC22: =COUNTIFS(Orders!$Z:$Z, $A22, Orders!$I:$I, "", Orders!$M:$M, "<>Cancelled") -> 0 | AD22: =SUMIFS(Orders!$U:$U, Orders!$Z:$Z, $A22, Orders!$M:$M, "Delivered") -> 100115 | AE22: =C22-AD22 -> 0 | AF22: =IFERROR(__xludf.DUMMYFUNCTION("IFERROR(TEXTJOIN("", "", TRUE, FILTER(Orders!$B$2:$B$2517, (TEXT(Orders!$D$2:$D$2517,""d-mmm"")=TEXT($A22,""d-mmm"")) * (ABS(Orders!$H$2:$H$2517 - Orders!$U$2:$U$2517) >= 1) * (Orders!$M$2:$M$2517=""Delivered""))), ""All Balanced"")"),"All Balanced") -> All Balanced | AG22: =IFERROR(__xludf.DUMMYFUNCTION("IFERROR(TEXTJOIN("", "", TRUE, FILTER(Orders!$I$2:$I$3000, (Orders!$M$2:$M$3000=""Delivered"") * (Orders!$N$2:$N$3000<>""Paid"") * (Orders!$Z$2:$Z$3000=$A22))), """")"),"") | AH22: =COUNTIFS(Orders!$M:$M, "Delivered", Orders!$N:$N, "<>Paid", Orders!$Z:$Z, $A22) -> 0
A23: 46010 | B23: =C23/Y23 -> 3195.5333 | C23: =SUMIFS(Orders!$H:$H, Orders!$Z:$Z, $A23, Orders!$M:$M, "Delivered") -> 95866 | D23: =SUMIFS(Orders!$Q:$Q, Orders!$Z:$Z, $A23, Orders!$M:$M, "Delivered") -> 36170 | E23: =D23/C23 -> 0.37729748 | F23: =C23-(C23*4/100) -> 92031.36 | G23: =C23-F23 -> 3834.64 | H23: =C23-D23 -> 59696 | I23: =IFERROR(J23/C23, 0)*100 -> 35.795235 | J23: 34315.46 | L23: =(200*W23)+C23*4% -> 11834.64 | M23: =SUMIFS(Orders!$W:$W, Orders!$Z:$Z, $A23) -> 11266.64 | N23: =H23-J23-K23-M23 -> 14113.9 | O23: =Y23/W23*100 -> 75 | P23: 4.6637584 | Q23: =J23/S23 -> 672.85216 | R23: =J23/W23 -> 857.8865 | S23: =COUNTIFS(Orders!$Z:$Z, $A23) -> 51 | T23: =COUNTIFS(Orders!$Z:$Z, $A23, Orders!$M:$M, "Cancelled") -> 11 | U23: =T23/S23 -> 0.21568627 | V23: =COUNTIFS(Orders!$Z:$Z, $A23, Orders!$M:$M, "pending") -> 0 | W23: =S23-T23 -> 40 | X23: =W23/S23 -> 0.78431373 | Y23: =COUNTIFS(Orders!$Z:$Z, $A23, Orders!$M:$M, "Delivered") -> 30 | Z23: =COUNTIFS(Orders!$Z:$Z, $A23, Orders!$M:$M, "Return Received") -> 10 | AA23: =W23-Y23-Z23-V23 -> 0 | AB23: {=SUM(COUNTIFS(Orders!$Z:$Z, $A23, Orders!$M:$M, {"Returned","Returned to Shipper"}))} -> 0 | AC23: =COUNTIFS(Orders!$Z:$Z, $A23, Orders!$I:$I, "", Orders!$M:$M, "<>Cancelled") -> 0 | AD23: =SUMIFS(Orders!$U:$U, Orders!$Z:$Z, $A23, Orders!$M:$M, "Delivered") -> 95866 | AE23: =C23-AD23 -> 0 | AF23: =IFERROR(__xludf.DUMMYFUNCTION("IFERROR(TEXTJOIN("", "", TRUE, FILTER(Orders!$B$2:$B$2517, (TEXT(Orders!$D$2:$D$2517,""d-mmm"")=TEXT($A23,""d-mmm"")) * (ABS(Orders!$H$2:$H$2517 - Orders!$U$2:$U$2517) >= 1) * (Orders!$M$2:$M$2517=""Delivered""))), ""All Balanced"")"),"All Balanced") -> All Balanced | AG23: =IFERROR(__xludf.DUMMYFUNCTION("IFERROR(TEXTJOIN("", "", TRUE, FILTER(Orders!$I$2:$I$3000, (Orders!$M$2:$M$3000=""Delivered"") * (Orders!$N$2:$N$3000<>""Paid"") * (Orders!$Z$2:$Z$3000=$A23))), """")"),"") | AH23: =COUNTIFS(Orders!$M:$M, "Delivered", Orders!$N:$N, "<>Paid", Orders!$Z:$Z, $A23) -> 0
A24: 46011 | B24: =C24/Y24 -> 3361.5652 | C24: =SUMIFS(Orders!$H:$H, Orders!$Z:$Z, $A24, Orders!$M:$M, "Delivered") -> 77316 | D24: =SUMIFS(Orders!$Q:$Q, Orders!$Z:$Z, $A24, Orders!$M:$M, "Delivered") -> 31305 | E24: =D24/C24 -> 0.40489679 | F24: =C24-(C24*4/100) -> 74223.36 | G24: =C24-F24 -> 3092.64 | H24: =C24-D24 -> 46011 | I24: =IFERROR(J24/C24, 0)*100 -> 39.296407 | J24: 30382.41 | L24: =(200*W24)+C24*4% -> 10292.64 | M24: =SUMIFS(Orders!$W:$W, Orders!$Z:$Z, $A24) -> 10704.84 | N24: =H24-J24-K24-M24 -> 4923.75 | O24: =Y24/W24*100 -> 63.888889 | P24: 5.1762522 | Q24: =J24/S24 -> 706.56767 | R24: =J24/W24 -> 843.95583 | S24: =COUNTIFS(Orders!$Z:$Z, $A24) -> 43 | T24: =COUNTIFS(Orders!$Z:$Z, $A24, Orders!$M:$M, "Cancelled") -> 7 | U24: =T24/S24 -> 0.1627907 | V24: =COUNTIFS(Orders!$Z:$Z, $A24, Orders!$M:$M, "pending") -> 0 | W24: =S24-T24 -> 36 | X24: =W24/S24 -> 0.8372093 | Y24: =COUNTIFS(Orders!$Z:$Z, $A24, Orders!$M:$M, "Delivered") -> 23 | Z24: =COUNTIFS(Orders!$Z:$Z, $A24, Orders!$M:$M, "Return Received") -> 13 | AA24: =W24-Y24-Z24-V24 -> 0 | AB24: {=SUM(COUNTIFS(Orders!$Z:$Z, $A24, Orders!$M:$M, {"Returned","Returned to Shipper"}))} -> 0 | AC24: =COUNTIFS(Orders!$Z:$Z, $A24, Orders!$I:$I, "", Orders!$M:$M, "<>Cancelled") -> 0 | AD24: =SUMIFS(Orders!$U:$U, Orders!$Z:$Z, $A24, Orders!$M:$M, "Delivered") -> 77316 | AE24: =C24-AD24 -> 0 | AF24: =IFERROR(__xludf.DUMMYFUNCTION("IFERROR(TEXTJOIN("", "", TRUE, FILTER(Orders!$B$2:$B$2517, (TEXT(Orders!$D$2:$D$2517,""d-mmm"")=TEXT($A24,""d-mmm"")) * (ABS(Orders!$H$2:$H$2517 - Orders!$U$2:$U$2517) >= 1) * (Orders!$M$2:$M$2517=""Delivered""))), ""All Balanced"")"),"All Balanced") -> All Balanced | AG24: =IFERROR(__xludf.DUMMYFUNCTION("IFERROR(TEXTJOIN("", "", TRUE, FILTER(Orders!$I$2:$I$3000, (Orders!$M$2:$M$3000=""Delivered"") * (Orders!$N$2:$N$3000<>""Paid"") * (Orders!$Z$2:$Z$3000=$A24))), """")"),"") | AH24: =COUNTIFS(Orders!$M:$M, "Delivered", Orders!$N:$N, "<>Paid", Orders!$Z:$Z, $A24) -> 0
A25: 46012 | B25: =C25/Y25 -> 3366.3077 | C25: =SUMIFS(Orders!$H:$H, Orders!$Z:$Z, $A25, Orders!$M:$M, "Delivered") -> 87524 | D25: =SUMIFS(Orders!$Q:$Q, Orders!$Z:$Z, $A25, Orders!$M:$M, "Delivered") -> 31780 | E25: =D25/C25 -> 0.36310041 | F25: =C25-(C25*4/100) -> 84023.04 | G25: =C25-F25 -> 3500.96 | H25: =C25-D25 -> 55744 | I25: =IFERROR(J25/C25, 0)*100 -> 43.987089 | J25: 38499.26 | L25: =(200*W25)+C25*4% -> 11500.96 | M25: =SUMIFS(Orders!$W:$W, Orders!$Z:$Z, $A25) -> 11933.9 | N25: =H25-J25-K25-M25 -> 5310.84 | O25: =Y25/W25*100 -> 65 | P25: 3.9601044 | Q25: =J25/S25 -> 916.64905 | R25: =J25/W25 -> 962.4815 | S25: =COUNTIFS(Orders!$Z:$Z, $A25) -> 42 | T25: =COUNTIFS(Orders!$Z:$Z, $A25, Orders!$M:$M, "Cancelled") -> 2 | U25: =T25/S25 -> 0.047619048 | V25: =COUNTIFS(Orders!$Z:$Z, $A25, Orders!$M:$M, "pending") -> 0 | W25: =S25-T25 -> 40 | X25: =W25/S25 -> 0.95238095 | Y25: =COUNTIFS(Orders!$Z:$Z, $A25, Orders!$M:$M, "Delivered") -> 26 | Z25: =COUNTIFS(Orders!$Z:$Z, $A25, Orders!$M:$M, "Return Received") -> 14 | AA25: =W25-Y25-Z25-V25 -> 0 | AB25: {=SUM(COUNTIFS(Orders!$Z:$Z, $A25, Orders!$M:$M, {"Returned","Returned to Shipper"}))} -> 0 | AC25: =COUNTIFS(Orders!$Z:$Z, $A25, Orders!$I:$I, "", Orders!$M:$M, "<>Cancelled") -> 0 | AD25: =SUMIFS(Orders!$U:$U, Orders!$Z:$Z, $A25, Orders!$M:$M, "Delivered") -> 87524 | AE25: =C25-AD25 -> 0 | AF25: =IFERROR(__xludf.DUMMYFUNCTION("IFERROR(TEXTJOIN("", "", TRUE, FILTER(Orders!$B$2:$B$2517, (TEXT(Orders!$D$2:$D$2517,""d-mmm"")=TEXT($A25,""d-mmm"")) * (ABS(Orders!$H$2:$H$2517 - Orders!$U$2:$U$2517) >= 1) * (Orders!$M$2:$M$2517=""Delivered""))), ""All Balanced"")"),"All Balanced") -> All Balanced | AG25: =IFERROR(__xludf.DUMMYFUNCTION("IFERROR(TEXTJOIN("", "", TRUE, FILTER(Orders!$I$2:$I$3000, (Orders!$M$2:$M$3000=""Delivered"") * (Orders!$N$2:$N$3000<>""Paid"") * (Orders!$Z$2:$Z$3000=$A25))), """")"),"") | AH25: =COUNTIFS(Orders!$M:$M, "Delivered", Orders!$N:$N, "<>Paid", Orders!$Z:$Z, $A25) -> 0
A26: 46013 | B26: =C26/Y26 -> 3199 | C26: =SUMIFS(Orders!$H:$H, Orders!$Z:$Z, $A26, Orders!$M:$M, "Delivered") -> 51184 | D26: =SUMIFS(Orders!$Q:$Q, Orders!$Z:$Z, $A26, Orders!$M:$M, "Delivered") -> 19730 | E26: =D26/C26 -> 0.38547202 | F26: =C26-(C26*4/100) -> 49136.64 | G26: =C26-F26 -> 2047.36 | H26: =C26-D26 -> 31454 | I26: =IFERROR(J26/C26, 0)*100 -> 49.643404 | J26: 25409.48 | L26: =(200*W26)+C26*4% -> 6847.36 | M26: =SUMIFS(Orders!$W:$W, Orders!$Z:$Z, $A26) -> 7108.04 | N26: =H26-J26-K26-M26 -> -1063.52 | O26: =Y26/W26*100 -> 66.666667 | P26: 3.5560187 | Q26: =J26/S26 -> 1016.3792 | R26: =J26/W26 -> 1058.7283 | S26: =COUNTIFS(Orders!$Z:$Z, $A26) -> 25 | T26: =COUNTIFS(Orders!$Z:$Z, $A26, Orders!$M:$M, "Cancelled") -> 1 | U26: =T26/S26 -> 0.04 | V26: =COUNTIFS(Orders!$Z:$Z, $A26, Orders!$M:$M, "pending") -> 0 | W26: =S26-T26 -> 24 | X26: =W26/S26 -> 0.96 | Y26: =COUNTIFS(Orders!$Z:$Z, $A26, Orders!$M:$M, "Delivered") -> 16 | Z26: =COUNTIFS(Orders!$Z:$Z, $A26, Orders!$M:$M, "Return Received") -> 8 | AA26: =W26-Y26-Z26-V26 -> 0 | AB26: {=SUM(COUNTIFS(Orders!$Z:$Z, $A26, Orders!$M:$M, {"Returned","Returned to Shipper"}))} -> 0 | AC26: =COUNTIFS(Orders!$Z:$Z, $A26, Orders!$I:$I, "", Orders!$M:$M, "<>Cancelled") -> 0 | AD26: =SUMIFS(Orders!$U:$U, Orders!$Z:$Z, $A26, Orders!$M:$M, "Delivered") -> 51184 | AE26: =C26-AD26 -> 0 | AF26: =IFERROR(__xludf.DUMMYFUNCTION("IFERROR(TEXTJOIN("", "", TRUE, FILTER(Orders!$B$2:$B$2517, (TEXT(Orders!$D$2:$D$2517,""d-mmm"")=TEXT($A26,""d-mmm"")) * (ABS(Orders!$H$2:$H$2517 - Orders!$U$2:$U$2517) >= 1) * (Orders!$M$2:$M$2517=""Delivered""))), ""All Balanced"")"),"All Balanced") -> All Balanced | AG26: =IFERROR(__xludf.DUMMYFUNCTION("IFERROR(TEXTJOIN("", "", TRUE, FILTER(Orders!$I$2:$I$3000, (Orders!$M$2:$M$3000=""Delivered"") * (Orders!$N$2:$N$3000<>""Paid"") * (Orders!$Z$2:$Z$3000=$A26))), """")"),"") | AH26: =COUNTIFS(Orders!$M:$M, "Delivered", Orders!$N:$N, "<>Paid", Orders!$Z:$Z, $A26) -> 0
A27: 46014 | B27: =C27/Y27 -> 2973.96 | C27: =SUMIFS(Orders!$H:$H, Orders!$Z:$Z, $A27, Orders!$M:$M, "Delivered") -> 74349 | D27: =SUMIFS(Orders!$Q:$Q, Orders!$Z:$Z, $A27, Orders!$M:$M, "Delivered") -> 28485 | E27: =D27/C27 -> 0.38312553 | F27: =C27-(C27*4/100) -> 71375.04 | G27: =C27-F27 -> 2973.96 | H27: =C27-D27 -> 45864 | I27: =IFERROR(J27/C27, 0)*100 -> 36.270548 | J27: 26966.79 | L27: =(200*W27)+C27*4% -> 8973.96 | M27: =SUMIFS(Orders!$W:$W, Orders!$Z:$Z, $A27) -> 9279.76 | N27: =H27-J27-K27-M27 -> 9617.45 | O27: =Y27/W27*100 -> 83.333333 | P27: 3.9173707 | Q27: =J27/S27 -> 842.71219 | R27: =J27/W27 -> 898.893 | S27: =COUNTIFS(Orders!$Z:$Z, $A27) -> 32 | T27: =COUNTIFS(Orders!$Z:$Z, $A27, Orders!$M:$M, "Cancelled") -> 2 | U27: =T27/S27 -> 0.0625 | V27: =COUNTIFS(Orders!$Z:$Z, $A27, Orders!$M:$M, "pending") -> 0 | W27: =S27-T27 -> 30 | X27: =W27/S27 -> 0.9375 | Y27: =COUNTIFS(Orders!$Z:$Z, $A27, Orders!$M:$M, "Delivered") -> 25 | Z27: =COUNTIFS(Orders!$Z:$Z, $A27, Orders!$M:$M, "Return Received") -> 5 | AA27: =W27-Y27-Z27-V27 -> 0 | AB27: {=SUM(COUNTIFS(Orders!$Z:$Z, $A27, Orders!$M:$M, {"Returned","Returned to Shipper"}))} -> 0 | AC27: =COUNTIFS(Orders!$Z:$Z, $A27, Orders!$I:$I, "", Orders!$M:$M, "<>Cancelled") -> 0 | AD27: =SUMIFS(Orders!$U:$U, Orders!$Z:$Z, $A27, Orders!$M:$M, "Delivered") -> 74349 | AE27: =C27-AD27 -> 0 | AF27: =IFERROR(__xludf.DUMMYFUNCTION("IFERROR(TEXTJOIN("", "", TRUE, FILTER(Orders!$B$2:$B$2517, (TEXT(Orders!$D$2:$D$2517,""d-mmm"")=TEXT($A27,""d-mmm"")) * (ABS(Orders!$H$2:$H$2517 - Orders!$U$2:$U$2517) >= 1) * (Orders!$M$2:$M$2517=""Delivered""))), ""All Balanced"")"),"All Balanced") -> All Balanced | AG27: =IFERROR(__xludf.DUMMYFUNCTION("IFERROR(TEXTJOIN("", "", TRUE, FILTER(Orders!$I$2:$I$3000, (Orders!$M$2:$M$3000=""Delivered"") * (Orders!$N$2:$N$3000<>""Paid"") * (Orders!$Z$2:$Z$3000=$A27))), """")"),"") | AH27: =COUNTIFS(Orders!$M:$M, "Delivered", Orders!$N:$N, "<>Paid", Orders!$Z:$Z, $A27) -> 0
A28: 46015 | B28: =C28/Y28 -> 2917.3267 | C28: =SUMIFS(Orders!$H:$H, Orders!$Z:$Z, $A28, Orders!$M:$M, "Delivered") -> 35007.92 | D28: =SUMIFS(Orders!$Q:$Q, Orders!$Z:$Z, $A28, Orders!$M:$M, "Delivered") -> 13220 | E28: =D28/C28 -> 0.37762883 | F28: =C28-(C28*4/100) -> 33607.603 | G28: =C28-F28 -> 1400.3168 | H28: =C28-D28 -> 21787.92 | I28: =IFERROR(J28/C28, 0)*100 -> 81.631014 | J28: 28577.32 | L28: =(200*W28)+C28*4% -> 5200.3168 | M28: =SUMIFS(Orders!$W:$W, Orders!$Z:$Z, $A28) -> 5171.24 | N28: =H28-J28-K28-M28 -> -11960.64 | O28: =Y28/W28*100 -> 63.157895 | P28: 2.3913581 | Q28: =J28/S28 -> 1360.8248 | R28: =J28/W28 -> 1504.0695 | S28: =COUNTIFS(Orders!$Z:$Z, $A28) -> 21 | T28: =COUNTIFS(Orders!$Z:$Z, $A28, Orders!$M:$M, "Cancelled") -> 2 | U28: =T28/S28 -> 0.095238095 | V28: =COUNTIFS(Orders!$Z:$Z, $A28, Orders!$M:$M, "pending") -> 0 | W28: =S28-T28 -> 19 | X28: =W28/S28 -> 0.9047619 | Y28: =COUNTIFS(Orders!$Z:$Z, $A28, Orders!$M:$M, "Delivered") -> 12 | Z28: =COUNTIFS(Orders!$Z:$Z, $A28, Orders!$M:$M, "Return Received") -> 7 | AA28: =W28-Y28-Z28-V28 -> 0 | AB28: {=SUM(COUNTIFS(Orders!$Z:$Z, $A28, Orders!$M:$M, {"Returned","Returned to Shipper"}))} -> 0 | AC28: =COUNTIFS(Orders!$Z:$Z, $A28, Orders!$I:$I, "", Orders!$M:$M, "<>Cancelled") -> 0 | AD28: =SUMIFS(Orders!$U:$U, Orders!$Z:$Z, $A28, Orders!$M:$M, "Delivered") -> 35007.92 | AE28: =C28-AD28 -> 0 | AF28: =IFERROR(__xludf.DUMMYFUNCTION("IFERROR(TEXTJOIN("", "", TRUE, FILTER(Orders!$B$2:$B$2517, (TEXT(Orders!$D$2:$D$2517,""d-mmm"")=TEXT($A28,""d-mmm"")) * (ABS(Orders!$H$2:$H$2517 - Orders!$U$2:$U$2517) >= 1) * (Orders!$M$2:$M$2517=""Delivered""))), ""All Balanced"")"),"All Balanced") -> All Balanced | AG28: =IFERROR(__xludf.DUMMYFUNCTION("IFERROR(TEXTJOIN("", "", TRUE, FILTER(Orders!$I$2:$I$3000, (Orders!$M$2:$M$3000=""Delivered"") * (Orders!$N$2:$N$3000<>""Paid"") * (Orders!$Z$2:$Z$3000=$A28))), """")"),"") | AH28: =COUNTIFS(Orders!$M:$M, "Delivered", Orders!$N:$N, "<>Paid", Orders!$Z:$Z, $A28) -> 0
A29: 46016 | B29: =C29/Y29 -> 3216.1034 | C29: =SUMIFS(Orders!$H:$H, Orders!$Z:$Z, $A29, Orders!$M:$M, "Delivered") -> 93267 | D29: =SUMIFS(Orders!$Q:$Q, Orders!$Z:$Z, $A29, Orders!$M:$M, "Delivered") -> 35130 | E29: =D29/C29 -> 0.37666056 | F29: =C29-(C29*4/100) -> 89536.32 | G29: =C29-F29 -> 3730.68 | H29: =C29-D29 -> 58137 | I29: =IFERROR(J29/C29, 0)*100 -> 31.576313 | J29: 29450.28 | L29: =(200*W29)+C29*4% -> 11330.68 | M29: =SUMIFS(Orders!$W:$W, Orders!$Z:$Z, $A29) -> 11054.94 | N29: =H29-J29-K29-M29 -> 17631.78 | O29: =Y29/W29*100 -> 76.315789 | P29: 4.4002946 | Q29: =J29/S29 -> 755.13538 | R29: =J29/W29 -> 775.00737 | S29: =COUNTIFS(Orders!$Z:$Z, $A29) -> 39 | T29: =COUNTIFS(Orders!$Z:$Z, $A29, Orders!$M:$M, "Cancelled") -> 1 | U29: =T29/S29 -> 0.025641026 | V29: =COUNTIFS(Orders!$Z:$Z, $A29, Orders!$M:$M, "pending") -> 0 | W29: =S29-T29 -> 38 | X29: =W29/S29 -> 0.97435897 | Y29: =COUNTIFS(Orders!$Z:$Z, $A29, Orders!$M:$M, "Delivered") -> 29 | Z29: =COUNTIFS(Orders!$Z:$Z, $A29, Orders!$M:$M, "Return Received") -> 9 | AA29: =W29-Y29-Z29-V29 -> 0 | AB29: {=SUM(COUNTIFS(Orders!$Z:$Z, $A29, Orders!$M:$M, {"Returned","Returned to Shipper"}))} -> 0 | AC29: =COUNTIFS(Orders!$Z:$Z, $A29, Orders!$I:$I, "", Orders!$M:$M, "<>Cancelled") -> 0 | AD29: =SUMIFS(Orders!$U:$U, Orders!$Z:$Z, $A29, Orders!$M:$M, "Delivered") -> 93267 | AE29: =C29-AD29 -> 0 | AF29: =IFERROR(__xludf.DUMMYFUNCTION("IFERROR(TEXTJOIN("", "", TRUE, FILTER(Orders!$B$2:$B$2517, (TEXT(Orders!$D$2:$D$2517,""d-mmm"")=TEXT($A29,""d-mmm"")) * (ABS(Orders!$H$2:$H$2517 - Orders!$U$2:$U$2517) >= 1) * (Orders!$M$2:$M$2517=""Delivered""))), ""All Balanced"")"),"All Balanced") -> All Balanced | AG29: =IFERROR(__xludf.DUMMYFUNCTION("IFERROR(TEXTJOIN("", "", TRUE, FILTER(Orders!$I$2:$I$3000, (Orders!$M$2:$M$3000=""Delivered"") * (Orders!$N$2:$N$3000<>""Paid"") * (Orders!$Z$2:$Z$3000=$A29))), """")"),"") | AH29: =COUNTIFS(Orders!$M:$M, "Delivered", Orders!$N:$N, "<>Paid", Orders!$Z:$Z, $A29) -> 0
A30: 46017 | B30: =C30/Y30 -> 2954.1235 | C30: =SUMIFS(Orders!$H:$H, Orders!$Z:$Z, $A30, Orders!$M:$M, "Delivered") -> 67944.84 | D30: =SUMIFS(Orders!$Q:$Q, Orders!$Z:$Z, $A30, Orders!$M:$M, "Delivered") -> 24210 | E30: =D30/C30 -> 0.35631845 | F30: =C30-(C30*4/100) -> 65227.046 | G30: =C30-F30 -> 2717.7936 | H30: =C30-D30 -> 43734.84 | I30: =IFERROR(J30/C30, 0)*100 -> 39.305958 | J30: 26706.37 | L30: =(200*W30)+C30*4% -> 9317.7936 | M30: =SUMIFS(Orders!$W:$W, Orders!$Z:$Z, $A30) -> 9553.4 | N30: =H30-J30-K30-M30 -> 7475.07 | O30: =Y30/W30*100 -> 69.69697 | P30: 4.7784972 | Q30: =J30/S30 -> 702.79921 | R30: =J30/W30 -> 809.28394 | S30: =COUNTIFS(Orders!$Z:$Z, $A30) -> 38 | T30: =COUNTIFS(Orders!$Z:$Z, $A30, Orders!$M:$M, "Cancelled") -> 5 | U30: =T30/S30 -> 0.13157895 | V30: =COUNTIFS(Orders!$Z:$Z, $A30, Orders!$M:$M, "pending") -> 0 | W30: =S30-T30 -> 33 | X30: =W30/S30 -> 0.86842105 | Y30: =COUNTIFS(Orders!$Z:$Z, $A30, Orders!$M:$M, "Delivered") -> 23 | Z30: =COUNTIFS(Orders!$Z:$Z, $A30, Orders!$M:$M, "Return Received") -> 10 | AA30: =W30-Y30-Z30-V30 -> 0 | AB30: {=SUM(COUNTIFS(Orders!$Z:$Z, $A30, Orders!$M:$M, {"Returned","Returned to Shipper"}))} -> 0 | AC30: =COUNTIFS(Orders!$Z:$Z, $A30, Orders!$I:$I, "", Orders!$M:$M, "<>Cancelled") -> 0 | AD30: =SUMIFS(Orders!$U:$U, Orders!$Z:$Z, $A30, Orders!$M:$M, "Delivered") -> 67944.84 | AE30: =C30-AD30 -> 0 | AF30: =IFERROR(__xludf.DUMMYFUNCTION("IFERROR(TEXTJOIN("", "", TRUE, FILTER(Orders!$B$2:$B$2517, (TEXT(Orders!$D$2:$D$2517,""d-mmm"")=TEXT($A30,""d-mmm"")) * (ABS(Orders!$H$2:$H$2517 - Orders!$U$2:$U$2517) >= 1) * (Orders!$M$2:$M$2517=""Delivered""))), ""All Balanced"")"),"All Balanced") -> All Balanced | AG30: =IFERROR(__xludf.DUMMYFUNCTION("IFERROR(TEXTJOIN("", "", TRUE, FILTER(Orders!$I$2:$I$3000, (Orders!$M$2:$M$3000=""Delivered"") * (Orders!$N$2:$N$3000<>""Paid"") * (Orders!$Z$2:$Z$3000=$A30))), """")"),"") | AH30: =COUNTIFS(Orders!$M:$M, "Delivered", Orders!$N:$N, "<>Paid", Orders!$Z:$Z, $A30) -> 0
A31: 46018 | B31: =C31/Y31 -> 3164.52 | C31: =SUMIFS(Orders!$H:$H, Orders!$Z:$Z, $A31, Orders!$M:$M, "Delivered") -> 60125.88 | D31: =SUMIFS(Orders!$Q:$Q, Orders!$Z:$Z, $A31, Orders!$M:$M, "Delivered") -> 21215 | E31: =D31/C31 -> 0.35284307 | F31: =C31-(C31*4/100) -> 57720.845 | G31: =C31-F31 -> 2405.0352 | H31: =C31-D31 -> 38910.88 | I31: =IFERROR(J31/C31, 0)*100 -> 41.88574 | J31: 25184.17 | L31: =(200*W31)+C31*4% -> 7605.0352 | M31: =SUMIFS(Orders!$W:$W, Orders!$Z:$Z, $A31) -> 7441.67 | N31: =H31-J31-K31-M31 -> 6285.04 | O31: =Y31/W31*100 -> 73.076923 | P31: 3.9164872 | Q31: =J31/S31 -> 868.41966 | R31: =J31/W31 -> 968.62192 | S31: =COUNTIFS(Orders!$Z:$Z, $A31) -> 29 | T31: =COUNTIFS(Orders!$Z:$Z, $A31, Orders!$M:$M, "Cancelled") -> 3 | U31: =T31/S31 -> 0.10344828 | V31: =COUNTIFS(Orders!$Z:$Z, $A31, Orders!$M:$M, "pending") -> 0 | W31: =S31-T31 -> 26 | X31: =W31/S31 -> 0.89655172 | Y31: =COUNTIFS(Orders!$Z:$Z, $A31, Orders!$M:$M, "Delivered") -> 19 | Z31: =COUNTIFS(Orders!$Z:$Z, $A31, Orders!$M:$M, "Return Received") -> 7 | AA31: =W31-Y31-Z31-V31 -> 0 | AB31: {=SUM(COUNTIFS(Orders!$Z:$Z, $A31, Orders!$M:$M, {"Returned","Returned to Shipper"}))} -> 0 | AC31: =COUNTIFS(Orders!$Z:$Z, $A31, Orders!$I:$I, "", Orders!$M:$M, "<>Cancelled") -> 0 | AD31: =SUMIFS(Orders!$U:$U, Orders!$Z:$Z, $A31, Orders!$M:$M, "Delivered") -> 60125.88 | AE31: =C31-AD31 -> 0 | AF31: =IFERROR(__xludf.DUMMYFUNCTION("IFERROR(TEXTJOIN("", "", TRUE, FILTER(Orders!$B$2:$B$2517, (TEXT(Orders!$D$2:$D$2517,""d-mmm"")=TEXT($A31,""d-mmm"")) * (ABS(Orders!$H$2:$H$2517 - Orders!$U$2:$U$2517) >= 1) * (Orders!$M$2:$M$2517=""Delivered""))), ""All Balanced"")"),"All Balanced") -> All Balanced | AG31: =IFERROR(__xludf.DUMMYFUNCTION("IFERROR(TEXTJOIN("", "", TRUE, FILTER(Orders!$I$2:$I$3000, (Orders!$M$2:$M$3000=""Delivered"") * (Orders!$N$2:$N$3000<>""Paid"") * (Orders!$Z$2:$Z$3000=$A31))), """")"),"") | AH31: =COUNTIFS(Orders!$M:$M, "Delivered", Orders!$N:$N, "<>Paid", Orders!$Z:$Z, $A31) -> 0
A32: 46019 | B32: =C32/Y32 -> 3551.9167 | C32: =SUMIFS(Orders!$H:$H, Orders!$Z:$Z, $A32, Orders!$M:$M, "Delivered") -> 42623 | D32: =SUMIFS(Orders!$Q:$Q, Orders!$Z:$Z, $A32, Orders!$M:$M, "Delivered") -> 14530 | E32: =D32/C32 -> 0.34089576 | F32: =C32-(C32*4/100) -> 40918.08 | G32: =C32-F32 -> 1704.92 | H32: =C32-D32 -> 28093 | I32: =IFERROR(J32/C32, 0)*100 -> 46.501748 | J32: 19820.44 | L32: =(200*W32)+C32*4% -> 5104.92 | M32: =SUMIFS(Orders!$W:$W, Orders!$Z:$Z, $A32) -> 5510.77 | N32: =H32-J32-K32-M32 -> 2761.79 | O32: =Y32/W32*100 -> 70.588235 | P32: 4.2461148 | Q32: =J32/S32 -> 861.75826 | R32: =J32/W32 -> 1165.9082 | S32: =COUNTIFS(Orders!$Z:$Z, $A32) -> 23 | T32: =COUNTIFS(Orders!$Z:$Z, $A32, Orders!$M:$M, "Cancelled") -> 6 | U32: =T32/S32 -> 0.26086957 | V32: =COUNTIFS(Orders!$Z:$Z, $A32, Orders!$M:$M, "pending") -> 0 | W32: =S32-T32 -> 17 | X32: =W32/S32 -> 0.73913043 | Y32: =COUNTIFS(Orders!$Z:$Z, $A32, Orders!$M:$M, "Delivered") -> 12 | Z32: =COUNTIFS(Orders!$Z:$Z, $A32, Orders!$M:$M, "Return Received") -> 5 | AA32: =W32-Y32-Z32-V32 -> 0 | AB32: {=SUM(COUNTIFS(Orders!$Z:$Z, $A32, Orders!$M:$M, {"Returned","Returned to Shipper"}))} -> 0 | AC32: =COUNTIFS(Orders!$Z:$Z, $A32, Orders!$I:$I, "", Orders!$M:$M, "<>Cancelled") -> 0 | AD32: =SUMIFS(Orders!$U:$U, Orders!$Z:$Z, $A32, Orders!$M:$M, "Delivered") -> 42623 | AE32: =C32-AD32 -> 0 | AF32: =IFERROR(__xludf.DUMMYFUNCTION("IFERROR(TEXTJOIN("", "", TRUE, FILTER(Orders!$B$2:$B$2517, (TEXT(Orders!$D$2:$D$2517,""d-mmm"")=TEXT($A32,""d-mmm"")) * (ABS(Orders!$H$2:$H$2517 - Orders!$U$2:$U$2517) >= 1) * (Orders!$M$2:$M$2517=""Delivered""))), ""All Balanced"")"),"All Balanced") -> All Balanced | AG32: =IFERROR(__xludf.DUMMYFUNCTION("IFERROR(TEXTJOIN("", "", TRUE, FILTER(Orders!$I$2:$I$3000, (Orders!$M$2:$M$3000=""Delivered"") * (Orders!$N$2:$N$3000<>""Paid"") * (Orders!$Z$2:$Z$3000=$A32))), """")"),"") | AH32: =COUNTIFS(Orders!$M:$M, "Delivered", Orders!$N:$N, "<>Paid", Orders!$Z:$Z, $A32) -> 0
A33: 46020 | B33: =C33/Y33 -> 3364.2236 | C33: =SUMIFS(Orders!$H:$H, Orders!$Z:$Z, $A33, Orders!$M:$M, "Delivered") -> 74012.92 | D33: =SUMIFS(Orders!$Q:$Q, Orders!$Z:$Z, $A33, Orders!$M:$M, "Delivered") -> 25090 | E33: =D33/C33 -> 0.33899487 | F33: =C33-(C33*4/100) -> 71052.403 | G33: =C33-F33 -> 2960.5168 | H33: =C33-D33 -> 48922.92 | I33: =IFERROR(J33/C33, 0)*100 -> 32.12304 | J33: 23775.2 | L33: =(200*W33)+C33*4% -> 8160.5168 | M33: =SUMIFS(Orders!$W:$W, Orders!$Z:$Z, $A33) -> 8419.05 | N33: =H33-J33-K33-M33 -> 16728.67 | O33: =Y33/W33*100 -> 84.615385 | P33: 4.7993793 | Q33: =J33/S33 -> 720.46061 | R33: =J33/W33 -> 914.43077 | S33: =COUNTIFS(Orders!$Z:$Z, $A33) -> 33 | T33: =COUNTIFS(Orders!$Z:$Z, $A33, Orders!$M:$M, "Cancelled") -> 7 | U33: =T33/S33 -> 0.21212121 | V33: =COUNTIFS(Orders!$Z:$Z, $A33, Orders!$M:$M, "pending") -> 0 | W33: =S33-T33 -> 26 | X33: =W33/S33 -> 0.78787879 | Y33: =COUNTIFS(Orders!$Z:$Z, $A33, Orders!$M:$M, "Delivered") -> 22 | Z33: =COUNTIFS(Orders!$Z:$Z, $A33, Orders!$M:$M, "Return Received") -> 4 | AA33: =W33-Y33-Z33-V33 -> 0 | AB33: {=SUM(COUNTIFS(Orders!$Z:$Z, $A33, Orders!$M:$M, {"Returned","Returned to Shipper"}))} -> 0 | AC33: =COUNTIFS(Orders!$Z:$Z, $A33, Orders!$I:$I, "", Orders!$M:$M, "<>Cancelled") -> 0 | AD33: =SUMIFS(Orders!$U:$U, Orders!$Z:$Z, $A33, Orders!$M:$M, "Delivered") -> 74012.92 | AE33: =C33-AD33 -> 0 | AF33: =IFERROR(__xludf.DUMMYFUNCTION("IFERROR(TEXTJOIN("", "", TRUE, FILTER(Orders!$B$2:$B$2517, (TEXT(Orders!$D$2:$D$2517,""d-mmm"")=TEXT($A33,""d-mmm"")) * (ABS(Orders!$H$2:$H$2517 - Orders!$U$2:$U$2517) >= 1) * (Orders!$M$2:$M$2517=""Delivered""))), ""All Balanced"")"),"All Balanced") -> All Balanced | AG33: =IFERROR(__xludf.DUMMYFUNCTION("IFERROR(TEXTJOIN("", "", TRUE, FILTER(Orders!$I$2:$I$3000, (Orders!$M$2:$M$3000=""Delivered"") * (Orders!$N$2:$N$3000<>""Paid"") * (Orders!$Z$2:$Z$3000=$A33))), """")"),"") | AH33: =COUNTIFS(Orders!$M:$M, "Delivered", Orders!$N:$N, "<>Paid", Orders!$Z:$Z, $A33) -> 0
A34: 46021 | B34: =C34/Y34 -> 3424.0541 | C34: =SUMIFS(Orders!$H:$H, Orders!$Z:$Z, $A34, Orders!$M:$M, "Delivered") -> 58208.92 | D34: =SUMIFS(Orders!$Q:$Q, Orders!$Z:$Z, $A34, Orders!$M:$M, "Delivered") -> 22315 | E34: =D34/C34 -> 0.38336049 | F34: =C34-(C34*4/100) -> 55880.563 | G34: =C34-F34 -> 2328.3568 | H34: =C34-D34 -> 35893.92 | I34: =IFERROR(J34/C34, 0)*100 -> 42.421935 | J34: 24693.35 | L34: =(200*W34)+C34*4% -> 7328.3568 | M34: =SUMIFS(Orders!$W:$W, Orders!$Z:$Z, $A34) -> 7016.02 | N34: =H34-J34-K34-M34 -> 4184.55 | O34: =Y34/W34*100 -> 68 | P34: 4.0113558 | Q34: =J34/S34 -> 949.74423 | R34: =J34/W34 -> 987.734 | S34: =COUNTIFS(Orders!$Z:$Z, $A34) -> 26 | T34: =COUNTIFS(Orders!$Z:$Z, $A34, Orders!$M:$M, "Cancelled") -> 1 | U34: =T34/S34 -> 0.038461538 | V34: =COUNTIFS(Orders!$Z:$Z, $A34, Orders!$M:$M, "pending") -> 0 | W34: =S34-T34 -> 25 | X34: =W34/S34 -> 0.96153846 | Y34: =COUNTIFS(Orders!$Z:$Z, $A34, Orders!$M:$M, "Delivered") -> 17 | Z34: =COUNTIFS(Orders!$Z:$Z, $A34, Orders!$M:$M, "Return Received") -> 8 | AA34: =W34-Y34-Z34-V34 -> 0 | AB34: {=SUM(COUNTIFS(Orders!$Z:$Z, $A34, Orders!$M:$M, {"Returned","Returned to Shipper"}))} -> 0 | AC34: =COUNTIFS(Orders!$Z:$Z, $A34, Orders!$I:$I, "", Orders!$M:$M, "<>Cancelled") -> 0 | AD34: =SUMIFS(Orders!$U:$U, Orders!$Z:$Z, $A34, Orders!$M:$M, "Delivered") -> 58208.92 | AE34: =C34-AD34 -> 0 | AF34: =IFERROR(__xludf.DUMMYFUNCTION("IFERROR(TEXTJOIN("", "", TRUE, FILTER(Orders!$B$2:$B$2517, (TEXT(Orders!$D$2:$D$2517,""d-mmm"")=TEXT($A34,""d-mmm"")) * (ABS(Orders!$H$2:$H$2517 - Orders!$U$2:$U$2517) >= 1) * (Orders!$M$2:$M$2517=""Delivered""))), ""All Balanced"")"),"All Balanced") -> All Balanced | AG34: =IFERROR(__xludf.DUMMYFUNCTION("IFERROR(TEXTJOIN("", "", TRUE, FILTER(Orders!$I$2:$I$3000, (Orders!$M$2:$M$3000=""Delivered"") * (Orders!$N$2:$N$3000<>""Paid"") * (Orders!$Z$2:$Z$3000=$A34))), """")"),"") | AH34: =COUNTIFS(Orders!$M:$M, "Delivered", Orders!$N:$N, "<>Paid", Orders!$Z:$Z, $A34) -> 0
A35: 46022 | B35: =C35/Y35 -> 3508 | C35: =SUMIFS(Orders!$H:$H, Orders!$Z:$Z, $A35, Orders!$M:$M, "Delivered") -> 49112 | D35: =SUMIFS(Orders!$Q:$Q, Orders!$Z:$Z, $A35, Orders!$M:$M, "Delivered") -> 17370 | E35: =D35/C35 -> 0.35368138 | F35: =C35-(C35*4/100) -> 47147.52 | G35: =C35-F35 -> 1964.48 | H35: =C35-D35 -> 31742 | I35: =IFERROR(J35/C35, 0)*100 -> 47.966933 | J35: 23557.52 | L35: =(200*W35)+C35*4% -> 6364.48 | M35: =SUMIFS(Orders!$W:$W, Orders!$Z:$Z, $A35) -> 6400.46 | N35: =H35-J35-K35-M35 -> 1784.02 | O35: =Y35/W35*100 -> 63.636364 | P35: 3.973162 | Q35: =J35/S35 -> 872.50074 | R35: =J35/W35 -> 1070.7964 | S35: =COUNTIFS(Orders!$Z:$Z, $A35) -> 27 | T35: =COUNTIFS(Orders!$Z:$Z, $A35, Orders!$M:$M, "Cancelled") -> 5 | U35: =T35/S35 -> 0.18518519 | V35: =COUNTIFS(Orders!$Z:$Z, $A35, Orders!$M:$M, "pending") -> 0 | W35: =S35-T35 -> 22 | X35: =W35/S35 -> 0.81481481 | Y35: =COUNTIFS(Orders!$Z:$Z, $A35, Orders!$M:$M, "Delivered") -> 14 | Z35: =COUNTIFS(Orders!$Z:$Z, $A35, Orders!$M:$M, "Return Received") -> 8 | AA35: =W35-Y35-Z35-V35 -> 0 | AB35: {=SUM(COUNTIFS(Orders!$Z:$Z, $A35, Orders!$M:$M, {"Returned","Returned to Shipper"}))} -> 0 | AC35: =COUNTIFS(Orders!$Z:$Z, $A35, Orders!$I:$I, "", Orders!$M:$M, "<>Cancelled") -> 0 | AD35: =SUMIFS(Orders!$U:$U, Orders!$Z:$Z, $A35, Orders!$M:$M, "Delivered") -> 49112 | AE35: =C35-AD35 -> 0 | AF35: =IFERROR(__xludf.DUMMYFUNCTION("IFERROR(TEXTJOIN("", "", TRUE, FILTER(Orders!$B$2:$B$2517, (TEXT(Orders!$D$2:$D$2517,""d-mmm"")=TEXT($A35,""d-mmm"")) * (ABS(Orders!$H$2:$H$2517 - Orders!$U$2:$U$2517) >= 1) * (Orders!$M$2:$M$2517=""Delivered""))), ""All Balanced"")"),"All Balanced") -> All Balanced | AG35: =IFERROR(__xludf.DUMMYFUNCTION("IFERROR(TEXTJOIN("", "", TRUE, FILTER(Orders!$I$2:$I$3000, (Orders!$M$2:$M$3000=""Delivered"") * (Orders!$N$2:$N$3000<>""Paid"") * (Orders!$Z$2:$Z$3000=$A35))), """")"),"") | AH35: =COUNTIFS(Orders!$M:$M, "Delivered", Orders!$N:$N, "<>Paid", Orders!$Z:$Z, $A35) -> 0
A37: Performance | C37: Del% | D37: CAL% | F37: mar% | G37: profit
A38: 45667 | C38: =AVERAGE(O5:O14) -> 72.329669 | D38: =AVERAGE('DEC 25'!AF5:AF14) -> #REF! | F38: =AVERAGE(I5:I14) -> 35.214278 | G38: =SUM(N5:N14) -> 157332.91
A39: 45981 | C39: =AVERAGE(O15:O24) -> 68.827247 | D39: =AVERAGE('DEC 25'!AF15:AF24) -> #REF! | F39: =AVERAGE(I15:I24) -> 35.744009 | G39: =sum(N15:N24) -> 118960.07
A40: 21-31 | C40: =AVERAGE(O25:O35) -> 71.280687 | D40: =AVERAGE('DEC 25'!AF25:AF35) -> #REF! | F40: =AVERAGE(I25:I35) -> 44.846702 | G40: =sum(N25:N35) -> 58755.05
C41: =AVERAGE(AE26:AE36) -> 0 | D41: =AVERAGE(AF26:AF36) -> #DIV/0! | F41: =sum(N26:N36) -> 53444.21 | G41: =sum(G38:G40) -> 335048.03
C43: IN | D43: IN | F43: OUT | G43: OUT | H43: OUT | I43: OUT | J43: IN | K43: OUT | M43: OUT | N43: OUT | O43: OUT | P43: IN | Q43: OUT | R43: OUT | S43: IN | T43: OUT | W43: IN
A44: Averages | G44: =AVERAGE(G47:G77) -> 2299.5852 | J44: =AVERAGE(J47:J77) -> 20189.689 | N44: =AVERAGE(N47:N77) -> 9062.6565 | O44: =AVERAGE(O47:O77) -> 67.965065 | S44: =AVERAGE(S47:S77) -> 29.129032 | T44: =AVERAGE(T47:T77) -> 4.1935484 | W44: =AVERAGE(W47:W77) -> 24.935484
A45: Totals | B45: =AVERAGE(B47:B77) -> 3391.0551 | C45: =sum(C47:C77) -> 1782178.5 | D45: =SUM(D47:D77) -> 652055 | E45: =AVERAGE(E47:E77) -> 0.36272809 | F45: =SUM(F47:F77) -> 1710891.4 | G45: =SUM(G47:G77) -> 71287.141 | H45: =sum(F47:F77) -> 1710891.4 | I45: =AVERAGE(I47:I77) -> 39.301761 | J45: =sum(J47:J77) -> 625880.35 | K45: =sum(K47:K77) -> 0 | L45: =SUM(L47:L77) -> 225887.14 | M45: =sum(M47:M77) -> 223300.83 | N45: =sum(N47:N77) -> 280942.35 | O45: =AVERAGE(O47:O77) -> 67.965065 | P45: =AVERAGE(P47:P77) -> 4.7840962 | Q45: =AVERAGE(Q47:Q77) -> 741.27256 | R45: =AVERAGE(R47:R77) -> 868.34175 | S45: =sum(S47:S77) -> 903 | T45: =sum(T47:T77) -> 130 | U45: =AVERAGE(U47:U77) -> 0.14335023 | V45: =sum(V47:V77) -> 1 | W45: =sum(W47:W77) -> 773 | X45: =AVERAGE(X47:X77) -> 0.85664977 | Y45: =sum(Y47:Y77) -> 517 | Z45: =sum(Z47:Z77) -> 255 | AA45: =SUM(AA47:AA77) -> 0 | AB45: =sum(AB47:AB77) -> 0 | AD45: =SUM(AD47:AD77) -> 1773480.5 | AE45: =sum(AE47:AE77) -> 8698
A46: Dates | B46: AOV | C46: Delivered sale | D46: CGS | F46: -4% tax | G46: TAX Paid | H46: Gross Profit | I46: % | J46: Marketing 10% tax | K46: Tiktok marketing | L46: est courier (200 x total parcel dispatch | M46: Actual exp + tax | N46: PNL (Day vise) | O46: Del% | P46: ROAS(meta) | Q46: CPA AVG (mar/landed orders) | R46: Net CPA AVG(after cancelations) | S46: Landed orders | T46: Cancelations | U46: cal % | V46: Pending | W46: Total Dipatched | X46: Dis % | Y46: Delivered | Z46: Restocked | AA46: Intransit | AB46: Fake Return | AC46: without tracking id | AD46: payment paid | AE46: Diff correction | AF46: Refrance Number that have diff | AG46: Unsorted Tracking IDs | AH46: Delivered (payment pending)
A47: 46023 | B47: =C47/Y47 -> 3174.5911 | C47: =SUMIFS(Orders!$H:$H, Orders!$Z:$Z, $A47, Orders!$M:$M, "Delivered") -> 85713.96 | D47: =SUMIFS(Orders!$Q:$Q, Orders!$Z:$Z, $A47, Orders!$M:$M, "Delivered") -> 29185 | E47: =D47/C47 -> 0.34049296 | F47: =C47-(C47*4/100) -> 82285.402 | G47: =C47-F47 -> 3428.5584 | H47: =C47-D47 -> 56528.96 | I47: =IFERROR(J47/C47, 0)*100 -> 26.825444 | J47: 22993.15 | L47: =(200*W47)+C47*4% -> 11228.558 | M47: =SUMIFS(Orders!$W:$W, Orders!$Z:$Z, $A47) -> 11465.11 | N47: =H47-J47-K47-M47 -> 22070.7 | O47: =Y47/W47*100 -> 69.230769 | P47: 6.0284554 | Q47: =J47/S47 -> 547.45595 | R47: =J47/W47 -> 589.56795 | S47: =COUNTIFS(Orders!$Z:$Z, $A47) -> 42 | T47: =COUNTIFS(Orders!$Z:$Z, $A47, Orders!$M:$M, "Cancelled") -> 3 | U47: =T47/S47 -> 0.071428571 | V47: =COUNTIFS(Orders!$Z:$Z, $A47, Orders!$M:$M, "pending") -> 0 | W47: =S47-T47 -> 39 | X47: =W47/S47 -> 0.92857143 | Y47: =COUNTIFS(Orders!$Z:$Z, $A47, Orders!$M:$M, "Delivered") -> 27 | Z47: =COUNTIFS(Orders!$Z:$Z, $A47, Orders!$M:$M, "Return Received") -> 12 | AA47: =W47-Y47-Z47-V47 -> 0 | AB47: =COUNTIFS(Orders!$Z:$Z, $A47, Orders!$M:$M, "Returned") + COUNTIFS(Orders!$Z:$Z, $A47, Orders!$M:$M, "Returned to Shipper") -> 0 | AC47: =COUNTIFS(Orders!$Z:$Z, $A47, Orders!$I:$I, "", Orders!$M:$M, "<>Cancelled") -> 0 | AD47: =SUMIFS(Orders!$U:$U, Orders!$Z:$Z, $A47, Orders!$M:$M, "Delivered") -> 85713.96 | AE47: =C47-AD47 -> 0 | AF47: =IFERROR(__xludf.DUMMYFUNCTION("IFERROR(TEXTJOIN("", "", TRUE, FILTER(Orders!$B$2:$B$2517, (TEXT(Orders!$D$2:$D$2517,""d-mmm"")=TEXT($A47,""d-mmm"")) * (ABS(Orders!$H$2:$H$2517 - Orders!$U$2:$U$2517) >= 1) * (Orders!$M$2:$M$2517=""Delivered""))), ""All Balanced"")"),"All Balanced") -> All Balanced | AG47: =IFERROR(__xludf.DUMMYFUNCTION("IFERROR(TEXTJOIN("", "", TRUE, FILTER(Orders!$I$2:$I$2517, (Orders!$M$2:$M$2517=""Delivered"") * (Orders!$N$2:$N$2517<>""Paid"") * (Orders!$Z$2:$Z$2517=$A47))), """")"),"") | AH47: =COUNTIFS(Orders!$M:$M, "Delivered", Orders!$N:$N, "<>Paid", Orders!$Z:$Z, $A47) -> 0
A48: 46024 | B48: =C48/Y48 -> 4227.4257 | C48: =SUMIFS(Orders!$H:$H, Orders!$Z:$Z, $A48, Orders!$M:$M, "Delivered") -> 59183.96 | D48: =SUMIFS(Orders!$Q:$Q, Orders!$Z:$Z, $A48, Orders!$M:$M, "Delivered") -> 23510 | E48: =D48/C48 -> 0.39723601 | F48: =C48-(C48*4/100) -> 56816.602 | G48: =C48-F48 -> 2367.3584 | H48: =C48-D48 -> 35673.96 | I48: =IFERROR(J48/C48, 0)*100 -> 41.033229 | J48: 24285.09 | L48: =(200*W48)+C48*4% -> 6967.3584 | M48: =SUMIFS(Orders!$W:$W, Orders!$Z:$Z, $A48) -> 6757.1 | N48: =H48-J48-K48-M48 -> 4631.77 | O48: =Y48/W48*100 -> 60.869565 | P48: 3.9121942 | Q48: =J48/S48 -> 934.04192 | R48: =J48/W48 -> 1055.8735 | S48: =COUNTIFS(Orders!$Z:$Z, $A48) -> 26 | T48: =COUNTIFS(Orders!$Z:$Z, $A48, Orders!$M:$M, "Cancelled") -> 3 | U48: =T48/S48 -> 0.11538462 | V48: =COUNTIFS(Orders!$Z:$Z, $A48, Orders!$M:$M, "pending") -> 0 | W48: =S48-T48 -> 23 | X48: =W48/S48 -> 0.88461538 | Y48: =COUNTIFS(Orders!$Z:$Z, $A48, Orders!$M:$M, "Delivered") -> 14 | Z48: =COUNTIFS(Orders!$Z:$Z, $A48, Orders!$M:$M, "Return Received") -> 9 | AA48: =W48-Y48-Z48-V48 -> 0 | AB48: =COUNTIFS(Orders!$Z:$Z, $A48, Orders!$M:$M, "Returned") + COUNTIFS(Orders!$Z:$Z, $A48, Orders!$M:$M, "Returned to Shipper") -> 0 | AC48: =COUNTIFS(Orders!$Z:$Z, $A48, Orders!$I:$I, "", Orders!$M:$M, "<>Cancelled") -> 0 | AD48: =SUMIFS(Orders!$U:$U, Orders!$Z:$Z, $A48, Orders!$M:$M, "Delivered") -> 59183.96 | AE48: =C48-AD48 -> 0 | AF48: =IFERROR(__xludf.DUMMYFUNCTION("IFERROR(TEXTJOIN("", "", TRUE, FILTER(Orders!$B$2:$B$2517, (TEXT(Orders!$D$2:$D$2517,""d-mmm"")=TEXT($A48,""d-mmm"")) * (ABS(Orders!$H$2:$H$2517 - Orders!$U$2:$U$2517) >= 1) * (Orders!$M$2:$M$2517=""Delivered""))), ""All Balanced"")"),"All Balanced") -> All Balanced | AG48: =IFERROR(__xludf.DUMMYFUNCTION("IFERROR(TEXTJOIN("", "", TRUE, FILTER(Orders!$I$2:$I$3000, (Orders!$M$2:$M$3000=""Delivered"") * (Orders!$N$2:$N$3000<>""Paid"") * (Orders!$Z$2:$Z$3000=$A48))), """")"),"") | AH48: =COUNTIFS(Orders!$M:$M, "Delivered", Orders!$N:$N, "<>Paid", Orders!$Z:$Z, $A48) -> 0
A49: 46025 | B49: =C49/Y49 -> 4186.8015 | C49: =SUMIFS(Orders!$H:$H, Orders!$Z:$Z, $A49, Orders!$M:$M, "Delivered") -> 113043.64 | D49: =SUMIFS(Orders!$Q:$Q, Orders!$Z:$Z, $A49, Orders!$M:$M, "Delivered") -> 41905 | E49: =D49/C49 -> 0.37069755 | F49: =C49-(C49*4/100) -> 108521.89 | G49: =C49-F49 -> 4521.7456 | H49: =C49-D49 -> 71138.64 | I49: =IFERROR(J49/C49, 0)*100 -> 20.491343 | J49: 23164.16 | L49: =(200*W49)+C49*4% -> 10921.746 | M49: =SUMIFS(Orders!$W:$W, Orders!$Z:$Z, $A49) -> 10397.03 | N49: =H49-J49-K49-M49 -> 37577.45 | O49: =Y49/W49*100 -> 84.375 | P49: 6.8110111 | Q49: =J49/S49 -> 609.58316 | R49: =J49/W49 -> 723.88 | S49: =COUNTIFS(Orders!$Z:$Z, $A49) -> 38 | T49: =COUNTIFS(Orders!$Z:$Z, $A49, Orders!$M:$M, "Cancelled") -> 6 | U49: =T49/S49 -> 0.15789474 | V49: =COUNTIFS(Orders!$Z:$Z, $A49, Orders!$M:$M, "pending") -> 0 | W49: =S49-T49 -> 32 | X49: =W49/S49 -> 0.84210526 | Y49: =COUNTIFS(Orders!$Z:$Z, $A49, Orders!$M:$M, "Delivered") -> 27 | Z49: =COUNTIFS(Orders!$Z:$Z, $A49, Orders!$M:$M, "Return Received") -> 5 | AA49: =W49-Y49-Z49-V49 -> 0 | AB49: =COUNTIFS(Orders!$Z:$Z, $A49, Orders!$M:$M, "Returned") + COUNTIFS(Orders!$Z:$Z, $A49, Orders!$M:$M, "Returned to Shipper") -> 0 | AC49: =COUNTIFS(Orders!$Z:$Z, $A49, Orders!$I:$I, "", Orders!$M:$M, "<>Cancelled") -> 0 | AD49: =SUMIFS(Orders!$U:$U, Orders!$Z:$Z, $A49, Orders!$M:$M, "Delivered") -> 113043.64 | AE49: =C49-AD49 -> 0 | AF49: =IFERROR(__xludf.DUMMYFUNCTION("IFERROR(TEXTJOIN("", "", TRUE, FILTER(Orders!$B$2:$B$2517, (TEXT(Orders!$D$2:$D$2517,""d-mmm"")=TEXT($A49,""d-mmm"")) * (ABS(Orders!$H$2:$H$2517 - Orders!$U$2:$U$2517) >= 1) * (Orders!$M$2:$M$2517=""Delivered""))), ""All Balanced"")"),"All Balanced") -> All Balanced | AG49: =IFERROR(__xludf.DUMMYFUNCTION("IFERROR(TEXTJOIN("", "", TRUE, FILTER(Orders!$I$2:$I$3000, (Orders!$M$2:$M$3000=""Delivered"") * (Orders!$N$2:$N$3000<>""Paid"") * (Orders!$Z$2:$Z$3000=$A49))), """")"),"") | AH49: =COUNTIFS(Orders!$M:$M, "Delivered", Orders!$N:$N, "<>Paid", Orders!$Z:$Z, $A49) -> 0
A50: 46026 | B50: =C50/Y50 -> 3021.9375 | C50: =SUMIFS(Orders!$H:$H, Orders!$Z:$Z, $A50, Orders!$M:$M, "Delivered") -> 48351 | D50: =SUMIFS(Orders!$Q:$Q, Orders!$Z:$Z, $A50, Orders!$M:$M, "Delivered") -> 16010 | E50: =D50/C50 -> 0.33112035 | F50: =C50-(C50*4/100) -> 46416.96 | G50: =C50-F50 -> 1934.04 | H50: =C50-D50 -> 32341 | I50: =IFERROR(J50/C50, 0)*100 -> 50.722281 | J50: 24524.73 | L50: =(200*W50)+C50*4% -> 6534.04 | M50: =SUMIFS(Orders!$W:$W, Orders!$Z:$Z, $A50) -> 6187.93 | N50: =H50-J50-K50-M50 -> 1628.34 | O50: =Y50/W50*100 -> 69.565217 | P50: 3.4018518 | Q50: =J50/S50 -> 908.32333 | R50: =J50/W50 -> 1066.2926 | S50: =COUNTIFS(Orders!$Z:$Z, $A50) -> 27 | T50: =COUNTIFS(Orders!$Z:$Z, $A50, Orders!$M:$M, "Cancelled") -> 4 | U50: =T50/S50 -> 0.14814815 | V50: =COUNTIFS(Orders!$Z:$Z, $A50, Orders!$M:$M, "pending") -> 0 | W50: =S50-T50 -> 23 | X50: =W50/S50 -> 0.85185185 | Y50: =COUNTIFS(Orders!$Z:$Z, $A50, Orders!$M:$M, "Delivered") -> 16 | Z50: =COUNTIFS(Orders!$Z:$Z, $A50, Orders!$M:$M, "Return Received") -> 7 | AA50: =W50-Y50-Z50-V50 -> 0 | AB50: =COUNTIFS(Orders!$Z:$Z, $A50, Orders!$M:$M, "Returned") + COUNTIFS(Orders!$Z:$Z, $A50, Orders!$M:$M, "Returned to Shipper") -> 0 | AC50: =COUNTIFS(Orders!$Z:$Z, $A50, Orders!$I:$I, "", Orders!$M:$M, "<>Cancelled") -> 0 | AD50: =SUMIFS(Orders!$U:$U, Orders!$Z:$Z, $A50, Orders!$M:$M, "Delivered") -> 48351 | AE50: =C50-AD50 -> 0 | AF50: =IFERROR(__xludf.DUMMYFUNCTION("IFERROR(TEXTJOIN("", "", TRUE, FILTER(Orders!$B$2:$B$2517, (TEXT(Orders!$D$2:$D$2517,""d-mmm"")=TEXT($A50,""d-mmm"")) * (ABS(Orders!$H$2:$H$2517 - Orders!$U$2:$U$2517) >= 1) * (Orders!$M$2:$M$2517=""Delivered""))), ""All Balanced"")"),"All Balanced") -> All Balanced | AG50: =IFERROR(__xludf.DUMMYFUNCTION("IFERROR(TEXTJOIN("", "", TRUE, FILTER(Orders!$I$2:$I$3000, (Orders!$M$2:$M$3000=""Delivered"") * (Orders!$N$2:$N$3000<>""Paid"") * (Orders!$Z$2:$Z$3000=$A50))), """")"),"") | AH50: =COUNTIFS(Orders!$M:$M, "Delivered", Orders!$N:$N, "<>Paid", Orders!$Z:$Z, $A50) -> 0
A51: 46027 | B51: =C51/Y51 -> 3502.4147 | C51: =SUMIFS(Orders!$H:$H, Orders!$Z:$Z, $A51, Orders!$M:$M, "Delivered") -> 66545.88 | D51: =SUMIFS(Orders!$Q:$Q, Orders!$Z:$Z, $A51, Orders!$M:$M, "Delivered") -> 23475 | E51: =D51/C51 -> 0.35276414 | F51: =C51-(C51*4/100) -> 63884.045 | G51: =C51-F51 -> 2661.8352 | H51: =C51-D51 -> 43070.88 | I51: =IFERROR(J51/C51, 0)*100 -> 31.31671 | J51: 20839.98 | L51: =(200*W51)+C51*4% -> 7661.8352 | M51: =SUMIFS(Orders!$W:$W, Orders!$Z:$Z, $A51) -> 7781.71 | N51: =H51-J51-K51-M51 -> 14449.19 | O51: =Y51/W51*100 -> 76 | P51: 4.5303186 | Q51: =J51/S51 -> 801.53769 | R51: =J51/W51 -> 833.5992 | S51: =COUNTIFS(Orders!$Z:$Z, $A51) -> 26 | T51: =COUNTIFS(Orders!$Z:$Z, $A51, Orders!$M:$M, "Cancelled") -> 1 | U51: =T51/S51 -> 0.038461538 | V51: =COUNTIFS(Orders!$Z:$Z, $A51, Orders!$M:$M, "pending") -> 0 | W51: =S51-T51 -> 25 | X51: =W51/S51 -> 0.96153846 | Y51: =COUNTIFS(Orders!$Z:$Z, $A51, Orders!$M:$M, "Delivered") -> 19 | Z51: =COUNTIFS(Orders!$Z:$Z, $A51, Orders!$M:$M, "Return Received") -> 6 | AA51: =W51-Y51-Z51-V51 -> 0 | AB51: =COUNTIFS(Orders!$Z:$Z, $A51, Orders!$M:$M, "Returned") + COUNTIFS(Orders!$Z:$Z, $A51, Orders!$M:$M, "Returned to Shipper") -> 0 | AC51: =COUNTIFS(Orders!$Z:$Z, $A51, Orders!$I:$I, "", Orders!$M:$M, "<>Cancelled") -> 0 | AD51: =SUMIFS(Orders!$U:$U, Orders!$Z:$Z, $A51, Orders!$M:$M, "Delivered") -> 66545.88 | AE51: =C51-AD51 -> 0 | AF51: =IFERROR(__xludf.DUMMYFUNCTION("IFERROR(TEXTJOIN("", "", TRUE, FILTER(Orders!$B$2:$B$2517, (TEXT(Orders!$D$2:$D$2517,""d-mmm"")=TEXT($A51,""d-mmm"")) * (ABS(Orders!$H$2:$H$2517 - Orders!$U$2:$U$2517) >= 1) * (Orders!$M$2:$M$2517=""Delivered""))), ""All Balanced"")"),"All Balanced") -> All Balanced | AG51: =IFERROR(__xludf.DUMMYFUNCTION("IFERROR(TEXTJOIN("", "", TRUE, FILTER(Orders!$I$2:$I$3000, (Orders!$M$2:$M$3000=""Delivered"") * (Orders!$N$2:$N$3000<>""Paid"") * (Orders!$Z$2:$Z$3000=$A51))), """")"),"") | AH51: =COUNTIFS(Orders!$M:$M, "Delivered", Orders!$N:$N, "<>Paid", Orders!$Z:$Z, $A51) -> 0
A52: 46028 | B52: =C52/Y52 -> 3146.9494 | C52: =SUMIFS(Orders!$H:$H, Orders!$Z:$Z, $A52, Orders!$M:$M, "Delivered") -> 56645.09 | D52: =SUMIFS(Orders!$Q:$Q, Orders!$Z:$Z, $A52, Orders!$M:$M, "Delivered") -> 20750 | E52: =D52/C52 -> 0.36631595 | F52: =C52-(C52*4/100) -> 54379.286 | G52: =C52-F52 -> 2265.8036 | H52: =C52-D52 -> 35895.09 | I52: =IFERROR(J52/C52, 0)*100 -> 32.108838 | J52: 18188.08 | L52: =(200*W52)+C52*4% -> 7465.8036 | M52: =SUMIFS(Orders!$W:$W, Orders!$Z:$Z, $A52) -> 8007.32 | N52: =H52-J52-K52-M52 -> 9699.69 | O52: =Y52/W52*100 -> 69.230769 | P52: 4.3691382 | Q52: =J52/S52 -> 606.26933 | R52: =J52/W52 -> 699.54154 | S52: =COUNTIFS(Orders!$Z:$Z, $A52) -> 30 | T52: =COUNTIFS(Orders!$Z:$Z, $A52, Orders!$M:$M, "Cancelled") -> 4 | U52: =T52/S52 -> 0.13333333 | V52: =COUNTIFS(Orders!$Z:$Z, $A52, Orders!$M:$M, "pending") -> 0 | W52: =S52-T52 -> 26 | X52: =W52/S52 -> 0.86666667 | Y52: =COUNTIFS(Orders!$Z:$Z, $A52, Orders!$M:$M, "Delivered") -> 18 | Z52: =COUNTIFS(Orders!$Z:$Z, $A52, Orders!$M:$M, "Return Received") -> 8 | AA52: =W52-Y52-Z52-V52 -> 0 | AB52: =COUNTIFS(Orders!$Z:$Z, $A52, Orders!$M:$M, "Returned") + COUNTIFS(Orders!$Z:$Z, $A52, Orders!$M:$M, "Returned to Shipper") -> 0 | AC52: =COUNTIFS(Orders!$Z:$Z, $A52, Orders!$I:$I, "", Orders!$M:$M, "<>Cancelled") -> 0 | AD52: =SUMIFS(Orders!$U:$U, Orders!$Z:$Z, $A52, Orders!$M:$M, "Delivered") -> 56645.09 | AE52: =C52-AD52 -> 0 | AF52: =IFERROR(__xludf.DUMMYFUNCTION("IFERROR(TEXTJOIN("", "", TRUE, FILTER(Orders!$B$2:$B$2517, (TEXT(Orders!$D$2:$D$2517,""d-mmm"")=TEXT($A52,""d-mmm"")) * (ABS(Orders!$H$2:$H$2517 - Orders!$U$2:$U$2517) >= 1) * (Orders!$M$2:$M$2517=""Delivered""))), ""All Balanced"")"),"All Balanced") -> All Balanced | AG52: =IFERROR(__xludf.DUMMYFUNCTION("IFERROR(TEXTJOIN("", "", TRUE, FILTER(Orders!$I$2:$I$3000, (Orders!$M$2:$M$3000=""Delivered"") * (Orders!$N$2:$N$3000<>""Paid"") * (Orders!$Z$2:$Z$3000=$A52))), """")"),"") | AH52: =COUNTIFS(Orders!$M:$M, "Delivered", Orders!$N:$N, "<>Paid", Orders!$Z:$Z, $A52) -> 0
A53: 46029 | B53: =C53/Y53 -> 3305.5 | C53: =SUMIFS(Orders!$H:$H, Orders!$Z:$Z, $A53, Orders!$M:$M, "Delivered") -> 46277 | D53: =SUMIFS(Orders!$Q:$Q, Orders!$Z:$Z, $A53, Orders!$M:$M, "Delivered") -> 17750 | E53: =D53/C53 -> 0.38355987 | F53: =C53-(C53*4/100) -> 44425.92 | G53: =C53-F53 -> 1851.08 | H53: =C53-D53 -> 28527 | I53: =IFERROR(J53/C53, 0)*100 -> 38.399054 | J53: 17769.93 | L53: =(200*W53)+C53*4% -> 4851.08 | M53: =SUMIFS(Orders!$W:$W, Orders!$Z:$Z, $A53) -> 5119.96 | N53: =H53-J53-K53-M53 -> 5637.11 | O53: =Y53/W53*100 -> 93.333333 | P53: 3.7017595 | Q53: =J53/S53 -> 846.18714 | R53: =J53/W53 -> 1184.662 | S53: =COUNTIFS(Orders!$Z:$Z, $A53) -> 21 | T53: =COUNTIFS(Orders!$Z:$Z, $A53, Orders!$M:$M, "Cancelled") -> 6 | U53: =T53/S53 -> 0.28571429 | V53: =COUNTIFS(Orders!$Z:$Z, $A53, Orders!$M:$M, "pending") -> 0 | W53: =S53-T53 -> 15 | X53: =W53/S53 -> 0.71428571 | Y53: =COUNTIFS(Orders!$Z:$Z, $A53, Orders!$M:$M, "Delivered") -> 14 | Z53: =COUNTIFS(Orders!$Z:$Z, $A53, Orders!$M:$M, "Return Received") -> 1 | AA53: =W53-Y53-Z53-V53 -> 0 | AB53: =COUNTIFS(Orders!$Z:$Z, $A53, Orders!$M:$M, "Returned") + COUNTIFS(Orders!$Z:$Z, $A53, Orders!$M:$M, "Returned to Shipper") -> 0 | AC53: =COUNTIFS(Orders!$Z:$Z, $A53, Orders!$I:$I, "", Orders!$M:$M, "<>Cancelled") -> 0 | AD53: =SUMIFS(Orders!$U:$U, Orders!$Z:$Z, $A53, Orders!$M:$M, "Delivered") -> 46277 | AE53: =C53-AD53 -> 0 | AF53: =IFERROR(__xludf.DUMMYFUNCTION("IFERROR(TEXTJOIN("", "", TRUE, FILTER(Orders!$B$2:$B$2517, (TEXT(Orders!$D$2:$D$2517,""d-mmm"")=TEXT($A53,""d-mmm"")) * (ABS(Orders!$H$2:$H$2517 - Orders!$U$2:$U$2517) >= 1) * (Orders!$M$2:$M$2517=""Delivered""))), ""All Balanced"")"),"All Balanced") -> All Balanced | AG53: =IFERROR(__xludf.DUMMYFUNCTION("IFERROR(TEXTJOIN("", "", TRUE, FILTER(Orders!$I$2:$I$3000, (Orders!$M$2:$M$3000=""Delivered"") * (Orders!$N$2:$N$3000<>""Paid"") * (Orders!$Z$2:$Z$3000=$A53))), """")"),"") | AH53: =COUNTIFS(Orders!$M:$M, "Delivered", Orders!$N:$N, "<>Paid", Orders!$Z:$Z, $A53) -> 0
A54: 46030 | B54: =C54/Y54 -> 2414 | C54: =SUMIFS(Orders!$H:$H, Orders!$Z:$Z, $A54, Orders!$M:$M, "Delivered") -> 14484 | D54: =SUMIFS(Orders!$Q:$Q, Orders!$Z:$Z, $A54, Orders!$M:$M, "Delivered") -> 5140 | E54: =D54/C54 -> 0.35487434 | F54: =C54-(C54*4/100) -> 13904.64 | G54: =C54-F54 -> 579.36 | H54: =C54-D54 -> 9344 | I54: =IFERROR(J54/C54, 0)*100 -> 103.94339 | J54: 15055.16 | L54: =(200*W54)+C54*4% -> 1979.36 | M54: =SUMIFS(Orders!$W:$W, Orders!$Z:$Z, $A54) -> 1959.68 | N54: =H54-J54-K54-M54 -> -7670.84 | O54: =Y54/W54*100 -> 85.714286 | P54: 1.0991845 | Q54: =J54/S54 -> 1881.895 | R54: =J54/W54 -> 2150.7371 | S54: =COUNTIFS(Orders!$Z:$Z, $A54) -> 8 | T54: =COUNTIFS(Orders!$Z:$Z, $A54, Orders!$M:$M, "Cancelled") -> 1 | U54: =T54/S54 -> 0.125 | V54: =COUNTIFS(Orders!$Z:$Z, $A54, Orders!$M:$M, "pending") -> 0 | W54: =S54-T54 -> 7 | X54: =W54/S54 -> 0.875 | Y54: =COUNTIFS(Orders!$Z:$Z, $A54, Orders!$M:$M, "Delivered") -> 6 | Z54: =COUNTIFS(Orders!$Z:$Z, $A54, Orders!$M:$M, "Return Received") -> 1 | AA54: =W54-Y54-Z54-V54 -> 0 | AB54: =COUNTIFS(Orders!$Z:$Z, $A54, Orders!$M:$M, "Returned") + COUNTIFS(Orders!$Z:$Z, $A54, Orders!$M:$M, "Returned to Shipper") -> 0 | AC54: =COUNTIFS(Orders!$Z:$Z, $A54, Orders!$I:$I, "", Orders!$M:$M, "<>Cancelled") -> 0 | AD54: =SUMIFS(Orders!$U:$U, Orders!$Z:$Z, $A54, Orders!$M:$M, "Delivered") -> 14484 | AE54: =C54-AD54 -> 0 | AF54: =IFERROR(__xludf.DUMMYFUNCTION("IFERROR(TEXTJOIN("", "", TRUE, FILTER(Orders!$B$2:$B$2517, (TEXT(Orders!$D$2:$D$2517,""d-mmm"")=TEXT($A54,""d-mmm"")) * (ABS(Orders!$H$2:$H$2517 - Orders!$U$2:$U$2517) >= 1) * (Orders!$M$2:$M$2517=""Delivered""))), ""All Balanced"")"),"All Balanced") -> All Balanced | AG54: =IFERROR(__xludf.DUMMYFUNCTION("IFERROR(TEXTJOIN("", "", TRUE, FILTER(Orders!$I$2:$I$3000, (Orders!$M$2:$M$3000=""Delivered"") * (Orders!$N$2:$N$3000<>""Paid"") * (Orders!$Z$2:$Z$3000=$A54))), """")"),"") | AH54: =COUNTIFS(Orders!$M:$M, "Delivered", Orders!$N:$N, "<>Paid", Orders!$Z:$Z, $A54) -> 0
A55: 46031 | B55: =C55/Y55 -> 3532.7727 | C55: =SUMIFS(Orders!$H:$H, Orders!$Z:$Z, $A55, Orders!$M:$M, "Delivered") -> 77721 | D55: =SUMIFS(Orders!$Q:$Q, Orders!$Z:$Z, $A55, Orders!$M:$M, "Delivered") -> 30310 | E55: =D55/C55 -> 0.38998469 | F55: =C55-(C55*4/100) -> 74612.16 | G55: =C55-F55 -> 3108.84 | H55: =C55-D55 -> 47411 | I55: =IFERROR(J55/C55, 0)*100 -> 29.552669 | J55: 22968.63 | L55: =(200*W55)+C55*4% -> 10108.84 | M55: =SUMIFS(Orders!$W:$W, Orders!$Z:$Z, $A55) -> 10086.17 | N55: =H55-J55-K55-M55 -> 14356.2 | O55: =Y55/W55*100 -> 62.857143 | P55: 6.3707552 | Q55: =J55/S55 -> 560.21049 | R55: =J55/W55 -> 656.24657 | S55: =COUNTIFS(Orders!$Z:$Z, $A55) -> 41 | T55: =COUNTIFS(Orders!$Z:$Z, $A55, Orders!$M:$M, "Cancelled") -> 6 | U55: =T55/S55 -> 0.14634146 | V55: =COUNTIFS(Orders!$Z:$Z, $A55, Orders!$M:$M, "pending") -> 0 | W55: =S55-T55 -> 35 | X55: =W55/S55 -> 0.85365854 | Y55: =COUNTIFS(Orders!$Z:$Z, $A55, Orders!$M:$M, "Delivered") -> 22 | Z55: =COUNTIFS(Orders!$Z:$Z, $A55, Orders!$M:$M, "Return Received") -> 13 | AA55: =W55-Y55-Z55-V55 -> 0 | AB55: =COUNTIFS(Orders!$Z:$Z, $A55, Orders!$M:$M, "Returned") + COUNTIFS(Orders!$Z:$Z, $A55, Orders!$M:$M, "Returned to Shipper") -> 0 | AC55: =COUNTIFS(Orders!$Z:$Z, $A55, Orders!$I:$I, "", Orders!$M:$M, "<>Cancelled") -> 0 | AD55: =SUMIFS(Orders!$U:$U, Orders!$Z:$Z, $A55, Orders!$M:$M, "Delivered") -> 77721 | AE55: =C55-AD55 -> 0 | AF55: =IFERROR(__xludf.DUMMYFUNCTION("IFERROR(TEXTJOIN("", "", TRUE, FILTER(Orders!$B$2:$B$2517, (TEXT(Orders!$D$2:$D$2517,""d-mmm"")=TEXT($A55,""d-mmm"")) * (ABS(Orders!$H$2:$H$2517 - Orders!$U$2:$U$2517) >= 1) * (Orders!$M$2:$M$2517=""Delivered""))), ""All Balanced"")"),"All Balanced") -> All Balanced | AG55: =IFERROR(__xludf.DUMMYFUNCTION("IFERROR(TEXTJOIN("", "", TRUE, FILTER(Orders!$I$2:$I$3000, (Orders!$M$2:$M$3000=""Delivered"") * (Orders!$N$2:$N$3000<>""Paid"") * (Orders!$Z$2:$Z$3000=$A55))), """")"),"") | AH55: =COUNTIFS(Orders!$M:$M, "Delivered", Orders!$N:$N, "<>Paid", Orders!$Z:$Z, $A55) -> 0
A56: 46032 | B56: =C56/Y56 -> 3011.15 | C56: =SUMIFS(Orders!$H:$H, Orders!$Z:$Z, $A56, Orders!$M:$M, "Delivered") -> 60223 | D56: =SUMIFS(Orders!$Q:$Q, Orders!$Z:$Z, $A56, Orders!$M:$M, "Delivered") -> 24550 | E56: =D56/C56 -> 0.40765156 | F56: =C56-(C56*4/100) -> 57814.08 | G56: =C56-F56 -> 2408.92 | H56: =C56-D56 -> 35673 | I56: =IFERROR(J56/C56, 0)*100 -> 46.969065 | J56: 28286.18 | L56: =(200*W56)+C56*4% -> 9008.92 | M56: =SUMIFS(Orders!$W:$W, Orders!$Z:$Z, $A56) -> 8883.04 | N56: =H56-J56-K56-M56 -> -1496.22 | O56: =Y56/W56*100 -> 60.606061 | P56: 4.1574259 | Q56: =J56/S56 -> 707.1545 | R56: =J56/W56 -> 857.15697 | S56: =COUNTIFS(Orders!$Z:$Z, $A56) -> 40 | T56: =COUNTIFS(Orders!$Z:$Z, $A56, Orders!$M:$M, "Cancelled") -> 7 | U56: =T56/S56 -> 0.175 | V56: =COUNTIFS(Orders!$Z:$Z, $A56, Orders!$M:$M, "pending") -> 0 | W56: =S56-T56 -> 33 | X56: =W56/S56 -> 0.825 | Y56: =COUNTIFS(Orders!$Z:$Z, $A56, Orders!$M:$M, "Delivered") -> 20 | Z56: =COUNTIFS(Orders!$Z:$Z, $A56, Orders!$M:$M, "Return Received") -> 13 | AA56: =W56-Y56-Z56-V56 -> 0 | AB56: =COUNTIFS(Orders!$Z:$Z, $A56, Orders!$M:$M, "Returned") + COUNTIFS(Orders!$Z:$Z, $A56, Orders!$M:$M, "Returned to Shipper") -> 0 | AC56: =COUNTIFS(Orders!$Z:$Z, $A56, Orders!$I:$I, "", Orders!$M:$M, "<>Cancelled") -> 0 | AD56: =SUMIFS(Orders!$U:$U, Orders!$Z:$Z, $A56, Orders!$M:$M, "Delivered") -> 60223 | AE56: =C56-AD56 -> 0 | AF56: =IFERROR(__xludf.DUMMYFUNCTION("IFERROR(TEXTJOIN("", "", TRUE, FILTER(Orders!$B$2:$B$2517, (TEXT(Orders!$D$2:$D$2517,""d-mmm"")=TEXT($A56,""d-mmm"")) * (ABS(Orders!$H$2:$H$2517 - Orders!$U$2:$U$2517) >= 1) * (Orders!$M$2:$M$2517=""Delivered""))), ""All Balanced"")"),"All Balanced") -> All Balanced | AG56: =IFERROR(__xludf.DUMMYFUNCTION("IFERROR(TEXTJOIN("", "", TRUE, FILTER(Orders!$I$2:$I$3000, (Orders!$M$2:$M$3000=""Delivered"") * (Orders!$N$2:$N$3000<>""Paid"") * (Orders!$Z$2:$Z$3000=$A56))), """")"),"") | AH56: =COUNTIFS(Orders!$M:$M, "Delivered", Orders!$N:$N, "<>Paid", Orders!$Z:$Z, $A56) -> 0
A57: 46033 | B57: =C57/Y57 -> 3752.1429 | C57: =SUMIFS(Orders!$H:$H, Orders!$Z:$Z, $A57, Orders!$M:$M, "Delivered") -> 52530 | D57: =SUMIFS(Orders!$Q:$Q, Orders!$Z:$Z, $A57, Orders!$M:$M, "Delivered") -> 18665 | E57: =D57/C57 -> 0.35532077 | F57: =C57-(C57*4/100) -> 50428.8 | G57: =C57-F57 -> 2101.2 | H57: =C57-D57 -> 33865 | I57: =IFERROR(J57/C57, 0)*100 -> 47.005083 | J57: 24691.77 | L57: =(200*W57)+C57*4% -> 6701.2 | M57: =SUMIFS(Orders!$W:$W, Orders!$Z:$Z, $A57) -> 6868.62 | N57: =H57-J57-K57-M57 -> 2304.61 | O57: =Y57/W57*100 -> 60.869565 | P57: 4.5931628 | Q57: =J57/S57 -> 823.059 | R57: =J57/W57 -> 1073.5552 | S57: =COUNTIFS(Orders!$Z:$Z, $A57) -> 30 | T57: =COUNTIFS(Orders!$Z:$Z, $A57, Orders!$M:$M, "Cancelled") -> 7 | U57: =T57/S57 -> 0.23333333 | V57: =COUNTIFS(Orders!$Z:$Z, $A57, Orders!$M:$M, "pending") -> 0 | W57: =S57-T57 -> 23 | X57: =W57/S57 -> 0.76666667 | Y57: =COUNTIFS(Orders!$Z:$Z, $A57, Orders!$M:$M, "Delivered") -> 14 | Z57: =COUNTIFS(Orders!$Z:$Z, $A57, Orders!$M:$M, "Return Received") -> 9 | AA57: =W57-Y57-Z57-V57 -> 0 | AB57: =COUNTIFS(Orders!$Z:$Z, $A57, Orders!$M:$M, "Returned") + COUNTIFS(Orders!$Z:$Z, $A57, Orders!$M:$M, "Returned to Shipper") -> 0 | AC57: =COUNTIFS(Orders!$Z:$Z, $A57, Orders!$I:$I, "", Orders!$M:$M, "<>Cancelled") -> 0 | AD57: =SUMIFS(Orders!$U:$U, Orders!$Z:$Z, $A57, Orders!$M:$M, "Delivered") -> 52530 | AE57: =C57-AD57 -> 0 | AF57: =IFERROR(__xludf.DUMMYFUNCTION("IFERROR(TEXTJOIN("", "", TRUE, FILTER(Orders!$B$2:$B$2517, (TEXT(Orders!$D$2:$D$2517,""d-mmm"")=TEXT($A57,""d-mmm"")) * (ABS(Orders!$H$2:$H$2517 - Orders!$U$2:$U$2517) >= 1) * (Orders!$M$2:$M$2517=""Delivered""))), ""All Balanced"")"),"All Balanced") -> All Balanced | AG57: =IFERROR(__xludf.DUMMYFUNCTION("IFERROR(TEXTJOIN("", "", TRUE, FILTER(Orders!$I$2:$I$3000, (Orders!$M$2:$M$3000=""Delivered"") * (Orders!$N$2:$N$3000<>""Paid"") * (Orders!$Z$2:$Z$3000=$A57))), """")"),"") | AH57: =COUNTIFS(Orders!$M:$M, "Delivered", Orders!$N:$N, "<>Paid", Orders!$Z:$Z, $A57) -> 0
A58: 46034 | B58: =C58/Y58 -> 4029.7647 | C58: =SUMIFS(Orders!$H:$H, Orders!$Z:$Z, $A58, Orders!$M:$M, "Delivered") -> 68506 | D58: =SUMIFS(Orders!$Q:$Q, Orders!$Z:$Z, $A58, Orders!$M:$M, "Delivered") -> 26670 | E58: =D58/C58 -> 0.38930897 | F58: =C58-(C58*4/100) -> 65765.76 | G58: =C58-F58 -> 2740.24 | H58: =C58-D58 -> 41836 | I58: =IFERROR(J58/C58, 0)*100 -> 29.927612 | J58: 20502.21 | L58: =(200*W58)+C58*4% -> 9940.24 | M58: =SUMIFS(Orders!$W:$W, Orders!$Z:$Z, $A58) -> 10017.27 | N58: =H58-J58-K58-M58 -> 11316.52 | O58: =Y58/W58*100 -> 47.222222 | P58: 6.6150098 | Q58: =J58/S58 -> 500.0539 | R58: =J58/W58 -> 569.50583 | S58: =COUNTIFS(Orders!$Z:$Z, $A58) -> 41 | T58: =COUNTIFS(Orders!$Z:$Z, $A58, Orders!$M:$M, "Cancelled") -> 5 | U58: =T58/S58 -> 0.12195122 | V58: =COUNTIFS(Orders!$Z:$Z, $A58, Orders!$M:$M, "pending") -> 0 | W58: =S58-T58 -> 36 | X58: =W58/S58 -> 0.87804878 | Y58: =COUNTIFS(Orders!$Z:$Z, $A58, Orders!$M:$M, "Delivered") -> 17 | Z58: =COUNTIFS(Orders!$Z:$Z, $A58, Orders!$M:$M, "Return Received") -> 19 | AA58: =W58-Y58-Z58-V58 -> 0 | AB58: =COUNTIFS(Orders!$Z:$Z, $A58, Orders!$M:$M, "Returned") + COUNTIFS(Orders!$Z:$Z, $A58, Orders!$M:$M, "Returned to Shipper") -> 0 | AC58: =COUNTIFS(Orders!$Z:$Z, $A58, Orders!$I:$I, "", Orders!$M:$M, "<>Cancelled") -> 0 | AD58: =SUMIFS(Orders!$U:$U, Orders!$Z:$Z, $A58, Orders!$M:$M, "Delivered") -> 68506 | AE58: =C58-AD58 -> 0 | AF58: =IFERROR(__xludf.DUMMYFUNCTION("IFERROR(TEXTJOIN("", "", TRUE, FILTER(Orders!$B$2:$B$2517, (TEXT(Orders!$D$2:$D$2517,""d-mmm"")=TEXT($A58,""d-mmm"")) * (ABS(Orders!$H$2:$H$2517 - Orders!$U$2:$U$2517) >= 1) * (Orders!$M$2:$M$2517=""Delivered""))), ""All Balanced"")"),"All Balanced") -> All Balanced | AG58: =IFERROR(__xludf.DUMMYFUNCTION("IFERROR(TEXTJOIN("", "", TRUE, FILTER(Orders!$I$2:$I$3000, (Orders!$M$2:$M$3000=""Delivered"") * (Orders!$N$2:$N$3000<>""Paid"") * (Orders!$Z$2:$Z$3000=$A58))), """")"),"") | AH58: =COUNTIFS(Orders!$M:$M, "Delivered", Orders!$N:$N, "<>Paid", Orders!$Z:$Z, $A58) -> 0
A59: 46035 | B59: =C59/Y59 -> 3267.3636 | C59: =SUMIFS(Orders!$H:$H, Orders!$Z:$Z, $A59, Orders!$M:$M, "Delivered") -> 35941 | D59: =SUMIFS(Orders!$Q:$Q, Orders!$Z:$Z, $A59, Orders!$M:$M, "Delivered") -> 13820 | E59: =D59/C59 -> 0.38451907 | F59: =C59-(C59*4/100) -> 34503.36 | G59: =C59-F59 -> 1437.64 | H59: =C59-D59 -> 22121 | I59: =IFERROR(J59/C59, 0)*100 -> 60.999193 | J59: 21923.72 | L59: =(200*W59)+C59*4% -> 5037.64 | M59: =SUMIFS(Orders!$W:$W, Orders!$Z:$Z, $A59) -> 5186.46 | N59: =H59-J59-K59-M59 -> -4989.18 | O59: =Y59/W59*100 -> 61.111111 | P59: 3.3973804 | Q59: =J59/S59 -> 1096.186 | R59: =J59/W59 -> 1217.9844 | S59: =COUNTIFS(Orders!$Z:$Z, $A59) -> 20 | T59: =COUNTIFS(Orders!$Z:$Z, $A59, Orders!$M:$M, "Cancelled") -> 2 | U59: =T59/S59 -> 0.1 | V59: =COUNTIFS(Orders!$Z:$Z, $A59, Orders!$M:$M, "pending") -> 0 | W59: =S59-T59 -> 18 | X59: =W59/S59 -> 0.9 | Y59: =COUNTIFS(Orders!$Z:$Z, $A59, Orders!$M:$M, "Delivered") -> 11 | Z59: =COUNTIFS(Orders!$Z:$Z, $A59, Orders!$M:$M, "Return Received") -> 7 | AA59: =W59-Y59-Z59-V59 -> 0 | AB59: =COUNTIFS(Orders!$Z:$Z, $A59, Orders!$M:$M, "Returned") + COUNTIFS(Orders!$Z:$Z, $A59, Orders!$M:$M, "Returned to Shipper") -> 0 | AC59: =COUNTIFS(Orders!$Z:$Z, $A59, Orders!$I:$I, "", Orders!$M:$M, "<>Cancelled") -> 0 | AD59: =SUMIFS(Orders!$U:$U, Orders!$Z:$Z, $A59, Orders!$M:$M, "Delivered") -> 35941 | AE59: =C59-AD59 -> 0 | AF59: =IFERROR(__xludf.DUMMYFUNCTION("IFERROR(TEXTJOIN("", "", TRUE, FILTER(Orders!$B$2:$B$2517, (TEXT(Orders!$D$2:$D$2517,""d-mmm"")=TEXT($A59,""d-mmm"")) * (ABS(Orders!$H$2:$H$2517 - Orders!$U$2:$U$2517) >= 1) * (Orders!$M$2:$M$2517=""Delivered""))), ""All Balanced"")"),"All Balanced") -> All Balanced | AG59: =IFERROR(__xludf.DUMMYFUNCTION("IFERROR(TEXTJOIN("", "", TRUE, FILTER(Orders!$I$2:$I$3000, (Orders!$M$2:$M$3000=""Delivered"") * (Orders!$N$2:$N$3000<>""Paid"") * (Orders!$Z$2:$Z$3000=$A59))), """")"),"") | AH59: =COUNTIFS(Orders!$M:$M, "Delivered", Orders!$N:$N, "<>Paid", Orders!$Z:$Z, $A59) -> 0
A60: 46036 | B60: =C60/Y60 -> 2781 | C60: =SUMIFS(Orders!$H:$H, Orders!$Z:$Z, $A60, Orders!$M:$M, "Delivered") -> 30591 | D60: =SUMIFS(Orders!$Q:$Q, Orders!$Z:$Z, $A60, Orders!$M:$M, "Delivered") -> 10505 | E60: =D60/C60 -> 0.34340165 | F60: =C60-(C60*4/100) -> 29367.36 | G60: =C60-F60 -> 1223.64 | H60: =C60-D60 -> 20086 | I60: =IFERROR(J60/C60, 0)*100 -> 14.382988 | J60: 4399.9 | L60: =(200*W60)+C60*4% -> 4223.64 | M60: =SUMIFS(Orders!$W:$W, Orders!$Z:$Z, $A60) -> 3782.45 | N60: =H60-J60-K60-M60 -> 11903.65 | O60: =Y60/W60*100 -> 73.333333 | P60: 6.1731389 | Q60: =J60/S60 -> 244.43889 | R60: =J60/W60 -> 293.32667 | S60: =COUNTIFS(Orders!$Z:$Z, $A60) -> 18 | T60: =COUNTIFS(Orders!$Z:$Z, $A60, Orders!$M:$M, "Cancelled") -> 3 | U60: =T60/S60 -> 0.16666667 | V60: =COUNTIFS(Orders!$Z:$Z, $A60, Orders!$M:$M, "pending") -> 0 | W60: =S60-T60 -> 15 | X60: =W60/S60 -> 0.83333333 | Y60: =COUNTIFS(Orders!$Z:$Z, $A60, Orders!$M:$M, "Delivered") -> 11 | Z60: =COUNTIFS(Orders!$Z:$Z, $A60, Orders!$M:$M, "Return Received") -> 4 | AA60: =W60-Y60-Z60-V60 -> 0 | AB60: =COUNTIFS(Orders!$Z:$Z, $A60, Orders!$M:$M, "Returned") + COUNTIFS(Orders!$Z:$Z, $A60, Orders!$M:$M, "Returned to Shipper") -> 0 | AC60: =COUNTIFS(Orders!$Z:$Z, $A60, Orders!$I:$I, "", Orders!$M:$M, "<>Cancelled") -> 0 | AD60: =SUMIFS(Orders!$U:$U, Orders!$Z:$Z, $A60, Orders!$M:$M, "Delivered") -> 27842 | AE60: =C60-AD60 -> 2749 | AF60: =IFERROR(__xludf.DUMMYFUNCTION("IFERROR(TEXTJOIN("", "", TRUE, FILTER(Orders!$B$2:$B$2517, (TEXT(Orders!$D$2:$D$2517,""d-mmm"")=TEXT($A60,""d-mmm"")) * (ABS(Orders!$H$2:$H$2517 - Orders!$U$2:$U$2517) >= 1) * (Orders!$M$2:$M$2517=""Delivered""))), ""All Balanced"")"),"TR28351") -> TR28351 | AG60: =IFERROR(__xludf.DUMMYFUNCTION("IFERROR(TEXTJOIN("", "", TRUE, FILTER(Orders!$I$2:$I$3000, (Orders!$M$2:$M$3000=""Delivered"") * (Orders!$N$2:$N$3000<>""Paid"") * (Orders!$Z$2:$Z$3000=$A60))), """")"),"") | AH60: =COUNTIFS(Orders!$M:$M, "Delivered", Orders!$N:$N, "<>Paid", Orders!$Z:$Z, $A60) -> 0
A61: 46037 | B61: =C61/Y61 -> 3193.3158 | C61: =SUMIFS(Orders!$H:$H, Orders!$Z:$Z, $A61, Orders!$M:$M, "Delivered") -> 60673 | D61: =SUMIFS(Orders!$Q:$Q, Orders!$Z:$Z, $A61, Orders!$M:$M, "Delivered") -> 19920 | E61: =D61/C61 -> 0.32831737 | F61: =C61-(C61*4/100) -> 58246.08 | G61: =C61-F61 -> 2426.92 | H61: =C61-D61 -> 40753 | I61: =IFERROR(J61/C61, 0)*100 -> 32.117598 | J61: 19486.71 | L61: =(200*W61)+C61*4% -> 8226.92 | M61: =SUMIFS(Orders!$W:$W, Orders!$Z:$Z, $A61) -> 8504.69 | N61: =H61-J61-K61-M61 -> 12761.6 | O61: =Y61/W61*100 -> 65.517241 | P61: 6.0482558 | Q61: =J61/S61 -> 573.13853 | R61: =J61/W61 -> 671.95552 | S61: =COUNTIFS(Orders!$Z:$Z, $A61) -> 34 | T61: =COUNTIFS(Orders!$Z:$Z, $A61, Orders!$M:$M, "Cancelled") -> 5 | U61: =T61/S61 -> 0.14705882 | V61: =COUNTIFS(Orders!$Z:$Z, $A61, Orders!$M:$M, "pending") -> 0 | W61: =S61-T61 -> 29 | X61: =W61/S61 -> 0.85294118 | Y61: =COUNTIFS(Orders!$Z:$Z, $A61, Orders!$M:$M, "Delivered") -> 19 | Z61: =COUNTIFS(Orders!$Z:$Z, $A61, Orders!$M:$M, "Return Received") -> 10 | AA61: =W61-Y61-Z61-V61 -> 0 | AB61: =COUNTIFS(Orders!$Z:$Z, $A61, Orders!$M:$M, "Returned") + COUNTIFS(Orders!$Z:$Z, $A61, Orders!$M:$M, "Returned to Shipper") -> 0 | AC61: =COUNTIFS(Orders!$Z:$Z, $A61, Orders!$I:$I, "", Orders!$M:$M, "<>Cancelled") -> 0 | AD61: =SUMIFS(Orders!$U:$U, Orders!$Z:$Z, $A61, Orders!$M:$M, "Delivered") -> 60673 | AE61: =C61-AD61 -> 0 | AF61: =IFERROR(__xludf.DUMMYFUNCTION("IFERROR(TEXTJOIN("", "", TRUE, FILTER(Orders!$B$2:$B$2517, (TEXT(Orders!$D$2:$D$2517,""d-mmm"")=TEXT($A61,""d-mmm"")) * (ABS(Orders!$H$2:$H$2517 - Orders!$U$2:$U$2517) >= 1) * (Orders!$M$2:$M$2517=""Delivered""))), ""All Balanced"")"),"All Balanced") -> All Balanced | AG61: =IFERROR(__xludf.DUMMYFUNCTION("IFERROR(TEXTJOIN("", "", TRUE, FILTER(Orders!$I$2:$I$3000, (Orders!$M$2:$M$3000=""Delivered"") * (Orders!$N$2:$N$3000<>""Paid"") * (Orders!$Z$2:$Z$3000=$A61))), """")"),"") | AH61: =COUNTIFS(Orders!$M:$M, "Delivered", Orders!$N:$N, "<>Paid", Orders!$Z:$Z, $A61) -> 0
A62: 46038 | B62: =C62/Y62 -> 4725.7619 | C62: =SUMIFS(Orders!$H:$H, Orders!$Z:$Z, $A62, Orders!$M:$M, "Delivered") -> 99241 | D62: =SUMIFS(Orders!$Q:$Q, Orders!$Z:$Z, $A62, Orders!$M:$M, "Delivered") -> 38190 | E62: =D62/C62 -> 0.38482079 | F62: =C62-(C62*4/100) -> 95271.36 | G62: =C62-F62 -> 3969.64 | H62: =C62-D62 -> 61051 | I62: =IFERROR(J62/C62, 0)*100 -> 23.981943 | J62: 23799.92 | L62: =(200*W62)+C62*4% -> 10369.64 | M62: =SUMIFS(Orders!$W:$W, Orders!$Z:$Z, $A62) -> 9485.84 | N62: =H62-J62-K62-M62 -> 27765.24 | O62: =Y62/W62*100 -> 65.625 | P62: 4.8768527 | Q62: =J62/S62 -> 679.99771 | R62: =J62/W62 -> 743.7475 | S62: =COUNTIFS(Orders!$Z:$Z, $A62) -> 35 | T62: =COUNTIFS(Orders!$Z:$Z, $A62, Orders!$M:$M, "Cancelled") -> 3 | U62: =T62/S62 -> 0.085714286 | V62: =COUNTIFS(Orders!$Z:$Z, $A62, Orders!$M:$M, "pending") -> 0 | W62: =S62-T62 -> 32 | X62: =W62/S62 -> 0.91428571 | Y62: =COUNTIFS(Orders!$Z:$Z, $A62, Orders!$M:$M, "Delivered") -> 21 | Z62: =COUNTIFS(Orders!$Z:$Z, $A62, Orders!$M:$M, "Return Received") -> 11 | AA62: =W62-Y62-Z62-V62 -> 0 | AB62: =COUNTIFS(Orders!$Z:$Z, $A62, Orders!$M:$M, "Returned") + COUNTIFS(Orders!$Z:$Z, $A62, Orders!$M:$M, "Returned to Shipper") -> 0 | AC62: =COUNTIFS(Orders!$Z:$Z, $A62, Orders!$I:$I, "", Orders!$M:$M, "<>Cancelled") -> 0 | AD62: =SUMIFS(Orders!$U:$U, Orders!$Z:$Z, $A62, Orders!$M:$M, "Delivered") -> 96142 | AE62: =C62-AD62 -> 3099 | AF62: =IFERROR(__xludf.DUMMYFUNCTION("IFERROR(TEXTJOIN("", "", TRUE, FILTER(Orders!$B$2:$B$2517, (TEXT(Orders!$D$2:$D$2517,""d-mmm"")=TEXT($A62,""d-mmm"")) * (ABS(Orders!$H$2:$H$2517 - Orders!$U$2:$U$2517) >= 1) * (Orders!$M$2:$M$2517=""Delivered""))), ""All Balanced"")"),"TR28392") -> TR28392 | AG62: =IFERROR(__xludf.DUMMYFUNCTION("IFERROR(TEXTJOIN("", "", TRUE, FILTER(Orders!$I$2:$I$3000, (Orders!$M$2:$M$3000=""Delivered"") * (Orders!$N$2:$N$3000<>""Paid"") * (Orders!$Z$2:$Z$3000=$A62))), """")"),"") | AH62: =COUNTIFS(Orders!$M:$M, "Delivered", Orders!$N:$N, "<>Paid", Orders!$Z:$Z, $A62) -> 0
A63: 46039 | B63: =C63/Y63 -> 3100.0625 | C63: =SUMIFS(Orders!$H:$H, Orders!$Z:$Z, $A63, Orders!$M:$M, "Delivered") -> 49601 | D63: =SUMIFS(Orders!$Q:$Q, Orders!$Z:$Z, $A63, Orders!$M:$M, "Delivered") -> 16660 | E63: =D63/C63 -> 0.33588032 | F63: =C63-(C63*4/100) -> 47616.96 | G63: =C63-F63 -> 1984.04 | H63: =C63-D63 -> 32941 | I63: =IFERROR(J63/C63, 0)*100 -> 50.375678 | J63: 24986.84 | L63: =(200*W63)+C63*4% -> 7184.04 | M63: =SUMIFS(Orders!$W:$W, Orders!$Z:$Z, $A63) -> 6959.72 | N63: =H63-J63-K63-M63 -> 994.44 | O63: =Y63/W63*100 -> 61.538462 | P63: 3.8514552 | Q63: =J63/S63 -> 832.89467 | R63: =J63/W63 -> 961.03231 | S63: =COUNTIFS(Orders!$Z:$Z, $A63) -> 30 | T63: =COUNTIFS(Orders!$Z:$Z, $A63, Orders!$M:$M, "Cancelled") -> 4 | U63: =T63/S63 -> 0.13333333 | V63: =COUNTIFS(Orders!$Z:$Z, $A63, Orders!$M:$M, "pending") -> 0 | W63: =S63-T63 -> 26 | X63: =W63/S63 -> 0.86666667 | Y63: =COUNTIFS(Orders!$Z:$Z, $A63, Orders!$M:$M, "Delivered") -> 16 | Z63: =COUNTIFS(Orders!$Z:$Z, $A63, Orders!$M:$M, "Return Received") -> 10 | AA63: =W63-Y63-Z63-V63 -> 0 | AB63: =COUNTIFS(Orders!$Z:$Z, $A63, Orders!$M:$M, "Returned") + COUNTIFS(Orders!$Z:$Z, $A63, Orders!$M:$M, "Returned to Shipper") -> 0 | AC63: =COUNTIFS(Orders!$Z:$Z, $A63, Orders!$I:$I, "", Orders!$M:$M, "<>Cancelled") -> 0 | AD63: =SUMIFS(Orders!$U:$U, Orders!$Z:$Z, $A63, Orders!$M:$M, "Delivered") -> 49601 | AE63: =C63-AD63 -> 0 | AF63: =IFERROR(__xludf.DUMMYFUNCTION("IFERROR(TEXTJOIN("", "", TRUE, FILTER(Orders!$B$2:$B$2517, (TEXT(Orders!$D$2:$D$2517,""d-mmm"")=TEXT($A63,""d-mmm"")) * (ABS(Orders!$H$2:$H$2517 - Orders!$U$2:$U$2517) >= 1) * (Orders!$M$2:$M$2517=""Delivered""))), ""All Balanced"")"),"All Balanced") -> All Balanced | AG63: =IFERROR(__xludf.DUMMYFUNCTION("IFERROR(TEXTJOIN("", "", TRUE, FILTER(Orders!$I$2:$I$3000, (Orders!$M$2:$M$3000=""Delivered"") * (Orders!$N$2:$N$3000<>""Paid"") * (Orders!$Z$2:$Z$3000=$A63))), """")"),"") | AH63: =COUNTIFS(Orders!$M:$M, "Delivered", Orders!$N:$N, "<>Paid", Orders!$Z:$Z, $A63) -> 0
A64: 46040 | B64: =C64/Y64 -> 3348.8333 | C64: =SUMIFS(Orders!$H:$H, Orders!$Z:$Z, $A64, Orders!$M:$M, "Delivered") -> 40186 | D64: =SUMIFS(Orders!$Q:$Q, Orders!$Z:$Z, $A64, Orders!$M:$M, "Delivered") -> 13270 | E64: =D64/C64 -> 0.3302145 | F64: =C64-(C64*4/100) -> 38578.56 | G64: =C64-F64 -> 1607.44 | H64: =C64-D64 -> 26916 | I64: =IFERROR(J64/C64, 0)*100 -> 52.949112 | J64: 21278.13 | L64: =(200*W64)+C64*4% -> 5807.44 | M64: =SUMIFS(Orders!$W:$W, Orders!$Z:$Z, $A64) -> 5474 | N64: =H64-J64-K64-M64 -> 163.87 | O64: =Y64/W64*100 -> 57.142857 | P64: 3.9430307 | Q64: =J64/S64 -> 851.1252 | R64: =J64/W64 -> 1013.2443 | S64: =COUNTIFS(Orders!$Z:$Z, $A64) -> 25 | T64: =COUNTIFS(Orders!$Z:$Z, $A64, Orders!$M:$M, "Cancelled") -> 4 | U64: =T64/S64 -> 0.16 | V64: =COUNTIFS(Orders!$Z:$Z, $A64, Orders!$M:$M, "pending") -> 0 | W64: =S64-T64 -> 21 | X64: =W64/S64 -> 0.84 | Y64: =COUNTIFS(Orders!$Z:$Z, $A64, Orders!$M:$M, "Delivered") -> 12 | Z64: =COUNTIFS(Orders!$Z:$Z, $A64, Orders!$M:$M, "Return Received") -> 9 | AA64: =W64-Y64-Z64-V64 -> 0 | AB64: =COUNTIFS(Orders!$Z:$Z, $A64, Orders!$M:$M, "Returned") + COUNTIFS(Orders!$Z:$Z, $A64, Orders!$M:$M, "Returned to Shipper") -> 0 | AC64: =COUNTIFS(Orders!$Z:$Z, $A64, Orders!$I:$I, "", Orders!$M:$M, "<>Cancelled") -> 0 | AD64: =SUMIFS(Orders!$U:$U, Orders!$Z:$Z, $A64, Orders!$M:$M, "Delivered") -> 40186 | AE64: =C64-AD64 -> 0 | AF64: =IFERROR(__xludf.DUMMYFUNCTION("IFERROR(TEXTJOIN("", "", TRUE, FILTER(Orders!$B$2:$B$2517, (TEXT(Orders!$D$2:$D$2517,""d-mmm"")=TEXT($A64,""d-mmm"")) * (ABS(Orders!$H$2:$H$2517 - Orders!$U$2:$U$2517) >= 1) * (Orders!$M$2:$M$2517=""Delivered""))), ""All Balanced"")"),"All Balanced") -> All Balanced | AG64: =IFERROR(__xludf.DUMMYFUNCTION("IFERROR(TEXTJOIN("", "", TRUE, FILTER(Orders!$I$2:$I$3000, (Orders!$M$2:$M$3000=""Delivered"") * (Orders!$N$2:$N$3000<>""Paid"") * (Orders!$Z$2:$Z$3000=$A64))), """")"),"") | AH64: =COUNTIFS(Orders!$M:$M, "Delivered", Orders!$N:$N, "<>Paid", Orders!$Z:$Z, $A64) -> 0
A65: 46041 | B65: =C65/Y65 -> 3075.4211 | C65: =SUMIFS(Orders!$H:$H, Orders!$Z:$Z, $A65, Orders!$M:$M, "Delivered") -> 58433 | D65: =SUMIFS(Orders!$Q:$Q, Orders!$Z:$Z, $A65, Orders!$M:$M, "Delivered") -> 21360 | E65: =D65/C65 -> 0.36554687 | F65: =C65-(C65*4/100) -> 56095.68 | G65: =C65-F65 -> 2337.32 | H65: =C65-D65 -> 37073 | I65: =IFERROR(J65/C65, 0)*100 -> 32.945014 | J65: 19250.76 | L65: =(200*W65)+C65*4% -> 7337.32 | M65: =SUMIFS(Orders!$W:$W, Orders!$Z:$Z, $A65) -> 7418.94 | N65: =H65-J65-K65-M65 -> 10403.3 | O65: =Y65/W65*100 -> 76 | P65: 5.713633 | Q65: =J65/S65 -> 620.99226 | R65: =J65/W65 -> 770.0304 | S65: =COUNTIFS(Orders!$Z:$Z, $A65) -> 31 | T65: =COUNTIFS(Orders!$Z:$Z, $A65, Orders!$M:$M, "Cancelled") -> 6 | U65: =T65/S65 -> 0.19354839 | V65: =COUNTIFS(Orders!$Z:$Z, $A65, Orders!$M:$M, "pending") -> 0 | W65: =S65-T65 -> 25 | X65: =W65/S65 -> 0.80645161 | Y65: =COUNTIFS(Orders!$Z:$Z, $A65, Orders!$M:$M, "Delivered") -> 19 | Z65: =COUNTIFS(Orders!$Z:$Z, $A65, Orders!$M:$M, "Return Received") -> 6 | AA65: =W65-Y65-Z65-V65 -> 0 | AB65: =COUNTIFS(Orders!$Z:$Z, $A65, Orders!$M:$M, "Returned") + COUNTIFS(Orders!$Z:$Z, $A65, Orders!$M:$M, "Returned to Shipper") -> 0 | AC65: =COUNTIFS(Orders!$Z:$Z, $A65, Orders!$I:$I, "", Orders!$M:$M, "<>Cancelled") -> 0 | AD65: =SUMIFS(Orders!$U:$U, Orders!$Z:$Z, $A65, Orders!$M:$M, "Delivered") -> 58433 | AE65: =C65-AD65 -> 0 | AF65: =IFERROR(__xludf.DUMMYFUNCTION("IFERROR(TEXTJOIN("", "", TRUE, FILTER(Orders!$B$2:$B$2517, (TEXT(Orders!$D$2:$D$2517,""d-mmm"")=TEXT($A65,""d-mmm"")) * (ABS(Orders!$H$2:$H$2517 - Orders!$U$2:$U$2517) >= 1) * (Orders!$M$2:$M$2517=""Delivered""))), ""All Balanced"")"),"All Balanced") -> All Balanced | AG65: =IFERROR(__xludf.DUMMYFUNCTION("IFERROR(TEXTJOIN("", "", TRUE, FILTER(Orders!$I$2:$I$3000, (Orders!$M$2:$M$3000=""Delivered"") * (Orders!$N$2:$N$3000<>""Paid"") * (Orders!$Z$2:$Z$3000=$A65))), """")"),"") | AH65: =COUNTIFS(Orders!$M:$M, "Delivered", Orders!$N:$N, "<>Paid", Orders!$Z:$Z, $A65) -> 0
A66: 46042 | B66: =C66/Y66 -> 3040.75 | C66: =SUMIFS(Orders!$H:$H, Orders!$Z:$Z, $A66, Orders!$M:$M, "Delivered") -> 36489 | D66: =SUMIFS(Orders!$Q:$Q, Orders!$Z:$Z, $A66, Orders!$M:$M, "Delivered") -> 13110 | E66: =D66/C66 -> 0.35928636 | F66: =C66-(C66*4/100) -> 35029.44 | G66: =C66-F66 -> 1459.56 | H66: =C66-D66 -> 23379 | I66: =IFERROR(J66/C66, 0)*100 -> 53.210173 | J66: 19415.86 | L66: =(200*W66)+C66*4% -> 6059.56 | M66: =SUMIFS(Orders!$W:$W, Orders!$Z:$Z, $A66) -> 6171.64 | N66: =H66-J66-K66-M66 -> -2208.5 | O66: =Y66/W66*100 -> 52.173913 | P66: 4.9749643 | Q66: =J66/S66 -> 693.42357 | R66: =J66/W66 -> 844.16783 | S66: =COUNTIFS(Orders!$Z:$Z, $A66) -> 28 | T66: =COUNTIFS(Orders!$Z:$Z, $A66, Orders!$M:$M, "Cancelled") -> 5 | U66: =T66/S66 -> 0.17857143 | V66: =COUNTIFS(Orders!$Z:$Z, $A66, Orders!$M:$M, "pending") -> 0 | W66: =S66-T66 -> 23 | X66: =W66/S66 -> 0.82142857 | Y66: =COUNTIFS(Orders!$Z:$Z, $A66, Orders!$M:$M, "Delivered") -> 12 | Z66: =COUNTIFS(Orders!$Z:$Z, $A66, Orders!$M:$M, "Return Received") -> 11 | AA66: =W66-Y66-Z66-V66 -> 0 | AB66: =COUNTIFS(Orders!$Z:$Z, $A66, Orders!$M:$M, "Returned") + COUNTIFS(Orders!$Z:$Z, $A66, Orders!$M:$M, "Returned to Shipper") -> 0 | AC66: =COUNTIFS(Orders!$Z:$Z, $A66, Orders!$I:$I, "", Orders!$M:$M, "<>Cancelled") -> 0 | AD66: =SUMIFS(Orders!$U:$U, Orders!$Z:$Z, $A66, Orders!$M:$M, "Delivered") -> 36489 | AE66: =C66-AD66 -> 0 | AF66: =IFERROR(__xludf.DUMMYFUNCTION("IFERROR(TEXTJOIN("", "", TRUE, FILTER(Orders!$B$2:$B$2517, (TEXT(Orders!$D$2:$D$2517,""d-mmm"")=TEXT($A66,""d-mmm"")) * (ABS(Orders!$H$2:$H$2517 - Orders!$U$2:$U$2517) >= 1) * (Orders!$M$2:$M$2517=""Delivered""))), ""All Balanced"")"),"All Balanced") -> All Balanced | AG66: =IFERROR(__xludf.DUMMYFUNCTION("IFERROR(TEXTJOIN("", "", TRUE, FILTER(Orders!$I$2:$I$3000, (Orders!$M$2:$M$3000=""Delivered"") * (Orders!$N$2:$N$3000<>""Paid"") * (Orders!$Z$2:$Z$3000=$A66))), """")"),"") | AH66: =COUNTIFS(Orders!$M:$M, "Delivered", Orders!$N:$N, "<>Paid", Orders!$Z:$Z, $A66) -> 0
A67: 46043 | B67: =C67/Y67 -> 3264.5789 | C67: =SUMIFS(Orders!$H:$H, Orders!$Z:$Z, $A67, Orders!$M:$M, "Delivered") -> 62027 | D67: =SUMIFS(Orders!$Q:$Q, Orders!$Z:$Z, $A67, Orders!$M:$M, "Delivered") -> 21330 | E67: =D67/C67 -> 0.3438825 | F67: =C67-(C67*4/100) -> 59545.92 | G67: =C67-F67 -> 2481.08 | H67: =C67-D67 -> 40697 | I67: =IFERROR(J67/C67, 0)*100 -> 30.426298 | J67: 18872.52 | L67: =(200*W67)+C67*4% -> 7681.08 | M67: =SUMIFS(Orders!$W:$W, Orders!$Z:$Z, $A67) -> 7360.94 | N67: =H67-J67-K67-M67 -> 14463.54 | O67: =Y67/W67*100 -> 73.076923 | P67: 4.4833431 | Q67: =J67/S67 -> 698.98222 | R67: =J67/W67 -> 725.86615 | S67: =COUNTIFS(Orders!$Z:$Z, $A67) -> 27 | T67: =COUNTIFS(Orders!$Z:$Z, $A67, Orders!$M:$M, "Cancelled") -> 1 | U67: =T67/S67 -> 0.037037037 | V67: =COUNTIFS(Orders!$Z:$Z, $A67, Orders!$M:$M, "pending") -> 0 | W67: =S67-T67 -> 26 | X67: =W67/S67 -> 0.96296296 | Y67: =COUNTIFS(Orders!$Z:$Z, $A67, Orders!$M:$M, "Delivered") -> 19 | Z67: =COUNTIFS(Orders!$Z:$Z, $A67, Orders!$M:$M, "Return Received") -> 7 | AA67: =W67-Y67-Z67-V67 -> 0 | AB67: =COUNTIFS(Orders!$Z:$Z, $A67, Orders!$M:$M, "Returned") + COUNTIFS(Orders!$Z:$Z, $A67, Orders!$M:$M, "Returned to Shipper") -> 0 | AC67: =COUNTIFS(Orders!$Z:$Z, $A67, Orders!$I:$I, "", Orders!$M:$M, "<>Cancelled") -> 0 | AD67: =SUMIFS(Orders!$U:$U, Orders!$Z:$Z, $A67, Orders!$M:$M, "Delivered") -> 62027 | AE67: =C67-AD67 -> 0 | AF67: =IFERROR(__xludf.DUMMYFUNCTION("IFERROR(TEXTJOIN("", "", TRUE, FILTER(Orders!$B$2:$B$2517, (TEXT(Orders!$D$2:$D$2517,""d-mmm"")=TEXT($A67,""d-mmm"")) * (ABS(Orders!$H$2:$H$2517 - Orders!$U$2:$U$2517) >= 1) * (Orders!$M$2:$M$2517=""Delivered""))), ""All Balanced"")"),"All Balanced") -> All Balanced | AG67: =IFERROR(__xludf.DUMMYFUNCTION("IFERROR(TEXTJOIN("", "", TRUE, FILTER(Orders!$I$2:$I$3000, (Orders!$M$2:$M$3000=""Delivered"") * (Orders!$N$2:$N$3000<>""Paid"") * (Orders!$Z$2:$Z$3000=$A67))), """")"),"") | AH67: =COUNTIFS(Orders!$M:$M, "Delivered", Orders!$N:$N, "<>Paid", Orders!$Z:$Z, $A67) -> 0
A68: 46044 | B68: =C68/Y68 -> 3214.625 | C68: =SUMIFS(Orders!$H:$H, Orders!$Z:$Z, $A68, Orders!$M:$M, "Delivered") -> 51434 | D68: =SUMIFS(Orders!$Q:$Q, Orders!$Z:$Z, $A68, Orders!$M:$M, "Delivered") -> 17545 | E68: =D68/C68 -> 0.34111677 | F68: =C68-(C68*4/100) -> 49376.64 | G68: =C68-F68 -> 2057.36 | H68: =C68-D68 -> 33889 | I68: =IFERROR(J68/C68, 0)*100 -> 35.023603 | J68: 18014.04 | L68: =(200*W68)+C68*4% -> 6857.36 | M68: =SUMIFS(Orders!$W:$W, Orders!$Z:$Z, $A68) -> 7302.74 | N68: =H68-J68-K68-M68 -> 8572.22 | O68: =Y68/W68*100 -> 66.666667 | P68: 6.4429911 | Q68: =J68/S68 -> 600.468 | R68: =J68/W68 -> 750.585 | S68: =COUNTIFS(Orders!$Z:$Z, $A68) -> 30 | T68: =COUNTIFS(Orders!$Z:$Z, $A68, Orders!$M:$M, "Cancelled") -> 6 | U68: =T68/S68 -> 0.2 | V68: =COUNTIFS(Orders!$Z:$Z, $A68, Orders!$M:$M, "pending") -> 0 | W68: =S68-T68 -> 24 | X68: =W68/S68 -> 0.8 | Y68: =COUNTIFS(Orders!$Z:$Z, $A68, Orders!$M:$M, "Delivered") -> 16 | Z68: =COUNTIFS(Orders!$Z:$Z, $A68, Orders!$M:$M, "Return Received") -> 8 | AA68: =W68-Y68-Z68-V68 -> 0 | AB68: =COUNTIFS(Orders!$Z:$Z, $A68, Orders!$M:$M, "Returned") + COUNTIFS(Orders!$Z:$Z, $A68, Orders!$M:$M, "Returned to Shipper") -> 0 | AC68: =COUNTIFS(Orders!$Z:$Z, $A68, Orders!$I:$I, "", Orders!$M:$M, "<>Cancelled") -> 0 | AD68: =SUMIFS(Orders!$U:$U, Orders!$Z:$Z, $A68, Orders!$M:$M, "Delivered") -> 51434 | AE68: =C68-AD68 -> 0 | AF68: =IFERROR(__xludf.DUMMYFUNCTION("IFERROR(TEXTJOIN("", "", TRUE, FILTER(Orders!$B$2:$B$2517, (TEXT(Orders!$D$2:$D$2517,""d-mmm"")=TEXT($A68,""d-mmm"")) * (ABS(Orders!$H$2:$H$2517 - Orders!$U$2:$U$2517) >= 1) * (Orders!$M$2:$M$2517=""Delivered""))), ""All Balanced"")"),"All Balanced") -> All Balanced | AG68: =IFERROR(__xludf.DUMMYFUNCTION("IFERROR(TEXTJOIN("", "", TRUE, FILTER(Orders!$I$2:$I$3000, (Orders!$M$2:$M$3000=""Delivered"") * (Orders!$N$2:$N$3000<>""Paid"") * (Orders!$Z$2:$Z$3000=$A68))), """")"),"") | AH68: =COUNTIFS(Orders!$M:$M, "Delivered", Orders!$N:$N, "<>Paid", Orders!$Z:$Z, $A68) -> 0
A69: 46045 | B69: =C69/Y69 -> 4689.3333 | C69: =SUMIFS(Orders!$H:$H, Orders!$Z:$Z, $A69, Orders!$M:$M, "Delivered") -> 98476 | D69: =SUMIFS(Orders!$Q:$Q, Orders!$Z:$Z, $A69, Orders!$M:$M, "Delivered") -> 40315 | E69: =D69/C69 -> 0.40938909 | F69: =C69-(C69*4/100) -> 94536.96 | G69: =C69-F69 -> 3939.04 | H69: =C69-D69 -> 58161 | I69: =IFERROR(J69/C69, 0)*100 -> 20.034973 | J69: 19729.64 | L69: =(200*W69)+C69*4% -> 10539.04 | M69: =SUMIFS(Orders!$W:$W, Orders!$Z:$Z, $A69) -> 9094.94 | N69: =H69-J69-K69-M69 -> 29336.42 | O69: =Y69/W69*100 -> 63.636364 | P69: 7.1342392 | Q69: =J69/S69 -> 505.88821 | R69: =J69/W69 -> 597.86788 | S69: =COUNTIFS(Orders!$Z:$Z, $A69) -> 39 | T69: =COUNTIFS(Orders!$Z:$Z, $A69, Orders!$M:$M, "Cancelled") -> 6 | U69: =T69/S69 -> 0.15384615 | V69: =COUNTIFS(Orders!$Z:$Z, $A69, Orders!$M:$M, "pending") -> 0 | W69: =S69-T69 -> 33 | X69: =W69/S69 -> 0.84615385 | Y69: =COUNTIFS(Orders!$Z:$Z, $A69, Orders!$M:$M, "Delivered") -> 21 | Z69: =COUNTIFS(Orders!$Z:$Z, $A69, Orders!$M:$M, "Return Received") -> 12 | AA69: =W69-Y69-Z69-V69 -> 0 | AB69: =COUNTIFS(Orders!$Z:$Z, $A69, Orders!$M:$M, "Returned") + COUNTIFS(Orders!$Z:$Z, $A69, Orders!$M:$M, "Returned to Shipper") -> 0 | AC69: =COUNTIFS(Orders!$Z:$Z, $A69, Orders!$I:$I, "", Orders!$M:$M, "<>Cancelled") -> 0 | AD69: =SUMIFS(Orders!$U:$U, Orders!$Z:$Z, $A69, Orders!$M:$M, "Delivered") -> 98476 | AE69: =C69-AD69 -> 0 | AF69: =IFERROR(__xludf.DUMMYFUNCTION("IFERROR(TEXTJOIN("", "", TRUE, FILTER(Orders!$B$2:$B$2517, (TEXT(Orders!$D$2:$D$2517,""d-mmm"")=TEXT($A69,""d-mmm"")) * (ABS(Orders!$H$2:$H$2517 - Orders!$U$2:$U$2517) >= 1) * (Orders!$M$2:$M$2517=""Delivered""))), ""All Balanced"")"),"All Balanced") -> All Balanced | AG69: =IFERROR(__xludf.DUMMYFUNCTION("IFERROR(TEXTJOIN("", "", TRUE, FILTER(Orders!$I$2:$I$3000, (Orders!$M$2:$M$3000=""Delivered"") * (Orders!$N$2:$N$3000<>""Paid"") * (Orders!$Z$2:$Z$3000=$A69))), """")"),"") | AH69: =COUNTIFS(Orders!$M:$M, "Delivered", Orders!$N:$N, "<>Paid", Orders!$Z:$Z, $A69) -> 0
A70: 46046 | B70: =C70/Y70 -> 3238 | C70: =SUMIFS(Orders!$H:$H, Orders!$Z:$Z, $A70, Orders!$M:$M, "Delivered") -> 61522 | D70: =SUMIFS(Orders!$Q:$Q, Orders!$Z:$Z, $A70, Orders!$M:$M, "Delivered") -> 20920 | E70: =D70/C70 -> 0.34004096 | F70: =C70-(C70*4/100) -> 59061.12 | G70: =C70-F70 -> 2460.88 | H70: =C70-D70 -> 40602 | I70: =IFERROR(J70/C70, 0)*100 -> 31.628864 | J70: 19458.71 | L70: =(200*W70)+C70*4% -> 7460.88 | M70: =SUMIFS(Orders!$W:$W, Orders!$Z:$Z, $A70) -> 7495.9152 | N70: =H70-J70-K70-M70 -> 13647.375 | O70: =Y70/W70*100 -> 76 | P70: 5.3765629 | Q70: =J70/S70 -> 648.62367 | R70: =J70/W70 -> 778.3484 | S70: =COUNTIFS(Orders!$Z:$Z, $A70) -> 30 | T70: =COUNTIFS(Orders!$Z:$Z, $A70, Orders!$M:$M, "Cancelled") -> 5 | U70: =T70/S70 -> 0.16666667 | V70: =COUNTIFS(Orders!$Z:$Z, $A70, Orders!$M:$M, "pending") -> 0 | W70: =S70-T70 -> 25 | X70: =W70/S70 -> 0.83333333 | Y70: =COUNTIFS(Orders!$Z:$Z, $A70, Orders!$M:$M, "Delivered") -> 19 | Z70: =COUNTIFS(Orders!$Z:$Z, $A70, Orders!$M:$M, "Return Received") -> 6 | AA70: =W70-Y70-Z70-V70 -> 0 | AB70: =COUNTIFS(Orders!$Z:$Z, $A70, Orders!$M:$M, "Returned") + COUNTIFS(Orders!$Z:$Z, $A70, Orders!$M:$M, "Returned to Shipper") -> 0 | AC70: =COUNTIFS(Orders!$Z:$Z, $A70, Orders!$I:$I, "", Orders!$M:$M, "<>Cancelled") -> 0 | AD70: =SUMIFS(Orders!$U:$U, Orders!$Z:$Z, $A70, Orders!$M:$M, "Delivered") -> 61522 | AE70: =C70-AD70 -> 0 | AF70: =IFERROR(__xludf.DUMMYFUNCTION("IFERROR(TEXTJOIN("", "", TRUE, FILTER(Orders!$B$2:$B$2517, (TEXT(Orders!$D$2:$D$2517,""d-mmm"")=TEXT($A70,""d-mmm"")) * (ABS(Orders!$H$2:$H$2517 - Orders!$U$2:$U$2517) >= 1) * (Orders!$M$2:$M$2517=""Delivered""))), ""All Balanced"")"),"All Balanced") -> All Balanced | AG70: =IFERROR(__xludf.DUMMYFUNCTION("IFERROR(TEXTJOIN("", "", TRUE, FILTER(Orders!$I$2:$I$3000, (Orders!$M$2:$M$3000=""Delivered"") * (Orders!$N$2:$N$3000<>""Paid"") * (Orders!$Z$2:$Z$3000=$A70))), """")"),"") | AH70: =COUNTIFS(Orders!$M:$M, "Delivered", Orders!$N:$N, "<>Paid", Orders!$Z:$Z, $A70) -> 0
A71: 46047 | B71: =C71/Y71 -> 3188.8 | C71: =SUMIFS(Orders!$H:$H, Orders!$Z:$Z, $A71, Orders!$M:$M, "Delivered") -> 31888 | D71: =SUMIFS(Orders!$Q:$Q, Orders!$Z:$Z, $A71, Orders!$M:$M, "Delivered") -> 11030 | E71: =D71/C71 -> 0.34589814 | F71: =C71-(C71*4/100) -> 30612.48 | G71: =C71-F71 -> 1275.52 | H71: =C71-D71 -> 20858 | I71: =IFERROR(J71/C71, 0)*100 -> 36.804629 | J71: 11736.26 | L71: =(200*W71)+C71*4% -> 3875.52 | M71: =SUMIFS(Orders!$W:$W, Orders!$Z:$Z, $A71) -> 3937 | N71: =H71-J71-K71-M71 -> 5184.74 | O71: =Y71/W71*100 -> 76.923077 | P71: 3.8085803 | Q71: =J71/S71 -> 838.30429 | R71: =J71/W71 -> 902.78923 | S71: =COUNTIFS(Orders!$Z:$Z, $A71) -> 14 | T71: =COUNTIFS(Orders!$Z:$Z, $A71, Orders!$M:$M, "Cancelled") -> 1 | U71: =T71/S71 -> 0.071428571 | V71: =COUNTIFS(Orders!$Z:$Z, $A71, Orders!$M:$M, "pending") -> 0 | W71: =S71-T71 -> 13 | X71: =W71/S71 -> 0.92857143 | Y71: =COUNTIFS(Orders!$Z:$Z, $A71, Orders!$M:$M, "Delivered") -> 10 | Z71: =COUNTIFS(Orders!$Z:$Z, $A71, Orders!$M:$M, "Return Received") -> 3 | AA71: =W71-Y71-Z71-V71 -> 0 | AB71: =COUNTIFS(Orders!$Z:$Z, $A71, Orders!$M:$M, "Returned") + COUNTIFS(Orders!$Z:$Z, $A71, Orders!$M:$M, "Returned to Shipper") -> 0 | AC71: =COUNTIFS(Orders!$Z:$Z, $A71, Orders!$I:$I, "", Orders!$M:$M, "<>Cancelled") -> 0 | AD71: =SUMIFS(Orders!$U:$U, Orders!$Z:$Z, $A71, Orders!$M:$M, "Delivered") -> 31888 | AE71: =C71-AD71 -> 0 | AF71: =IFERROR(__xludf.DUMMYFUNCTION("IFERROR(TEXTJOIN("", "", TRUE, FILTER(Orders!$B$2:$B$2517, (TEXT(Orders!$D$2:$D$2517,""d-mmm"")=TEXT($A71,""d-mmm"")) * (ABS(Orders!$H$2:$H$2517 - Orders!$U$2:$U$2517) >= 1) * (Orders!$M$2:$M$2517=""Delivered""))), ""All Balanced"")"),"All Balanced") -> All Balanced | AG71: =IFERROR(__xludf.DUMMYFUNCTION("IFERROR(TEXTJOIN("", "", TRUE, FILTER(Orders!$I$2:$I$3000, (Orders!$M$2:$M$3000=""Delivered"") * (Orders!$N$2:$N$3000<>""Paid"") * (Orders!$Z$2:$Z$3000=$A71))), """")"),"") | AH71: =COUNTIFS(Orders!$M:$M, "Delivered", Orders!$N:$N, "<>Paid", Orders!$Z:$Z, $A71) -> 0
A72: 46048 | B72: =C72/Y72 -> 3458.0455 | C72: =SUMIFS(Orders!$H:$H, Orders!$Z:$Z, $A72, Orders!$M:$M, "Delivered") -> 76077 | D72: =SUMIFS(Orders!$Q:$Q, Orders!$Z:$Z, $A72, Orders!$M:$M, "Delivered") -> 28130 | E72: =D72/C72 -> 0.36975696 | F72: =C72-(C72*4/100) -> 73033.92 | G72: =C72-F72 -> 3043.08 | H72: =C72-D72 -> 47947 | I72: =IFERROR(J72/C72, 0)*100 -> 29.914113 | J72: 22757.76 | L72: =(200*W72)+C72*4% -> 9643.08 | M72: =SUMIFS(Orders!$W:$W, Orders!$Z:$Z, $A72) -> 9781.4676 | N72: =H72-J72-K72-M72 -> 15407.772 | O72: =Y72/W72*100 -> 66.666667 | P72: 5.2111111 | Q72: =J72/S72 -> 598.88842 | R72: =J72/W72 -> 689.62909 | S72: =COUNTIFS(Orders!$Z:$Z, $A72) -> 38 | T72: =COUNTIFS(Orders!$Z:$Z, $A72, Orders!$M:$M, "Cancelled") -> 5 | U72: =T72/S72 -> 0.13157895 | V72: =COUNTIFS(Orders!$Z:$Z, $A72, Orders!$M:$M, "pending") -> 0 | W72: =S72-T72 -> 33 | X72: =W72/S72 -> 0.86842105 | Y72: =COUNTIFS(Orders!$Z:$Z, $A72, Orders!$M:$M, "Delivered") -> 22 | Z72: =COUNTIFS(Orders!$Z:$Z, $A72, Orders!$M:$M, "Return Received") -> 11 | AA72: =W72-Y72-Z72-V72 -> 0 | AB72: =COUNTIFS(Orders!$Z:$Z, $A72, Orders!$M:$M, "Returned") + COUNTIFS(Orders!$Z:$Z, $A72, Orders!$M:$M, "Returned to Shipper") -> 0 | AC72: =COUNTIFS(Orders!$Z:$Z, $A72, Orders!$I:$I, "", Orders!$M:$M, "<>Cancelled") -> 0 | AD72: =SUMIFS(Orders!$U:$U, Orders!$Z:$Z, $A72, Orders!$M:$M, "Delivered") -> 76077 | AE72: =C72-AD72 -> 0 | AF72: =IFERROR(__xludf.DUMMYFUNCTION("IFERROR(TEXTJOIN("", "", TRUE, FILTER(Orders!$B$2:$B$2517, (TEXT(Orders!$D$2:$D$2517,""d-mmm"")=TEXT($A72,""d-mmm"")) * (ABS(Orders!$H$2:$H$2517 - Orders!$U$2:$U$2517) >= 1) * (Orders!$M$2:$M$2517=""Delivered""))), ""All Balanced"")"),"All Balanced") -> All Balanced | AG72: =IFERROR(__xludf.DUMMYFUNCTION("IFERROR(TEXTJOIN("", "", TRUE, FILTER(Orders!$I$2:$I$3000, (Orders!$M$2:$M$3000=""Delivered"") * (Orders!$N$2:$N$3000<>""Paid"") * (Orders!$Z$2:$Z$3000=$A72))), """")"),"") | AH72: =COUNTIFS(Orders!$M:$M, "Delivered", Orders!$N:$N, "<>Paid", Orders!$Z:$Z, $A72) -> 0
A73: 46049 | B73: =C73/Y73 -> 2891.9286 | C73: =SUMIFS(Orders!$H:$H, Orders!$Z:$Z, $A73, Orders!$M:$M, "Delivered") -> 40487 | D73: =SUMIFS(Orders!$Q:$Q, Orders!$Z:$Z, $A73, Orders!$M:$M, "Delivered") -> 14895 | E73: =D73/C73 -> 0.36789587 | F73: =C73-(C73*4/100) -> 38867.52 | G73: =C73-F73 -> 1619.48 | H73: =C73-D73 -> 25592 | I73: =IFERROR(J73/C73, 0)*100 -> 53.559982 | J73: 21684.83 | L73: =(200*W73)+C73*4% -> 6219.48 | M73: =SUMIFS(Orders!$W:$W, Orders!$Z:$Z, $A73) -> 6298.5376 | N73: =H73-J73-K73-M73 -> -2391.3676 | O73: =Y73/W73*100 -> 60.869565 | P73: 3.6327427 | Q73: =J73/S73 -> 722.82767 | R73: =J73/W73 -> 942.8187 | S73: =COUNTIFS(Orders!$Z:$Z, $A73) -> 30 | T73: =COUNTIFS(Orders!$Z:$Z, $A73, Orders!$M:$M, "Cancelled") -> 7 | U73: =T73/S73 -> 0.23333333 | V73: =COUNTIFS(Orders!$Z:$Z, $A73, Orders!$M:$M, "pending") -> 0 | W73: =S73-T73 -> 23 | X73: =W73/S73 -> 0.76666667 | Y73: =COUNTIFS(Orders!$Z:$Z, $A73, Orders!$M:$M, "Delivered") -> 14 | Z73: =COUNTIFS(Orders!$Z:$Z, $A73, Orders!$M:$M, "Return Received") -> 9 | AA73: =W73-Y73-Z73-V73 -> 0 | AB73: =COUNTIFS(Orders!$Z:$Z, $A73, Orders!$M:$M, "Returned") + COUNTIFS(Orders!$Z:$Z, $A73, Orders!$M:$M, "Returned to Shipper") -> 0 | AC73: =COUNTIFS(Orders!$Z:$Z, $A73, Orders!$I:$I, "", Orders!$M:$M, "<>Cancelled") -> 0 | AD73: =SUMIFS(Orders!$U:$U, Orders!$Z:$Z, $A73, Orders!$M:$M, "Delivered") -> 40487 | AE73: =C73-AD73 -> 0 | AF73: =IFERROR(__xludf.DUMMYFUNCTION("IFERROR(TEXTJOIN("", "", TRUE, FILTER(Orders!$B$2:$B$2517, (TEXT(Orders!$D$2:$D$2517,""d-mmm"")=TEXT($A73,""d-mmm"")) * (ABS(Orders!$H$2:$H$2517 - Orders!$U$2:$U$2517) >= 1) * (Orders!$M$2:$M$2517=""Delivered""))), ""All Balanced"")"),"All Balanced") -> All Balanced | AG73: =IFERROR(__xludf.DUMMYFUNCTION("IFERROR(TEXTJOIN("", "", TRUE, FILTER(Orders!$I$2:$I$3000, (Orders!$M$2:$M$3000=""Delivered"") * (Orders!$N$2:$N$3000<>""Paid"") * (Orders!$Z$2:$Z$3000=$A73))), """")"),"") | AH73: =COUNTIFS(Orders!$M:$M, "Delivered", Orders!$N:$N, "<>Paid", Orders!$Z:$Z, $A73) -> 0
A74: 46050 | B74: =C74/Y74 -> 3143.9474 | C74: =SUMIFS(Orders!$H:$H, Orders!$Z:$Z, $A74, Orders!$M:$M, "Delivered") -> 59735 | D74: =SUMIFS(Orders!$Q:$Q, Orders!$Z:$Z, $A74, Orders!$M:$M, "Delivered") -> 22690 | E74: =D74/C74 -> 0.37984431 | F74: =C74-(C74*4/100) -> 57345.6 | G74: =C74-F74 -> 2389.4 | H74: =C74-D74 -> 37045 | I74: =IFERROR(J74/C74, 0)*100 -> 35.47545 | J74: 21191.26 | L74: =(200*W74)+C74*4% -> 7389.4 | M74: =SUMIFS(Orders!$W:$W, Orders!$Z:$Z, $A74) -> 6986.99 | N74: =H74-J74-K74-M74 -> 8866.75 | O74: =Y74/W74*100 -> 76 | P74: 5.0752202 | Q74: =J74/S74 -> 706.37533 | R74: =J74/W74 -> 847.6504 | S74: =COUNTIFS(Orders!$Z:$Z, $A74) -> 30 | T74: =COUNTIFS(Orders!$Z:$Z, $A74, Orders!$M:$M, "Cancelled") -> 5 | U74: =T74/S74 -> 0.16666667 | V74: =COUNTIFS(Orders!$Z:$Z, $A74, Orders!$M:$M, "pending") -> 0 | W74: =S74-T74 -> 25 | X74: =W74/S74 -> 0.83333333 | Y74: =COUNTIFS(Orders!$Z:$Z, $A74, Orders!$M:$M, "Delivered") -> 19 | Z74: =COUNTIFS(Orders!$Z:$Z, $A74, Orders!$M:$M, "Return Received") -> 6 | AA74: =W74-Y74-Z74-V74 -> 0 | AB74: =COUNTIFS(Orders!$Z:$Z, $A74, Orders!$M:$M, "Returned") + COUNTIFS(Orders!$Z:$Z, $A74, Orders!$M:$M, "Returned to Shipper") -> 0 | AC74: =COUNTIFS(Orders!$Z:$Z, $A74, Orders!$I:$I, "", Orders!$M:$M, "<>Cancelled") -> 0 | AD74: =SUMIFS(Orders!$U:$U, Orders!$Z:$Z, $A74, Orders!$M:$M, "Delivered") -> 56885 | AE74: =C74-AD74 -> 2850 | AF74: =IFERROR(__xludf.DUMMYFUNCTION("IFERROR(TEXTJOIN("", "", TRUE, FILTER(Orders!$B$2:$B$2517, (TEXT(Orders!$D$2:$D$2517,""d-mmm"")=TEXT($A74,""d-mmm"")) * (ABS(Orders!$H$2:$H$2517 - Orders!$U$2:$U$2517) >= 1) * (Orders!$M$2:$M$2517=""Delivered""))), ""All Balanced"")"),"TR28769") -> TR28769 | AG74: =IFERROR(__xludf.DUMMYFUNCTION("IFERROR(TEXTJOIN("", "", TRUE, FILTER(Orders!$I$2:$I$3000, (Orders!$M$2:$M$3000=""Delivered"") * (Orders!$N$2:$N$3000<>""Paid"") * (Orders!$Z$2:$Z$3000=$A74))), """")"),"") | AH74: =COUNTIFS(Orders!$M:$M, "Delivered", Orders!$N:$N, "<>Paid", Orders!$Z:$Z, $A74) -> 0
A75: 46051 | B75: =C75/Y75 -> 4089.8182 | C75: =SUMIFS(Orders!$H:$H, Orders!$Z:$Z, $A75, Orders!$M:$M, "Delivered") -> 44988 | D75: =SUMIFS(Orders!$Q:$Q, Orders!$Z:$Z, $A75, Orders!$M:$M, "Delivered") -> 16820 | E75: =D75/C75 -> 0.37387748 | F75: =C75-(C75*4/100) -> 43188.48 | G75: =C75-F75 -> 1799.52 | H75: =C75-D75 -> 28168 | I75: =IFERROR(J75/C75, 0)*100 -> 47.386992 | J75: 21318.46 | L75: =(200*W75)+C75*4% -> 6199.52 | M75: =SUMIFS(Orders!$W:$W, Orders!$Z:$Z, $A75) -> 6131.08 | N75: =H75-J75-K75-M75 -> 718.46 | O75: =Y75/W75*100 -> 50 | P75: 4.8727014 | Q75: =J75/S75 -> 761.37357 | R75: =J75/W75 -> 969.02091 | S75: =COUNTIFS(Orders!$Z:$Z, $A75) -> 28 | T75: =COUNTIFS(Orders!$Z:$Z, $A75, Orders!$M:$M, "Cancelled") -> 6 | U75: =T75/S75 -> 0.21428571 | V75: =COUNTIFS(Orders!$Z:$Z, $A75, Orders!$M:$M, "pending") -> 1 | W75: =S75-T75 -> 22 | X75: =W75/S75 -> 0.78571429 | Y75: =COUNTIFS(Orders!$Z:$Z, $A75, Orders!$M:$M, "Delivered") -> 11 | Z75: =COUNTIFS(Orders!$Z:$Z, $A75, Orders!$M:$M, "Return Received") -> 10 | AA75: =W75-Y75-Z75-V75 -> 0 | AB75: =COUNTIFS(Orders!$Z:$Z, $A75, Orders!$M:$M, "Returned") + COUNTIFS(Orders!$Z:$Z, $A75, Orders!$M:$M, "Returned to Shipper") -> 0 | AC75: =COUNTIFS(Orders!$Z:$Z, $A75, Orders!$I:$I, "", Orders!$M:$M, "<>Cancelled") -> 0 | AD75: =SUMIFS(Orders!$U:$U, Orders!$Z:$Z, $A75, Orders!$M:$M, "Delivered") -> 44988 | AE75: =C75-AD75 -> 0 | AF75: =IFERROR(__xludf.DUMMYFUNCTION("IFERROR(TEXTJOIN("", "", TRUE, FILTER(Orders!$B$2:$B$2517, (TEXT(Orders!$D$2:$D$2517,""d-mmm"")=TEXT($A75,""d-mmm"")) * (ABS(Orders!$H$2:$H$2517 - Orders!$U$2:$U$2517) >= 1) * (Orders!$M$2:$M$2517=""Delivered""))), ""All Balanced"")"),"All Balanced") -> All Balanced | AG75: =IFERROR(__xludf.DUMMYFUNCTION("IFERROR(TEXTJOIN("", "", TRUE, FILTER(Orders!$I$2:$I$3000, (Orders!$M$2:$M$3000=""Delivered"") * (Orders!$N$2:$N$3000<>""Paid"") * (Orders!$Z$2:$Z$3000=$A75))), """")"),"") | AH75: =COUNTIFS(Orders!$M:$M, "Delivered", Orders!$N:$N, "<>Paid", Orders!$Z:$Z, $A75) -> 0
A76: 46052 | B76: =C76/Y76 -> 2994.2727 | C76: =SUMIFS(Orders!$H:$H, Orders!$Z:$Z, $A76, Orders!$M:$M, "Delivered") -> 32937 | D76: =SUMIFS(Orders!$Q:$Q, Orders!$Z:$Z, $A76, Orders!$M:$M, "Delivered") -> 11280 | E76: =D76/C76 -> 0.34247199 | F76: =C76-(C76*4/100) -> 31619.52 | G76: =C76-F76 -> 1317.48 | H76: =C76-D76 -> 21657 | I76: =IFERROR(J76/C76, 0)*100 -> 53.793424 | J76: 17717.94 | L76: =(200*W76)+C76*4% -> 4317.48 | M76: =SUMIFS(Orders!$W:$W, Orders!$Z:$Z, $A76) -> 4457.5376 | N76: =H76-J76-K76-M76 -> -518.4776 | O76: =Y76/W76*100 -> 73.333333 | P76: 2.8857245 | Q76: =J76/S76 -> 1042.2318 | R76: =J76/W76 -> 1181.196 | S76: =COUNTIFS(Orders!$Z:$Z, $A76) -> 17 | T76: =COUNTIFS(Orders!$Z:$Z, $A76, Orders!$M:$M, "Cancelled") -> 2 | U76: =T76/S76 -> 0.11764706 | V76: =COUNTIFS(Orders!$Z:$Z, $A76, Orders!$M:$M, "pending") -> 0 | W76: =S76-T76 -> 15 | X76: =W76/S76 -> 0.88235294 | Y76: =COUNTIFS(Orders!$Z:$Z, $A76, Orders!$M:$M, "Delivered") -> 11 | Z76: =COUNTIFS(Orders!$Z:$Z, $A76, Orders!$M:$M, "Return Received") -> 4 | AA76: =W76-Y76-Z76-V76 -> 0 | AB76: =COUNTIFS(Orders!$Z:$Z, $A76, Orders!$M:$M, "Returned") + COUNTIFS(Orders!$Z:$Z, $A76, Orders!$M:$M, "Returned to Shipper") -> 0 | AC76: =COUNTIFS(Orders!$Z:$Z, $A76, Orders!$I:$I, "", Orders!$M:$M, "<>Cancelled") -> 0 | AD76: =SUMIFS(Orders!$U:$U, Orders!$Z:$Z, $A76, Orders!$M:$M, "Delivered") -> 32937 | AE76: =C76-AD76 -> 0 | AF76: =IFERROR(__xludf.DUMMYFUNCTION("IFERROR(TEXTJOIN("", "", TRUE, FILTER(Orders!$B$2:$B$2517, (TEXT(Orders!$D$2:$D$2517,""d-mmm"")=TEXT($A76,""d-mmm"")) * (ABS(Orders!$H$2:$H$2517 - Orders!$U$2:$U$2517) >= 1) * (Orders!$M$2:$M$2517=""Delivered""))), ""All Balanced"")"),"All Balanced") -> All Balanced | AG76: =IFERROR(__xludf.DUMMYFUNCTION("IFERROR(TEXTJOIN("", "", TRUE, FILTER(Orders!$I$2:$I$3000, (Orders!$M$2:$M$3000=""Delivered"") * (Orders!$N$2:$N$3000<>""Paid"") * (Orders!$Z$2:$Z$3000=$A76))), """")"),"") | AH76: =COUNTIFS(Orders!$M:$M, "Delivered", Orders!$N:$N, "<>Paid", Orders!$Z:$Z, $A76) -> 0
A77: 46053 | B77: =C77/Y77 -> 3111.4 | C77: =SUMIFS(Orders!$H:$H, Orders!$Z:$Z, $A77, Orders!$M:$M, "Delivered") -> 62228 | D77: =SUMIFS(Orders!$Q:$Q, Orders!$Z:$Z, $A77, Orders!$M:$M, "Delivered") -> 22345 | E77: =D77/C77 -> 0.35908273 | F77: =C77-(C77*4/100) -> 59738.88 | G77: =C77-F77 -> 2489.12 | H77: =C77-D77 -> 39883 | I77: =IFERROR(J77/C77, 0)*100 -> 25.049849 | J77: 15588.02 | L77: =(200*W77)+C77*4% -> 8089.12 | M77: =SUMIFS(Orders!$W:$W, Orders!$Z:$Z, $A77) -> 7939 | N77: =H77-J77-K77-M77 -> 16355.98 | O77: =Y77/W77*100 -> 71.428571 | P77: 4.8147863 | Q77: =J77/S77 -> 537.51793 | R77: =J77/W77 -> 556.715 | S77: =COUNTIFS(Orders!$Z:$Z, $A77) -> 29 | T77: =COUNTIFS(Orders!$Z:$Z, $A77, Orders!$M:$M, "Cancelled") -> 1 | U77: =T77/S77 -> 0.034482759 | V77: =COUNTIFS(Orders!$Z:$Z, $A77, Orders!$M:$M, "pending") -> 0 | W77: =S77-T77 -> 28 | X77: =W77/S77 -> 0.96551724 | Y77: =COUNTIFS(Orders!$Z:$Z, $A77, Orders!$M:$M, "Delivered") -> 20 | Z77: =COUNTIFS(Orders!$Z:$Z, $A77, Orders!$M:$M, "Return Received") -> 8 | AA77: =W77-Y77-Z77-V77 -> 0 | AB77: =COUNTIFS(Orders!$Z:$Z, $A77, Orders!$M:$M, "Returned") + COUNTIFS(Orders!$Z:$Z, $A77, Orders!$M:$M, "Returned to Shipper") -> 0 | AC77: =COUNTIFS(Orders!$Z:$Z, $A77, Orders!$I:$I, "", Orders!$M:$M, "<>Cancelled") -> 0 | AD77: =SUMIFS(Orders!$U:$U, Orders!$Z:$Z, $A77, Orders!$M:$M, "Delivered") -> 62228 | AE77: =C77-AD77 -> 0 | AF77: =IFERROR(__xludf.DUMMYFUNCTION("IFERROR(TEXTJOIN("", "", TRUE, FILTER(Orders!$B$2:$B$2517, (TEXT(Orders!$D$2:$D$2517,""d-mmm"")=TEXT($A77,""d-mmm"")) * (ABS(Orders!$H$2:$H$2517 - Orders!$U$2:$U$2517) >= 1) * (Orders!$M$2:$M$2517=""Delivered""))), ""All Balanced"")"),"All Balanced") -> All Balanced | AG77: =IFERROR(__xludf.DUMMYFUNCTION("IFERROR(TEXTJOIN("", "", TRUE, FILTER(Orders!$I$2:$I$3000, (Orders!$M$2:$M$3000=""Delivered"") * (Orders!$N$2:$N$3000<>""Paid"") * (Orders!$Z$2:$Z$3000=$A77))), """")"),"") | AH77: =COUNTIFS(Orders!$M:$M, "Delivered", Orders!$N:$N, "<>Paid", Orders!$Z:$Z, $A77) -> 0
A79: Performance | C79: Del% | D79: CAL% | F79: mar% | G79: profit
A80: 45667 | C80: =AVERAGE(O47:O56) -> 73.178214 | D80: =AVERAGE(AJ5:AJ14) -> #DIV/0! | F80: =AVERAGE(I47:I56) -> 42.136202 | G80: =SUM(N47:N56) -> 100883.39
A81: 45981 | C81: =AVERAGE(O57:O66) -> 62.05337 | D81: =AVERAGE(AJ15:AJ24) -> #DIV/0! | F81: =AVERAGE(I57:I66) -> 39.789439 | G81: =sum(N57:N66) -> 70415.55
A82: 21-31 | C82: =AVERAGE(O67:O77) -> 68.600106 | D82: =AVERAGE(AJ25:AJ35) -> #DIV/0! | F82: =AVERAGE(I67:I77) -> 36.281653 | G82: =sum(N67:N77) -> 109643.41
C83: =AVERAGE(AE68:AE78) -> 285 | D83: =AVERAGE(AF68:AF78) -> #DIV/0! | F83: =sum(N68:N78) -> 95179.872 | G83: =sum(G80:G82) -> 280942.35 | H83: -12800 | I83: =sum(G83:H83) -> 268142.35
C86: IN | D86: IN | F86: OUT | G86: OUT | H86: OUT | I86: OUT | J86: IN | K86: OUT | M86: OUT | N86: OUT | O86: OUT | P86: IN | Q86: OUT | R86: OUT | S86: IN | T86: OUT | W86: IN
A87: Averages | G87: =AVERAGE(G90:G120) -> 2121.3416 | J87: =AVERAGE(J90:J120) -> 17374.678 | N87: =AVERAGE(N90:N120) -> 12498.252 | O87: =AVERAGE(O90:O120) -> 79.03513 | S87: =AVERAGE(S90:S120) -> 24.928571 | T87: =AVERAGE(T90:T120) -> 3.8928571 | W87: =AVERAGE(W90:W120) -> 21.035714
A88: Totals | B88: =AVERAGE(B90:B117) -> 3217.6847 | C88: =sum(C90:C120) -> 1484939.1 | D88: =SUM(D90:D120) -> 480630 | E88: =AVERAGE(E90:E117) -> 0.32649447 | F88: =SUM(F90:F120) -> 1425541.5 | G88: =SUM(G90:G120) -> 59397.564 | H88: =sum(F90:F120) -> 1425541.5 | I88: =AVERAGE(I90:I117) -> 34.901375 | J88: =sum(J90:J120) -> 486490.99 | K88: =sum(K90:K120) -> 0 | L88: =SUM(L90:L120) -> 177197.56 | M88: =sum(M90:M120) -> 167867.05 | N88: =sum(N90:N120) -> 349951.06 | O88: =AVERAGE(O90:O120) -> 79.03513 | P88: =AVERAGE(P90:P120) -> 4.837616 | Q88: =AVERAGE(Q90:Q120) -> 733.69433 | R88: =AVERAGE(R90:R120) -> 869.22652 | S88: =sum(S90:S120) -> 698 | T88: =sum(T90:T120) -> 109 | U88: =AVERAGE(U90:U117) -> 0.15165048 | V88: =sum(V90:V120) -> 0 | W88: =sum(W90:W120) -> 589 | X88: =average(X90:X117) -> 0.84834952 | Y88: =sum(Y90:Y120) -> 464 | Z88: =sum(Z90:Z120) -> 125 | AA88: =sum(AA90:AA120) -> 0 | AB88: =sum(AB90:AB120) -> 0 | AD88: =SUM(AD90:AD120) -> 1463043.6 | AE88: =sum(AE90:AE120) -> 21895.5
A89: Dates | B89: AOV | C89: Delivered sale | D89: CGS | E89: CGS % | F89: -4% tax | G89: TAX Paid | H89: Gross Profit | I89: % | J89: Marketing 10% tax | K89: Tiktok marketing | L89: est courier (200 x total parcel dispatch | M89: Actual exp + tax | N89: PNL (Day vise) | O89: Del% | P89: ROAS(meta) | Q89: CPA AVG (mar/landed orders) | R89: Net CPA AVG(after cancelations) | S89: Landed orders | T89: Cancelations | U89: cal % | V89: Pending | W89: Total Dipatched | Y89: Delivered | Z89: Restocked | AA89: Intransit | AB89: Fake Return | AC89: without tracking id | AD89: payment paid | AE89: Diff correction | AF89: Refrance Number that have diff | AG89: Unsorted Tracking IDs | AH89: Delivered (payment pending)
A90: 46054 | B90: =C90/Y90 -> 3102.125 | C90: =SUMIFS(Orders!$H:$H, Orders!$Z:$Z, $A90, Orders!$M:$M, "Delivered") -> 49634 | D90: =SUMIFS(Orders!$Q:$Q, Orders!$Z:$Z, $A90, Orders!$M:$M, "Delivered") -> 19440 | E90: =D90/C90 -> 0.391667 | F90: =C90-(C90*4/100) -> 47648.64 | G90: =C90-F90 -> 1985.36 | H90: =C90-D90 -> 30194 | I90: =IFERROR(J90/C90, 0)*100 -> 38.817847 | J90: 19266.85 | L90: =(200*W90)+C90*4% -> 6785.36 | M90: =SUMIFS(Orders!$W:$W, Orders!$Z:$Z, $A90) -> 6554.5376 | N90: =H90-J90-K90-M90 -> 4372.6124 | O90: =Y90/W90*100 -> 66.666667 | P90: 4.380508 | Q90: =J90/S90 -> 770.674 | R90: =J90/W90 -> 802.78542 | S90: =COUNTIFS(Orders!$Z:$Z, $A90) -> 25 | T90: =COUNTIFS(Orders!$Z:$Z, $A90, Orders!$M:$M, "Cancelled") -> 1 | U90: =T90/S90 -> 0.04 | V90: =COUNTIFS(Orders!$Z:$Z, $A90, Orders!$M:$M, "pending") -> 0 | W90: =S90-T90 -> 24 | X90: =W90/S90 -> 0.96 | Y90: =COUNTIFS(Orders!$Z:$Z, $A90, Orders!$M:$M, "Delivered") -> 16 | Z90: =COUNTIFS(Orders!$Z:$Z, $A90, Orders!$M:$M, "Return Received") -> 8 | AA90: =W90-Y90-Z90-V90 -> 0 | AB90: =COUNTIFS(Orders!$Z:$Z, $A90, Orders!$M:$M, "Returned") + COUNTIFS(Orders!$Z:$Z, $A90, Orders!$M:$M, "Returned to Shipper") -> 0 | AC90: =COUNTIFS(Orders!$Z:$Z, $A90, Orders!$I:$I, "", Orders!$M:$M, "<>Cancelled") -> 0 | AD90: =SUMIFS(Orders!$U:$U, Orders!$Z:$Z, $A90, Orders!$M:$M, "Delivered") -> 49634 | AE90: =C90-AD90 -> 0 | AF90: =IFERROR(__xludf.DUMMYFUNCTION("IFERROR(TEXTJOIN("", "", TRUE, FILTER(Orders!$B$2:$B$2517, (TEXT(Orders!$D$2:$D$2517,""d-mmm"")=TEXT($A90,""d-mmm"")) * (ABS(Orders!$H$2:$H$2517 - Orders!$U$2:$U$2517) >= 1) * (Orders!$M$2:$M$2517=""Delivered""))), ""All Balanced"")"),"All Balanced") -> All Balanced | AG90: =IFERROR(__xludf.DUMMYFUNCTION("IFERROR(TEXTJOIN("", "", TRUE, FILTER(Orders!$I$2:$I$2517, (Orders!$M$2:$M$2517=""Delivered"") * (Orders!$N$2:$N$2517<>""Paid"") * (Orders!$Z$2:$Z$2517=$A90))), """")"),"") | AH90: =COUNTIFS(Orders!$M:$M, "Delivered", Orders!$N:$N, "<>Paid", Orders!$Z:$Z, $A90) -> 0
A91: 46055 | B91: =C91/Y91 -> 3847.5625 | C91: =SUMIFS(Orders!$H:$H, Orders!$Z:$Z, $A91, Orders!$M:$M, "Delivered") -> 61561 | D91: =SUMIFS(Orders!$Q:$Q, Orders!$Z:$Z, $A91, Orders!$M:$M, "Delivered") -> 22165 | E91: =D91/C91 -> 0.36004938 | F91: =C91-(C91*4/100) -> 59098.56 | G91: =C91-F91 -> 2462.44 | H91: =C91-D91 -> 39396 | I91: =IFERROR(J91/C91, 0)*100 -> 27.885934 | J91: 17166.86 | L91: =(200*W91)+C91*4% -> 7062.44 | M91: =SUMIFS(Orders!$W:$W, Orders!$Z:$Z, $A91) -> 6876.4776 | N91: =H91-J91-K91-M91 -> 15352.662 | O91: =Y91/W91*100 -> 69.565217 | P91: 6.4197398 | Q91: =J91/S91 -> 591.96069 | R91: =J91/W91 -> 746.38522 | S91: =COUNTIFS(Orders!$Z:$Z, $A91) -> 29 | T91: =COUNTIFS(Orders!$Z:$Z, $A91, Orders!$M:$M, "Cancelled") -> 6 | U91: =T91/S91 -> 0.20689655 | V91: =COUNTIFS(Orders!$Z:$Z, $A91, Orders!$M:$M, "pending") -> 0 | W91: =S91-T91 -> 23 | X91: =W91/S91 -> 0.79310345 | Y91: =COUNTIFS(Orders!$Z:$Z, $A91, Orders!$M:$M, "Delivered") -> 16 | Z91: =COUNTIFS(Orders!$Z:$Z, $A91, Orders!$M:$M, "Return Received") -> 7 | AA91: =W91-Y91-Z91-V91 -> 0 | AB91: =COUNTIFS(Orders!$Z:$Z, $A91, Orders!$M:$M, "Returned") + COUNTIFS(Orders!$Z:$Z, $A91, Orders!$M:$M, "Returned to Shipper") -> 0 | AC91: =COUNTIFS(Orders!$Z:$Z, $A91, Orders!$I:$I, "", Orders!$M:$M, "<>Cancelled") -> 0 | AD91: =SUMIFS(Orders!$U:$U, Orders!$Z:$Z, $A91, Orders!$M:$M, "Delivered") -> 53110 | AE91: =C91-AD91 -> 8451 | AF91: =IFERROR(__xludf.DUMMYFUNCTION("IFERROR(TEXTJOIN("", "", TRUE, FILTER(Orders!$B$2:$B$2517, (TEXT(Orders!$D$2:$D$2517,""d-mmm"")=TEXT($A91,""d-mmm"")) * (ABS(Orders!$H$2:$H$2517 - Orders!$U$2:$U$2517) >= 1) * (Orders!$M$2:$M$2517=""Delivered""))), ""All Balanced"")"),"TR28888") -> TR28888 | AG91: =IFERROR(__xludf.DUMMYFUNCTION("IFERROR(TEXTJOIN("", "", TRUE, FILTER(Orders!$I$2:$I$3000, (Orders!$M$2:$M$3000=""Delivered"") * (Orders!$N$2:$N$3000<>""Paid"") * (Orders!$Z$2:$Z$3000=$A91))), """")"),"") | AH91: =COUNTIFS(Orders!$M:$M, "Delivered", Orders!$N:$N, "<>Paid", Orders!$Z:$Z, $A91) -> 0
A92: 46056 | B92: =C92/Y92 -> 3639.3333 | C92: =SUMIFS(Orders!$H:$H, Orders!$Z:$Z, $A92, Orders!$M:$M, "Delivered") -> 54590 | D92: =SUMIFS(Orders!$Q:$Q, Orders!$Z:$Z, $A92, Orders!$M:$M, "Delivered") -> 19600 | E92: =D92/C92 -> 0.35904012 | F92: =C92-(C92*4/100) -> 52406.4 | G92: =C92-F92 -> 2183.6 | H92: =C92-D92 -> 34990 | I92: =IFERROR(J92/C92, 0)*100 -> 32.475527 | J92: 17728.39 | L92: =(200*W92)+C92*4% -> 5383.6 | M92: =SUMIFS(Orders!$W:$W, Orders!$Z:$Z, $A92) -> 5285.0752 | N92: =H92-J92-K92-M92 -> 11976.535 | O92: =Y92/W92*100 -> 93.75 | P92: 4.0564085 | Q92: =J92/S92 -> 886.4195 | R92: =J92/W92 -> 1108.0244 | S92: =COUNTIFS(Orders!$Z:$Z, $A92) -> 20 | T92: =COUNTIFS(Orders!$Z:$Z, $A92, Orders!$M:$M, "Cancelled") -> 4 | U92: =T92/S92 -> 0.2 | V92: =COUNTIFS(Orders!$Z:$Z, $A92, Orders!$M:$M, "pending") -> 0 | W92: =S92-T92 -> 16 | X92: =W92/S92 -> 0.8 | Y92: =COUNTIFS(Orders!$Z:$Z, $A92, Orders!$M:$M, "Delivered") -> 15 | Z92: =COUNTIFS(Orders!$Z:$Z, $A92, Orders!$M:$M, "Return Received") -> 1 | AA92: =W92-Y92-Z92-V92 -> 0 | AB92: =COUNTIFS(Orders!$Z:$Z, $A92, Orders!$M:$M, "Returned") + COUNTIFS(Orders!$Z:$Z, $A92, Orders!$M:$M, "Returned to Shipper") -> 0 | AC92: =COUNTIFS(Orders!$Z:$Z, $A92, Orders!$I:$I, "", Orders!$M:$M, "<>Cancelled") -> 0 | AD92: =SUMIFS(Orders!$U:$U, Orders!$Z:$Z, $A92, Orders!$M:$M, "Delivered") -> 54590 | AE92: =C92-AD92 -> 0 | AF92: =IFERROR(__xludf.DUMMYFUNCTION("IFERROR(TEXTJOIN("", "", TRUE, FILTER(Orders!$B$2:$B$2517, (TEXT(Orders!$D$2:$D$2517,""d-mmm"")=TEXT($A92,""d-mmm"")) * (ABS(Orders!$H$2:$H$2517 - Orders!$U$2:$U$2517) >= 1) * (Orders!$M$2:$M$2517=""Delivered""))), ""All Balanced"")"),"All Balanced") -> All Balanced | AG92: =IFERROR(__xludf.DUMMYFUNCTION("IFERROR(TEXTJOIN("", "", TRUE, FILTER(Orders!$I$2:$I$3000, (Orders!$M$2:$M$3000=""Delivered"") * (Orders!$N$2:$N$3000<>""Paid"") * (Orders!$Z$2:$Z$3000=$A92))), """")"),"") | AH92: =COUNTIFS(Orders!$M:$M, "Delivered", Orders!$N:$N, "<>Paid", Orders!$Z:$Z, $A92) -> 0
A93: 46057 | B93: =C93/Y93 -> 3899 | C93: =SUMIFS(Orders!$H:$H, Orders!$Z:$Z, $A93, Orders!$M:$M, "Delivered") -> 27293 | D93: =SUMIFS(Orders!$Q:$Q, Orders!$Z:$Z, $A93, Orders!$M:$M, "Delivered") -> 9525 | E93: =D93/C93 -> 0.34899058 | F93: =C93-(C93*4/100) -> 26201.28 | G93: =C93-F93 -> 1091.72 | H93: =C93-D93 -> 17768 | I93: =IFERROR(J93/C93, 0)*100 -> 56.342359 | J93: 15377.52 | L93: =(200*W93)+C93*4% -> 3091.72 | M93: =SUMIFS(Orders!$W:$W, Orders!$Z:$Z, $A93) -> 3187.19 | N93: =H93-J93-K93-M93 -> -796.71 | O93: =Y93/W93*100 -> 70 | P93: 3.2895885 | Q93: =J93/S93 -> 1025.168 | R93: =J93/W93 -> 1537.752 | S93: =COUNTIFS(Orders!$Z:$Z, $A93) -> 15 | T93: =COUNTIFS(Orders!$Z:$Z, $A93, Orders!$M:$M, "Cancelled") -> 5 | U93: =T93/S93 -> 0.33333333 | V93: =COUNTIFS(Orders!$Z:$Z, $A93, Orders!$M:$M, "pending") -> 0 | W93: =S93-T93 -> 10 | X93: =W93/S93 -> 0.66666667 | Y93: =COUNTIFS(Orders!$Z:$Z, $A93, Orders!$M:$M, "Delivered") -> 7 | Z93: =COUNTIFS(Orders!$Z:$Z, $A93, Orders!$M:$M, "Return Received") -> 3 | AA93: =W93-Y93-Z93-V93 -> 0 | AB93: =COUNTIFS(Orders!$Z:$Z, $A93, Orders!$M:$M, "Returned") + COUNTIFS(Orders!$Z:$Z, $A93, Orders!$M:$M, "Returned to Shipper") -> 0 | AC93: =COUNTIFS(Orders!$Z:$Z, $A93, Orders!$I:$I, "", Orders!$M:$M, "<>Cancelled") -> 0 | AD93: =SUMIFS(Orders!$U:$U, Orders!$Z:$Z, $A93, Orders!$M:$M, "Delivered") -> 27293 | AE93: =C93-AD93 -> 0 | AF93: =IFERROR(__xludf.DUMMYFUNCTION("IFERROR(TEXTJOIN("", "", TRUE, FILTER(Orders!$B$2:$B$2517, (TEXT(Orders!$D$2:$D$2517,""d-mmm"")=TEXT($A93,""d-mmm"")) * (ABS(Orders!$H$2:$H$2517 - Orders!$U$2:$U$2517) >= 1) * (Orders!$M$2:$M$2517=""Delivered""))), ""All Balanced"")"),"All Balanced") -> All Balanced | AG93: =IFERROR(__xludf.DUMMYFUNCTION("IFERROR(TEXTJOIN("", "", TRUE, FILTER(Orders!$I$2:$I$3000, (Orders!$M$2:$M$3000=""Delivered"") * (Orders!$N$2:$N$3000<>""Paid"") * (Orders!$Z$2:$Z$3000=$A93))), """")"),"") | AH93: =COUNTIFS(Orders!$M:$M, "Delivered", Orders!$N:$N, "<>Paid", Orders!$Z:$Z, $A93) -> 0
A94: 46058 | B94: =C94/Y94 -> 2888.2857 | C94: =SUMIFS(Orders!$H:$H, Orders!$Z:$Z, $A94, Orders!$M:$M, "Delivered") -> 40436 | D94: =SUMIFS(Orders!$Q:$Q, Orders!$Z:$Z, $A94, Orders!$M:$M, "Delivered") -> 16170 | E94: =D94/C94 -> 0.39989119 | F94: =C94-(C94*4/100) -> 38818.56 | G94: =C94-F94 -> 1617.44 | H94: =C94-D94 -> 24266 | I94: =IFERROR(J94/C94, 0)*100 -> 39.651004 | J94: 16033.28 | L94: =(200*W94)+C94*4% -> 5217.44 | M94: =SUMIFS(Orders!$W:$W, Orders!$Z:$Z, $A94) -> 5290.5376 | N94: =H94-J94-K94-M94 -> 2942.1824 | O94: =Y94/W94*100 -> 77.777778 | P94: 4.207548 | Q94: =J94/S94 -> 728.78545 | R94: =J94/W94 -> 890.73778 | S94: =COUNTIFS(Orders!$Z:$Z, $A94) -> 22 | T94: =COUNTIFS(Orders!$Z:$Z, $A94, Orders!$M:$M, "Cancelled") -> 4 | U94: =T94/S94 -> 0.18181818 | V94: =COUNTIFS(Orders!$Z:$Z, $A94, Orders!$M:$M, "pending") -> 0 | W94: =S94-T94 -> 18 | X94: =W94/S94 -> 0.81818182 | Y94: =COUNTIFS(Orders!$Z:$Z, $A94, Orders!$M:$M, "Delivered") -> 14 | Z94: =COUNTIFS(Orders!$Z:$Z, $A94, Orders!$M:$M, "Return Received") -> 4 | AA94: =W94-Y94-Z94-V94 -> 0 | AB94: =COUNTIFS(Orders!$Z:$Z, $A94, Orders!$M:$M, "Returned") + COUNTIFS(Orders!$Z:$Z, $A94, Orders!$M:$M, "Returned to Shipper") -> 0 | AC94: =COUNTIFS(Orders!$Z:$Z, $A94, Orders!$I:$I, "", Orders!$M:$M, "<>Cancelled") -> 0 | AD94: =SUMIFS(Orders!$U:$U, Orders!$Z:$Z, $A94, Orders!$M:$M, "Delivered") -> 40436 | AE94: =C94-AD94 -> 0 | AF94: =IFERROR(__xludf.DUMMYFUNCTION("IFERROR(TEXTJOIN("", "", TRUE, FILTER(Orders!$B$2:$B$2517, (TEXT(Orders!$D$2:$D$2517,""d-mmm"")=TEXT($A94,""d-mmm"")) * (ABS(Orders!$H$2:$H$2517 - Orders!$U$2:$U$2517) >= 1) * (Orders!$M$2:$M$2517=""Delivered""))), ""All Balanced"")"),"All Balanced") -> All Balanced | AG94: =IFERROR(__xludf.DUMMYFUNCTION("IFERROR(TEXTJOIN("", "", TRUE, FILTER(Orders!$I$2:$I$3000, (Orders!$M$2:$M$3000=""Delivered"") * (Orders!$N$2:$N$3000<>""Paid"") * (Orders!$Z$2:$Z$3000=$A94))), """")"),"") | AH94: =COUNTIFS(Orders!$M:$M, "Delivered", Orders!$N:$N, "<>Paid", Orders!$Z:$Z, $A94) -> 0
A95: 46059 | B95: =C95/Y95 -> 3219.0833 | C95: =SUMIFS(Orders!$H:$H, Orders!$Z:$Z, $A95, Orders!$M:$M, "Delivered") -> 38629 | D95: =SUMIFS(Orders!$Q:$Q, Orders!$Z:$Z, $A95, Orders!$M:$M, "Delivered") -> 12810 | E95: =D95/C95 -> 0.33161614 | F95: =C95-(C95*4/100) -> 37083.84 | G95: =C95-F95 -> 1545.16 | H95: =C95-D95 -> 25819 | I95: =IFERROR(J95/C95, 0)*100 -> 33.413058 | J95: 12907.13 | L95: =(200*W95)+C95*4% -> 4145.16 | M95: =SUMIFS(Orders!$W:$W, Orders!$Z:$Z, $A95) -> 4475.94 | N95: =H95-J95-K95-M95 -> 8435.93 | O95: =Y95/W95*100 -> 92.307692 | P95: 4.0078406 | Q95: =J95/S95 -> 921.93786 | R95: =J95/W95 -> 992.85615 | S95: =COUNTIFS(Orders!$Z:$Z, $A95) -> 14 | T95: =COUNTIFS(Orders!$Z:$Z, $A95, Orders!$M:$M, "Cancelled") -> 1 | U95: =T95/S95 -> 0.071428571 | V95: =COUNTIFS(Orders!$Z:$Z, $A95, Orders!$M:$M, "pending") -> 0 | W95: =S95-T95 -> 13 | X95: =W95/S95 -> 0.92857143 | Y95: =COUNTIFS(Orders!$Z:$Z, $A95, Orders!$M:$M, "Delivered") -> 12 | Z95: =COUNTIFS(Orders!$Z:$Z, $A95, Orders!$M:$M, "Return Received") -> 1 | AA95: =W95-Y95-Z95-V95 -> 0 | AB95: =COUNTIFS(Orders!$Z:$Z, $A95, Orders!$M:$M, "Returned") + COUNTIFS(Orders!$Z:$Z, $A95, Orders!$M:$M, "Returned to Shipper") -> 0 | AC95: =COUNTIFS(Orders!$Z:$Z, $A95, Orders!$I:$I, "", Orders!$M:$M, "<>Cancelled") -> 0 | AD95: =SUMIFS(Orders!$U:$U, Orders!$Z:$Z, $A95, Orders!$M:$M, "Delivered") -> 38629 | AE95: =C95-AD95 -> 0 | AF95: =IFERROR(__xludf.DUMMYFUNCTION("IFERROR(TEXTJOIN("", "", TRUE, FILTER(Orders!$B$2:$B$2517, (TEXT(Orders!$D$2:$D$2517,""d-mmm"")=TEXT($A95,""d-mmm"")) * (ABS(Orders!$H$2:$H$2517 - Orders!$U$2:$U$2517) >= 1) * (Orders!$M$2:$M$2517=""Delivered""))), ""All Balanced"")"),"All Balanced") -> All Balanced | AG95: =IFERROR(__xludf.DUMMYFUNCTION("IFERROR(TEXTJOIN("", "", TRUE, FILTER(Orders!$I$2:$I$3000, (Orders!$M$2:$M$3000=""Delivered"") * (Orders!$N$2:$N$3000<>""Paid"") * (Orders!$Z$2:$Z$3000=$A95))), """")"),"") | AH95: =COUNTIFS(Orders!$M:$M, "Delivered", Orders!$N:$N, "<>Paid", Orders!$Z:$Z, $A95) -> 0
A96: 46060 | B96: =C96/Y96 -> 3250.6667 | C96: =SUMIFS(Orders!$H:$H, Orders!$Z:$Z, $A96, Orders!$M:$M, "Delivered") -> 48760 | D96: =SUMIFS(Orders!$Q:$Q, Orders!$Z:$Z, $A96, Orders!$M:$M, "Delivered") -> 18070 | E96: =D96/C96 -> 0.37059065 | F96: =C96-(C96*4/100) -> 46809.6 | G96: =C96-F96 -> 1950.4 | H96: =C96-D96 -> 30690 | I96: =IFERROR(J96/C96, 0)*100 -> 28.637223 | J96: 13963.51 | L96: =(200*W96)+C96*4% -> 5350.4 | M96: =SUMIFS(Orders!$W:$W, Orders!$Z:$Z, $A96) -> 4678 | N96: =H96-J96-K96-M96 -> 12048.49 | O96: =Y96/W96*100 -> 88.235294 | P96: 4.8747843 | Q96: =J96/S96 -> 775.75056 | R96: =J96/W96 -> 821.38294 | S96: =COUNTIFS(Orders!$Z:$Z, $A96) -> 18 | T96: =COUNTIFS(Orders!$Z:$Z, $A96, Orders!$M:$M, "Cancelled") -> 1 | U96: =T96/S96 -> 0.055555556 | V96: =COUNTIFS(Orders!$Z:$Z, $A96, Orders!$M:$M, "pending") -> 0 | W96: =S96-T96 -> 17 | X96: =W96/S96 -> 0.94444444 | Y96: =COUNTIFS(Orders!$Z:$Z, $A96, Orders!$M:$M, "Delivered") -> 15 | Z96: =COUNTIFS(Orders!$Z:$Z, $A96, Orders!$M:$M, "Return Received") -> 2 | AA96: =W96-Y96-Z96-V96 -> 0 | AB96: =COUNTIFS(Orders!$Z:$Z, $A96, Orders!$M:$M, "Returned") + COUNTIFS(Orders!$Z:$Z, $A96, Orders!$M:$M, "Returned to Shipper") -> 0 | AC96: =COUNTIFS(Orders!$Z:$Z, $A96, Orders!$I:$I, "", Orders!$M:$M, "<>Cancelled") -> 0 | AD96: =SUMIFS(Orders!$U:$U, Orders!$Z:$Z, $A96, Orders!$M:$M, "Delivered") -> 48760 | AE96: =C96-AD96 -> 0 | AF96: =IFERROR(__xludf.DUMMYFUNCTION("IFERROR(TEXTJOIN("", "", TRUE, FILTER(Orders!$B$2:$B$2517, (TEXT(Orders!$D$2:$D$2517,""d-mmm"")=TEXT($A96,""d-mmm"")) * (ABS(Orders!$H$2:$H$2517 - Orders!$U$2:$U$2517) >= 1) * (Orders!$M$2:$M$2517=""Delivered""))), ""All Balanced"")"),"All Balanced") -> All Balanced | AG96: =IFERROR(__xludf.DUMMYFUNCTION("IFERROR(TEXTJOIN("", "", TRUE, FILTER(Orders!$I$2:$I$3000, (Orders!$M$2:$M$3000=""Delivered"") * (Orders!$N$2:$N$3000<>""Paid"") * (Orders!$Z$2:$Z$3000=$A96))), """")"),"") | AH96: =COUNTIFS(Orders!$M:$M, "Delivered", Orders!$N:$N, "<>Paid", Orders!$Z:$Z, $A96) -> 0
A97: 46061 | B97: =C97/Y97 -> 3259 | C97: =SUMIFS(Orders!$H:$H, Orders!$Z:$Z, $A97, Orders!$M:$M, "Delivered") -> 48885 | D97: =SUMIFS(Orders!$Q:$Q, Orders!$Z:$Z, $A97, Orders!$M:$M, "Delivered") -> 15870 | E97: =D97/C97 -> 0.32463946 | F97: =C97-(C97*4/100) -> 46929.6 | G97: =C97-F97 -> 1955.4 | H97: =C97-D97 -> 33015 | I97: =IFERROR(J97/C97, 0)*100 -> 31.994886 | J97: 15640.7 | L97: =(200*W97)+C97*4% -> 5555.4 | M97: =SUMIFS(Orders!$W:$W, Orders!$Z:$Z, $A97) -> 5063 | N97: =H97-J97-K97-M97 -> 12311.3 | O97: =Y97/W97*100 -> 83.333333 | P97: 5.1531702 | Q97: =J97/S97 -> 601.56538 | R97: =J97/W97 -> 868.92778 | S97: =COUNTIFS(Orders!$Z:$Z, $A97) -> 26 | T97: =COUNTIFS(Orders!$Z:$Z, $A97, Orders!$M:$M, "Cancelled") -> 8 | U97: =T97/S97 -> 0.30769231 | V97: =COUNTIFS(Orders!$Z:$Z, $A97, Orders!$M:$M, "pending") -> 0 | W97: =S97-T97 -> 18 | X97: =W97/S97 -> 0.69230769 | Y97: =COUNTIFS(Orders!$Z:$Z, $A97, Orders!$M:$M, "Delivered") -> 15 | Z97: =COUNTIFS(Orders!$Z:$Z, $A97, Orders!$M:$M, "Return Received") -> 3 | AA97: =W97-Y97-Z97-V97 -> 0 | AB97: =COUNTIFS(Orders!$Z:$Z, $A97, Orders!$M:$M, "Returned") + COUNTIFS(Orders!$Z:$Z, $A97, Orders!$M:$M, "Returned to Shipper") -> 0 | AC97: =COUNTIFS(Orders!$Z:$Z, $A97, Orders!$I:$I, "", Orders!$M:$M, "<>Cancelled") -> 0 | AD97: =SUMIFS(Orders!$U:$U, Orders!$Z:$Z, $A97, Orders!$M:$M, "Delivered") -> 48885 | AE97: =C97-AD97 -> 0 | AF97: =IFERROR(__xludf.DUMMYFUNCTION("IFERROR(TEXTJOIN("", "", TRUE, FILTER(Orders!$B$2:$B$2517, (TEXT(Orders!$D$2:$D$2517,""d-mmm"")=TEXT($A97,""d-mmm"")) * (ABS(Orders!$H$2:$H$2517 - Orders!$U$2:$U$2517) >= 1) * (Orders!$M$2:$M$2517=""Delivered""))), ""All Balanced"")"),"All Balanced") -> All Balanced | AG97: =IFERROR(__xludf.DUMMYFUNCTION("IFERROR(TEXTJOIN("", "", TRUE, FILTER(Orders!$I$2:$I$3000, (Orders!$M$2:$M$3000=""Delivered"") * (Orders!$N$2:$N$3000<>""Paid"") * (Orders!$Z$2:$Z$3000=$A97))), """")"),"") | AH97: =COUNTIFS(Orders!$M:$M, "Delivered", Orders!$N:$N, "<>Paid", Orders!$Z:$Z, $A97) -> 0
A98: 46062 | B98: =C98/Y98 -> 2807.0714 | C98: =SUMIFS(Orders!$H:$H, Orders!$Z:$Z, $A98, Orders!$M:$M, "Delivered") -> 39299 | D98: =SUMIFS(Orders!$Q:$Q, Orders!$Z:$Z, $A98, Orders!$M:$M, "Delivered") -> 14525 | E98: =D98/C98 -> 0.36960228 | F98: =C98-(C98*4/100) -> 37727.04 | G98: =C98-F98 -> 1571.96 | H98: =C98-D98 -> 24774 | I98: =IFERROR(J98/C98, 0)*100 -> 37.587292 | J98: 14771.43 | L98: =(200*W98)+C98*4% -> 5571.96 | M98: =SUMIFS(Orders!$W:$W, Orders!$Z:$Z, $A98) -> 5289.6296 | N98: =H98-J98-K98-M98 -> 4712.9404 | O98: =Y98/W98*100 -> 70 | P98: 4.6901494 | Q98: =J98/S98 -> 615.47625 | R98: =J98/W98 -> 738.5715 | S98: =COUNTIFS(Orders!$Z:$Z, $A98) -> 24 | T98: =COUNTIFS(Orders!$Z:$Z, $A98, Orders!$M:$M, "Cancelled") -> 4 | U98: =T98/S98 -> 0.16666667 | V98: =COUNTIFS(Orders!$Z:$Z, $A98, Orders!$M:$M, "pending") -> 0 | W98: =S98-T98 -> 20 | X98: =W98/S98 -> 0.83333333 | Y98: =COUNTIFS(Orders!$Z:$Z, $A98, Orders!$M:$M, "Delivered") -> 14 | Z98: =COUNTIFS(Orders!$Z:$Z, $A98, Orders!$M:$M, "Return Received") -> 6 | AA98: =W98-Y98-Z98-V98 -> 0 | AB98: =COUNTIFS(Orders!$Z:$Z, $A98, Orders!$M:$M, "Returned") + COUNTIFS(Orders!$Z:$Z, $A98, Orders!$M:$M, "Returned to Shipper") -> 0 | AC98: =COUNTIFS(Orders!$Z:$Z, $A98, Orders!$I:$I, "", Orders!$M:$M, "<>Cancelled") -> 0 | AD98: =SUMIFS(Orders!$U:$U, Orders!$Z:$Z, $A98, Orders!$M:$M, "Delivered") -> 39299 | AE98: =C98-AD98 -> 0 | AF98: =IFERROR(__xludf.DUMMYFUNCTION("IFERROR(TEXTJOIN("", "", TRUE, FILTER(Orders!$B$2:$B$2517, (TEXT(Orders!$D$2:$D$2517,""d-mmm"")=TEXT($A98,""d-mmm"")) * (ABS(Orders!$H$2:$H$2517 - Orders!$U$2:$U$2517) >= 1) * (Orders!$M$2:$M$2517=""Delivered""))), ""All Balanced"")"),"All Balanced") -> All Balanced | AG98: =IFERROR(__xludf.DUMMYFUNCTION("IFERROR(TEXTJOIN("", "", TRUE, FILTER(Orders!$I$2:$I$3000, (Orders!$M$2:$M$3000=""Delivered"") * (Orders!$N$2:$N$3000<>""Paid"") * (Orders!$Z$2:$Z$3000=$A98))), """")"),"") | AH98: =COUNTIFS(Orders!$M:$M, "Delivered", Orders!$N:$N, "<>Paid", Orders!$Z:$Z, $A98) -> 0
A99: 46063 | B99: =C99/Y99 -> 3467.2222 | C99: =SUMIFS(Orders!$H:$H, Orders!$Z:$Z, $A99, Orders!$M:$M, "Delivered") -> 62410 | D99: =SUMIFS(Orders!$Q:$Q, Orders!$Z:$Z, $A99, Orders!$M:$M, "Delivered") -> 22560 | E99: =D99/C99 -> 0.36148053 | F99: =C99-(C99*4/100) -> 59913.6 | G99: =C99-F99 -> 2496.4 | H99: =C99-D99 -> 39850 | I99: =IFERROR(J99/C99, 0)*100 -> 22.878737 | J99: 14278.62 | L99: =(200*W99)+C99*4% -> 7096.4 | M99: =SUMIFS(Orders!$W:$W, Orders!$Z:$Z, $A99) -> 7305.6352 | N99: =H99-J99-K99-M99 -> 18265.745 | O99: =Y99/W99*100 -> 78.26087 | P99: 7.1684118 | Q99: =J99/S99 -> 492.36621 | R99: =J99/W99 -> 620.80957 | S99: =COUNTIFS(Orders!$Z:$Z, $A99) -> 29 | T99: =COUNTIFS(Orders!$Z:$Z, $A99, Orders!$M:$M, "Cancelled") -> 6 | U99: =T99/S99 -> 0.20689655 | V99: =COUNTIFS(Orders!$Z:$Z, $A99, Orders!$M:$M, "pending") -> 0 | W99: =S99-T99 -> 23 | X99: =W99/S99 -> 0.79310345 | Y99: =COUNTIFS(Orders!$Z:$Z, $A99, Orders!$M:$M, "Delivered") -> 18 | Z99: =COUNTIFS(Orders!$Z:$Z, $A99, Orders!$M:$M, "Return Received") -> 5 | AA99: =W99-Y99-Z99-V99 -> 0 | AB99: =COUNTIFS(Orders!$Z:$Z, $A99, Orders!$M:$M, "Returned") + COUNTIFS(Orders!$Z:$Z, $A99, Orders!$M:$M, "Returned to Shipper") -> 0 | AC99: =COUNTIFS(Orders!$Z:$Z, $A99, Orders!$I:$I, "", Orders!$M:$M, "<>Cancelled") -> 0 | AD99: =SUMIFS(Orders!$U:$U, Orders!$Z:$Z, $A99, Orders!$M:$M, "Delivered") -> 62410 | AE99: =C99-AD99 -> 0 | AF99: =IFERROR(__xludf.DUMMYFUNCTION("IFERROR(TEXTJOIN("", "", TRUE, FILTER(Orders!$B$2:$B$2517, (TEXT(Orders!$D$2:$D$2517,""d-mmm"")=TEXT($A99,""d-mmm"")) * (ABS(Orders!$H$2:$H$2517 - Orders!$U$2:$U$2517) >= 1) * (Orders!$M$2:$M$2517=""Delivered""))), ""All Balanced"")"),"All Balanced") -> All Balanced | AG99: =IFERROR(__xludf.DUMMYFUNCTION("IFERROR(TEXTJOIN("", "", TRUE, FILTER(Orders!$I$2:$I$3000, (Orders!$M$2:$M$3000=""Delivered"") * (Orders!$N$2:$N$3000<>""Paid"") * (Orders!$Z$2:$Z$3000=$A99))), """")"),"") | AH99: =COUNTIFS(Orders!$M:$M, "Delivered", Orders!$N:$N, "<>Paid", Orders!$Z:$Z, $A99) -> 0
A100: 46064 | B100: =C100/Y100 -> 3072.2308 | C100: =SUMIFS(Orders!$H:$H, Orders!$Z:$Z, $A100, Orders!$M:$M, "Delivered") -> 39939 | D100: =SUMIFS(Orders!$Q:$Q, Orders!$Z:$Z, $A100, Orders!$M:$M, "Delivered") -> 13870 | E100: =D100/C100 -> 0.3472796 | F100: =C100-(C100*4/100) -> 38341.44 | G100: =C100-F100 -> 1597.56 | H100: =C100-D100 -> 26069 | I100: =IFERROR(J100/C100, 0)*100 -> 37.530759 | J100: 14989.41 | L100: =(200*W100)+C100*4% -> 4397.56 | M100: =SUMIFS(Orders!$W:$W, Orders!$Z:$Z, $A100) -> 4190.5376 | N100: =H100-J100-K100-M100 -> 6889.0524 | O100: =Y100/W100*100 -> 92.857143 | P100: 3.5213852 | Q100: =J100/S100 -> 936.83812 | R100: =J100/W100 -> 1070.6721 | S100: =COUNTIFS(Orders!$Z:$Z, $A100) -> 16 | T100: =COUNTIFS(Orders!$Z:$Z, $A100, Orders!$M:$M, "Cancelled") -> 2 | U100: =T100/S100 -> 0.125 | V100: =COUNTIFS(Orders!$Z:$Z, $A100, Orders!$M:$M, "pending") -> 0 | W100: =S100-T100 -> 14 | X100: =W100/S100 -> 0.875 | Y100: =COUNTIFS(Orders!$Z:$Z, $A100, Orders!$M:$M, "Delivered") -> 13 | Z100: =COUNTIFS(Orders!$Z:$Z, $A100, Orders!$M:$M, "Return Received") -> 1 | AA100: =W100-Y100-Z100-V100 -> 0 | AB100: =COUNTIFS(Orders!$Z:$Z, $A100, Orders!$M:$M, "Returned") + COUNTIFS(Orders!$Z:$Z, $A100, Orders!$M:$M, "Returned to Shipper") -> 0 | AC100: =COUNTIFS(Orders!$Z:$Z, $A100, Orders!$I:$I, "", Orders!$M:$M, "<>Cancelled") -> 0 | AD100: =SUMIFS(Orders!$U:$U, Orders!$Z:$Z, $A100, Orders!$M:$M, "Delivered") -> 39939 | AE100: =C100-AD100 -> 0 | AF100: =IFERROR(__xludf.DUMMYFUNCTION("IFERROR(TEXTJOIN("", "", TRUE, FILTER(Orders!$B$2:$B$2517, (TEXT(Orders!$D$2:$D$2517,""d-mmm"")=TEXT($A100,""d-mmm"")) * (ABS(Orders!$H$2:$H$2517 - Orders!$U$2:$U$2517) >= 1) * (Orders!$M$2:$M$2517=""Delivered""))), ""All Balanced"")"),"All Balanced") -> All Balanced | AG100: =IFERROR(__xludf.DUMMYFUNCTION("IFERROR(TEXTJOIN("", "", TRUE, FILTER(Orders!$I$2:$I$3000, (Orders!$M$2:$M$3000=""Delivered"") * (Orders!$N$2:$N$3000<>""Paid"") * (Orders!$Z$2:$Z$3000=$A100))), """")"),"") | AH100: =COUNTIFS(Orders!$M:$M, "Delivered", Orders!$N:$N, "<>Paid", Orders!$Z:$Z, $A100) -> 0
A101: 46065 | B101: =C101/Y101 -> 3294.7059 | C101: =SUMIFS(Orders!$H:$H, Orders!$Z:$Z, $A101, Orders!$M:$M, "Delivered") -> 56010 | D101: =SUMIFS(Orders!$Q:$Q, Orders!$Z:$Z, $A101, Orders!$M:$M, "Delivered") -> 19690 | E101: =D101/C101 -> 0.35154437 | F101: =C101-(C101*4/100) -> 53769.6 | G101: =C101-F101 -> 2240.4 | H101: =C101-D101 -> 36320 | I101: =IFERROR(J101/C101, 0)*100 -> 26.286002 | J101: 14722.79 | L101: =(200*W101)+C101*4% -> 6640.4 | M101: =SUMIFS(Orders!$W:$W, Orders!$Z:$Z, $A101) -> 6398.99 | N101: =H101-J101-K101-M101 -> 15198.22 | O101: =Y101/W101*100 -> 77.272727 | P101: 5.4113199 | Q101: =J101/S101 -> 588.9116 | R101: =J101/W101 -> 669.21773 | S101: =COUNTIFS(Orders!$Z:$Z, $A101) -> 25 | T101: =COUNTIFS(Orders!$Z:$Z, $A101, Orders!$M:$M, "Cancelled") -> 3 | U101: =T101/S101 -> 0.12 | V101: =COUNTIFS(Orders!$Z:$Z, $A101, Orders!$M:$M, "pending") -> 0 | W101: =S101-T101 -> 22 | X101: =W101/S101 -> 0.88 | Y101: =COUNTIFS(Orders!$Z:$Z, $A101, Orders!$M:$M, "Delivered") -> 17 | Z101: =COUNTIFS(Orders!$Z:$Z, $A101, Orders!$M:$M, "Return Received") -> 5 | AA101: =W101-Y101-Z101-V101 -> 0 | AB101: =COUNTIFS(Orders!$Z:$Z, $A101, Orders!$M:$M, "Returned") + COUNTIFS(Orders!$Z:$Z, $A101, Orders!$M:$M, "Returned to Shipper") -> 0 | AC101: =COUNTIFS(Orders!$Z:$Z, $A101, Orders!$I:$I, "", Orders!$M:$M, "<>Cancelled") -> 0 | AD101: =SUMIFS(Orders!$U:$U, Orders!$Z:$Z, $A101, Orders!$M:$M, "Delivered") -> 56010 | AE101: =C101-AD101 -> 0 | AF101: =IFERROR(__xludf.DUMMYFUNCTION("IFERROR(TEXTJOIN("", "", TRUE, FILTER(Orders!$B$2:$B$2517, (TEXT(Orders!$D$2:$D$2517,""d-mmm"")=TEXT($A101,""d-mmm"")) * (ABS(Orders!$H$2:$H$2517 - Orders!$U$2:$U$2517) >= 1) * (Orders!$M$2:$M$2517=""Delivered""))), ""All Balanced"")"),"All Balanced") -> All Balanced | AG101: =IFERROR(__xludf.DUMMYFUNCTION("IFERROR(TEXTJOIN("", "", TRUE, FILTER(Orders!$I$2:$I$3000, (Orders!$M$2:$M$3000=""Delivered"") * (Orders!$N$2:$N$3000<>""Paid"") * (Orders!$Z$2:$Z$3000=$A101))), """")"),"") | AH101: =COUNTIFS(Orders!$M:$M, "Delivered", Orders!$N:$N, "<>Paid", Orders!$Z:$Z, $A101) -> 0
A102: 46066 | B102: =C102/Y102 -> 2723.7 | C102: =SUMIFS(Orders!$H:$H, Orders!$Z:$Z, $A102, Orders!$M:$M, "Delivered") -> 27237 | D102: =SUMIFS(Orders!$Q:$Q, Orders!$Z:$Z, $A102, Orders!$M:$M, "Delivered") -> 9470 | E102: =D102/C102 -> 0.34768881 | F102: =C102-(C102*4/100) -> 26147.52 | G102: =C102-F102 -> 1089.48 | H102: =C102-D102 -> 17767 | I102: =IFERROR(J102/C102, 0)*100 -> 56.901421 | J102: 15498.24 | L102: =(200*W102)+C102*4% -> 3689.48 | M102: =SUMIFS(Orders!$W:$W, Orders!$Z:$Z, $A102) -> 3833.2916 | N102: =H102-J102-K102-M102 -> -1564.5316 | O102: =Y102/W102*100 -> 76.923077 | P102: 2.2949314 | Q102: =J102/S102 -> 1107.0171 | R102: =J102/W102 -> 1192.1723 | S102: =COUNTIFS(Orders!$Z:$Z, $A102) -> 14 | T102: =COUNTIFS(Orders!$Z:$Z, $A102, Orders!$M:$M, "Cancelled") -> 1 | U102: =T102/S102 -> 0.071428571 | V102: =COUNTIFS(Orders!$Z:$Z, $A102, Orders!$M:$M, "pending") -> 0 | W102: =S102-T102 -> 13 | X102: =W102/S102 -> 0.92857143 | Y102: =COUNTIFS(Orders!$Z:$Z, $A102, Orders!$M:$M, "Delivered") -> 10 | Z102: =COUNTIFS(Orders!$Z:$Z, $A102, Orders!$M:$M, "Return Received") -> 3 | AA102: =W102-Y102-Z102-V102 -> 0 | AB102: =COUNTIFS(Orders!$Z:$Z, $A102, Orders!$M:$M, "Returned") + COUNTIFS(Orders!$Z:$Z, $A102, Orders!$M:$M, "Returned to Shipper") -> 0 | AC102: =COUNTIFS(Orders!$Z:$Z, $A102, Orders!$I:$I, "", Orders!$M:$M, "<>Cancelled") -> 0 | AD102: =SUMIFS(Orders!$U:$U, Orders!$Z:$Z, $A102, Orders!$M:$M, "Delivered") -> 27237 | AE102: =C102-AD102 -> 0 | AF102: =IFERROR(__xludf.DUMMYFUNCTION("IFERROR(TEXTJOIN("", "", TRUE, FILTER(Orders!$B$2:$B$2517, (TEXT(Orders!$D$2:$D$2517,""d-mmm"")=TEXT($A102,""d-mmm"")) * (ABS(Orders!$H$2:$H$2517 - Orders!$U$2:$U$2517) >= 1) * (Orders!$M$2:$M$2517=""Delivered""))), ""All Balanced"")"),"All Balanced") -> All Balanced | AG102: =IFERROR(__xludf.DUMMYFUNCTION("IFERROR(TEXTJOIN("", "", TRUE, FILTER(Orders!$I$2:$I$3000, (Orders!$M$2:$M$3000=""Delivered"") * (Orders!$N$2:$N$3000<>""Paid"") * (Orders!$Z$2:$Z$3000=$A102))), """")"),"") | AH102: =COUNTIFS(Orders!$M:$M, "Delivered", Orders!$N:$N, "<>Paid", Orders!$Z:$Z, $A102) -> 0
A103: 46067 | B103: =C103/Y103 -> 3101.2273 | C103: =SUMIFS(Orders!$H:$H, Orders!$Z:$Z, $A103, Orders!$M:$M, "Delivered") -> 68227 | D103: =SUMIFS(Orders!$Q:$Q, Orders!$Z:$Z, $A103, Orders!$M:$M, "Delivered") -> 23400 | E103: =D103/C103 -> 0.34297272 | F103: =C103-(C103*4/100) -> 65497.92 | G103: =C103-F103 -> 2729.08 | H103: =C103-D103 -> 44827 | I103: =IFERROR(J103/C103, 0)*100 -> 25.213039 | J103: 17202.1 | L103: =(200*W103)+C103*4% -> 7929.08 | M103: =SUMIFS(Orders!$W:$W, Orders!$Z:$Z, $A103) -> 8107.6096 | N103: =H103-J103-K103-M103 -> 19517.29 | O103: =Y103/W103*100 -> 84.615385 | P103: 5.8009614 | Q103: =J103/S103 -> 593.17586 | R103: =J103/W103 -> 661.61923 | S103: =COUNTIFS(Orders!$Z:$Z, $A103) -> 29 | T103: =COUNTIFS(Orders!$Z:$Z, $A103, Orders!$M:$M, "Cancelled") -> 3 | U103: =T103/S103 -> 0.10344828 | V103: =COUNTIFS(Orders!$Z:$Z, $A103, Orders!$M:$M, "pending") -> 0 | W103: =S103-T103 -> 26 | X103: =W103/S103 -> 0.89655172 | Y103: =COUNTIFS(Orders!$Z:$Z, $A103, Orders!$M:$M, "Delivered") -> 22 | Z103: =COUNTIFS(Orders!$Z:$Z, $A103, Orders!$M:$M, "Return Received") -> 4 | AA103: =W103-Y103-Z103-V103 -> 0 | AB103: =COUNTIFS(Orders!$Z:$Z, $A103, Orders!$M:$M, "Returned") + COUNTIFS(Orders!$Z:$Z, $A103, Orders!$M:$M, "Returned to Shipper") -> 0 | AC103: =COUNTIFS(Orders!$Z:$Z, $A103, Orders!$I:$I, "", Orders!$M:$M, "<>Cancelled") -> 0 | AD103: =SUMIFS(Orders!$U:$U, Orders!$Z:$Z, $A103, Orders!$M:$M, "Delivered") -> 68227 | AE103: =C103-AD103 -> 0 | AF103: =IFERROR(__xludf.DUMMYFUNCTION("IFERROR(TEXTJOIN("", "", TRUE, FILTER(Orders!$B$2:$B$2517, (TEXT(Orders!$D$2:$D$2517,""d-mmm"")=TEXT($A103,""d-mmm"")) * (ABS(Orders!$H$2:$H$2517 - Orders!$U$2:$U$2517) >= 1) * (Orders!$M$2:$M$2517=""Delivered""))), ""All Balanced"")"),"All Balanced") -> All Balanced | AG103: =IFERROR(__xludf.DUMMYFUNCTION("IFERROR(TEXTJOIN("", "", TRUE, FILTER(Orders!$I$2:$I$3000, (Orders!$M$2:$M$3000=""Delivered"") * (Orders!$N$2:$N$3000<>""Paid"") * (Orders!$Z$2:$Z$3000=$A103))), """")"),"") | AH103: =COUNTIFS(Orders!$M:$M, "Delivered", Orders!$N:$N, "<>Paid", Orders!$Z:$Z, $A103) -> 0
A104: 46068 | B104: =C104/Y104 -> 3297.125 | C104: =SUMIFS(Orders!$H:$H, Orders!$Z:$Z, $A104, Orders!$M:$M, "Delivered") -> 52754 | D104: =SUMIFS(Orders!$Q:$Q, Orders!$Z:$Z, $A104, Orders!$M:$M, "Delivered") -> 18280 | E104: =D104/C104 -> 0.34651401 | F104: =C104-(C104*4/100) -> 50643.84 | G104: =C104-F104 -> 2110.16 | H104: =C104-D104 -> 34474 | I104: =IFERROR(J104/C104, 0)*100 -> 36.884672 | J104: 19458.14 | L104: =(200*W104)+C104*4% -> 5710.16 | M104: =SUMIFS(Orders!$W:$W, Orders!$Z:$Z, $A104) -> 5334 | N104: =H104-J104-K104-M104 -> 9681.86 | O104: =Y104/W104*100 -> 88.888889 | P104: 3.3651569 | Q104: =J104/S104 -> 1024.1126 | R104: =J104/W104 -> 1081.0078 | S104: =COUNTIFS(Orders!$Z:$Z, $A104) -> 19 | T104: =COUNTIFS(Orders!$Z:$Z, $A104, Orders!$M:$M, "Cancelled") -> 1 | U104: =T104/S104 -> 0.052631579 | V104: =COUNTIFS(Orders!$Z:$Z, $A104, Orders!$M:$M, "pending") -> 0 | W104: =S104-T104 -> 18 | X104: =W104/S104 -> 0.94736842 | Y104: =COUNTIFS(Orders!$Z:$Z, $A104, Orders!$M:$M, "Delivered") -> 16 | Z104: =COUNTIFS(Orders!$Z:$Z, $A104, Orders!$M:$M, "Return Received") -> 2 | AA104: =W104-Y104-Z104-V104 -> 0 | AB104: =COUNTIFS(Orders!$Z:$Z, $A104, Orders!$M:$M, "Returned") + COUNTIFS(Orders!$Z:$Z, $A104, Orders!$M:$M, "Returned to Shipper") -> 0 | AC104: =COUNTIFS(Orders!$Z:$Z, $A104, Orders!$I:$I, "", Orders!$M:$M, "<>Cancelled") -> 0 | AD104: =SUMIFS(Orders!$U:$U, Orders!$Z:$Z, $A104, Orders!$M:$M, "Delivered") -> 52754 | AE104: =C104-AD104 -> 0 | AF104: =IFERROR(__xludf.DUMMYFUNCTION("IFERROR(TEXTJOIN("", "", TRUE, FILTER(Orders!$B$2:$B$2517, (TEXT(Orders!$D$2:$D$2517,""d-mmm"")=TEXT($A104,""d-mmm"")) * (ABS(Orders!$H$2:$H$2517 - Orders!$U$2:$U$2517) >= 1) * (Orders!$M$2:$M$2517=""Delivered""))), ""All Balanced"")"),"All Balanced") -> All Balanced | AG104: =IFERROR(__xludf.DUMMYFUNCTION("IFERROR(TEXTJOIN("", "", TRUE, FILTER(Orders!$I$2:$I$3000, (Orders!$M$2:$M$3000=""Delivered"") * (Orders!$N$2:$N$3000<>""Paid"") * (Orders!$Z$2:$Z$3000=$A104))), """")"),"") | AH104: =COUNTIFS(Orders!$M:$M, "Delivered", Orders!$N:$N, "<>Paid", Orders!$Z:$Z, $A104) -> 0
